Workbook

Sheet Simulador
A1: SIMULADOR CUT OFF | E1: ANTES | L1: DEPOIS | S1: DELTA | Z1: Efetivadas = jun/26, jul/26
E2: # Efeti | F2: Txa Apr | G2: %FPD $ | H2: %O30M2 $ | I2: %O30M3 $ | J2: %O60M6 $ | L2: # Efeti | M2: Txa Apr | N2: %FPD $ | O2: %O30M2 $ | P2: %O30M3 $ | Q2: %O60M6 $ | S2: Δ Efeti | T2: Δ $ Vl. Primeira Fatura | U2: Δ $ Saldo Mob 2 | V2: Δ $ Saldo Mob 3 | W2: Δ $ Saldo Mob 6 | Z2: FPD = mar/26, abr/26, mai/26
D3: GERAL | E3: =BS_CONSOLIDADO!D4 -> 7559 | F3: =BS_CONSOLIDADO!Q4 -> 0.17993221 | G3: =BS_CONSOLIDADO!M4 -> 0.10580333 | H3: =BS_CONSOLIDADO!N4 -> 0.086896166 | I3: =BS_CONSOLIDADO!O4 -> 0.13901439 | J3: =BS_CONSOLIDADO!P4 -> 0.20534061 | L3: =E3-(-S3) -> 7559 | M3: =IF(COUNTBLANK(L6)=1,F3,(BS_CONSOLIDADO!C4-BS_SIMULADOR!T5)/(BS_CONSOLIDADO!B4-BS_SIMULADOR!S5)) -> 0.17993221 | N3: =IF(COUNTBLANK($L6)=1,G3,(BS_CONSOLIDADO!E4-BS_SIMULADOR!V5)/(BS_CONSOLIDADO!F4-BS_SIMULADOR!W5)) -> 0.10580333 | O3: =IF(COUNTBLANK($L6)=1,H3,(BS_CONSOLIDADO!G4-BS_SIMULADOR!X5)/(BS_CONSOLIDADO!H4-BS_SIMULADOR!Y5)) -> 0.086896166 | P3: =IF(COUNTBLANK($L6)=1,I3,(BS_CONSOLIDADO!I4-BS_SIMULADOR!Z5)/(BS_CONSOLIDADO!J4-BS_SIMULADOR!AA5)) -> 0.13901439 | Q3: =IF(COUNTBLANK(L6)=1,J3,(BS_CONSOLIDADO!K4-BS_SIMULADOR!AB5)/(BS_CONSOLIDADO!L4-BS_SIMULADOR!AC5)) -> 0.20534061 | S3: =SUM(S6:S400) -> 0 | T3: =SUM(T6:T400) -> 0 | U3: =SUM(U6:U400) -> 0 | V3: =SUM(V6:V400) -> 0 | W3: =SUM(W6:W400) -> 0 | Z3: Over30M2 = mar/26, abr/26, mai/26
B4: =COUNTA(B6:B400) -> 1 | Z4: Over30M3 = fev/26, mar/26, abr/26
A5: {=_xlfn.UNIQUE(_xlfn._xlws.FILTER(bs_propostas!A:A, bs_propostas!A:A <> ""))} -> Parceiro | B5: Cut Off | D5: Parceiros Selecionados | E5: # Efeti | F5: Txa Apr | G5: %FPD $ | H5: %O30M2 $ | I5: %O30M3 $ | J5: %O60M6 $ | L5: # Efeti | M5: Txa Apr | N5: %FPD $ | O5: %O30M2 $ | P5: %O30M3 $ | Q5: %O60M6 $ | S5: Δ Efeti | T5: Δ $ Vl. Primeira Fatura | U5: Δ $ Saldo Mob 2 | V5: Δ $ Saldo Mob 3 | W5: Δ $ Saldo Mob 6 | Z5: Over60M6 = nov/25, dez/25, jan/26
A6: Parceiro 1 | D6: {=_xlfn.UNIQUE(_xlfn._xlws.FILTER(A6:A400, B6:B400 <> "", ""))} -> Parceiro 17 | E6: =IF(COUNTBLANK(D6)=1,"",_xlfn.XLOOKUP(D6,BS_CONSOLIDADO!A:A,BS_CONSOLIDADO!D:D,"")) -> 943 | F6: =IF(COUNTBLANK(D6)=1,"",_xlfn.XLOOKUP(D6,BS_CONSOLIDADO!A:A,BS_CONSOLIDADO!Q:Q,"")) -> 0.2099882 | G6: =IF(COUNTBLANK($D6)=1,"",_xlfn.XLOOKUP($D6,BS_CONSOLIDADO!$A:$A,BS_CONSOLIDADO!M:M,"")) -> 0.1082029 | H6: =IF(COUNTBLANK($D6)=1,"",_xlfn.XLOOKUP($D6,BS_CONSOLIDADO!$A:$A,BS_CONSOLIDADO!N:N,"")) -> 0.092431944 | I6: =IF(COUNTBLANK(D6)=1,"",_xlfn.XLOOKUP(D6,BS_CONSOLIDADO!A:A,BS_CONSOLIDADO!O:O,"")) -> 0.16626681 | J6: =IF(COUNTBLANK(D6)=1,"",_xlfn.XLOOKUP(D6,BS_CONSOLIDADO!A:A,BS_CONSOLIDADO!P:P,"")) -> 0.23754568 | L6: =IF(COUNTBLANK(D6)=1,"",_xlfn.XLOOKUP(D6,BS_SIMULADOR!A:A,BS_SIMULADOR!D:D,"")) -> 943 | M6: =IF(COUNTBLANK(D6)=1,"",_xlfn.XLOOKUP(D6,BS_SIMULADOR!A:A,BS_SIMULADOR!Q:Q,"")) -> 0.2099882 | N6: =IF(COUNTBLANK($D6)=1,"",_xlfn.XLOOKUP($D6,BS_SIMULADOR!$A:$A,BS_SIMULADOR!M:M,"")) -> 0.1082029 | O6: =IF(COUNTBLANK($D6)=1,"",_xlfn.XLOOKUP($D6,BS_SIMULADOR!$A:$A,BS_SIMULADOR!N:N,"")) -> 0.092431944 | P6: =IF(COUNTBLANK($D6)=1,"",_xlfn.XLOOKUP($D6,BS_SIMULADOR!$A:$A,BS_SIMULADOR!O:O,"")) -> 0.16626681 | Q6: =IF(COUNTBLANK($D6)=1,"",_xlfn.XLOOKUP($D6,BS_SIMULADOR!$A:$A,BS_SIMULADOR!P:P,"")) -> 0.23754568 | S6: =IFERROR(IF(COUNTBLANK(D6)=1,"",E6-L6)*(-1),"") -> 0 | T6: =IFERROR(IF(COUNTBLANK($D6)=1,"",(_xlfn.XLOOKUP($D6,BS_CONSOLIDADO!$A:$A,BS_CONSOLIDADO!F:F,""))-(_xlfn.XLOOKUP($D6,BS_SIMULADOR!$A:$A,BS_SIMULADOR!F:F,"")))*(-1),"") -> 0 | U6: =IFERROR(IF(COUNTBLANK($D6)=1,"",(_xlfn.XLOOKUP($D6,BS_CONSOLIDADO!$A:$A,BS_CONSOLIDADO!H:H,""))-(_xlfn.XLOOKUP($D6,BS_SIMULADOR!$A:$A,BS_SIMULADOR!H:H,"")))*(-1),"") -> 0 | V6: =IFERROR(IF(COUNTBLANK($D6)=1,"",(_xlfn.XLOOKUP($D6,BS_CONSOLIDADO!$A:$A,BS_CONSOLIDADO!J:J,""))-(_xlfn.XLOOKUP($D6,BS_SIMULADOR!$A:$A,BS_SIMULADOR!J:J,"")))*(-1),"") -> 0 | W6: =IFERROR(IF(COUNTBLANK($D6)=1,"",(_xlfn.XLOOKUP($D6,BS_CONSOLIDADO!$A:$A,BS_CONSOLIDADO!L:L,""))-(_xlfn.XLOOKUP($D6,BS_SIMULADOR!$A:$A,BS_SIMULADOR!L:L,"")))*(-1),"") -> 0
A7: Parceiro 2 | E7: =IF(COUNTBLANK(D7)=1,"",_xlfn.XLOOKUP(D7,BS_CONSOLIDADO!A:A,BS_CONSOLIDADO!D:D,"")) | F7: =IF(COUNTBLANK(D7)=1,"",_xlfn.XLOOKUP(D7,BS_CONSOLIDADO!A:A,BS_CONSOLIDADO!Q:Q,"")) | G7: =IF(COUNTBLANK($D7)=1,"",_xlfn.XLOOKUP($D7,BS_CONSOLIDADO!$A:$A,BS_CONSOLIDADO!M:M,"")) | H7: =IF(COUNTBLANK(D7)=1,"",_xlfn.XLOOKUP(D7,BS_CONSOLIDADO!A:A,BS_CONSOLIDADO!N:N,"")) | I7: =IF(COUNTBLANK(D7)=1,"",_xlfn.XLOOKUP(D7,BS_CONSOLIDADO!A:A,BS_CONSOLIDADO!O:O,"")) | J7: =IF(COUNTBLANK(D7)=1,"",_xlfn.XLOOKUP(D7,BS_CONSOLIDADO!A:A,BS_CONSOLIDADO!P:P,"")) | L7: =IF(COUNTBLANK(D7)=1,"",_xlfn.XLOOKUP(D7,BS_SIMULADOR!A:A,BS_SIMULADOR!D:D,"")) | M7: =IF(COUNTBLANK(D7)=1,"",_xlfn.XLOOKUP(D7,BS_SIMULADOR!A:A,BS_SIMULADOR!Q:Q,"")) | N7: =IF(COUNTBLANK($D7)=1,"",_xlfn.XLOOKUP($D7,BS_SIMULADOR!$A:$A,BS_SIMULADOR!M:M,"")) | O7: =IF(COUNTBLANK(D7)=1,"",_xlfn.XLOOKUP(D7,BS_SIMULADOR!A:A,BS_SIMULADOR!N:N,"")) | P7: =IF(COUNTBLANK(D7)=1,"",_xlfn.XLOOKUP(D7,BS_SIMULADOR!A:A,BS_SIMULADOR!O:O,"")) | Q7: =IF(COUNTBLANK($D7)=1,"",_xlfn.XLOOKUP($D7,BS_SIMULADOR!$A:$A,BS_SIMULADOR!P:P,"")) | S7: =IFERROR(IF(COUNTBLANK(D7)=1,"",E7-L7)*(-1),"") | T7: =IFERROR(IF(COUNTBLANK($D7)=1,"",(_xlfn.XLOOKUP($D7,BS_CONSOLIDADO!$A:$A,BS_CONSOLIDADO!F:F,""))-(_xlfn.XLOOKUP($D7,BS_SIMULADOR!$A:$A,BS_SIMULADOR!F:F,"")))*(-1),"") | U7: =IFERROR(IF(COUNTBLANK(D7)=1,"",(_xlfn.XLOOKUP(D7,BS_CONSOLIDADO!A:A,BS_CONSOLIDADO!H:H,""))-(_xlfn.XLOOKUP(D7,BS_SIMULADOR!A:A,BS_SIMULADOR!H:H,"")))*(-1),"") | V7: =IFERROR(IF(COUNTBLANK(D7)=1,"",(_xlfn.XLOOKUP(D7,BS_CONSOLIDADO!A:A,BS_CONSOLIDADO!J:J,""))-(_xlfn.XLOOKUP(D7,BS_SIMULADOR!A:A,BS_SIMULADOR!J:J,"")))*(-1),"") | W7: =IFERROR(IF(COUNTBLANK($D7)=1,"",(_xlfn.XLOOKUP($D7,BS_CONSOLIDADO!$A:$A,BS_CONSOLIDADO!L:L,""))-(_xlfn.XLOOKUP($D7,BS_SIMULADOR!$A:$A,BS_SIMULADOR!L:L,"")))*(-1),"")
A8: Parceiro 3 | E8: =IF(COUNTBLANK(D8)=1,"",_xlfn.XLOOKUP(D8,BS_CONSOLIDADO!A:A,BS_CONSOLIDADO!D:D,"")) | F8: =IF(COUNTBLANK(D8)=1,"",_xlfn.XLOOKUP(D8,BS_CONSOLIDADO!A:A,BS_CONSOLIDADO!Q:Q,"")) | G8: =IF(COUNTBLANK($D8)=1,"",_xlfn.XLOOKUP($D8,BS_CONSOLIDADO!$A:$A,BS_CONSOLIDADO!M:M,"")) | H8: =IF(COUNTBLANK(D8)=1,"",_xlfn.XLOOKUP(D8,BS_CONSOLIDADO!A:A,BS_CONSOLIDADO!N:N,"")) | I8: =IF(COUNTBLANK(D8)=1,"",_xlfn.XLOOKUP(D8,BS_CONSOLIDADO!A:A,BS_CONSOLIDADO!O:O,"")) | J8: =IF(COUNTBLANK(D8)=1,"",_xlfn.XLOOKUP(D8,BS_CONSOLIDADO!A:A,BS_CONSOLIDADO!P:P,"")) | L8: =IF(COUNTBLANK(D8)=1,"",_xlfn.XLOOKUP(D8,BS_SIMULADOR!A:A,BS_SIMULADOR!D:D,"")) | M8: =IF(COUNTBLANK(D8)=1,"",_xlfn.XLOOKUP(D8,BS_SIMULADOR!A:A,BS_SIMULADOR!Q:Q,"")) | N8: =IF(COUNTBLANK($D8)=1,"",_xlfn.XLOOKUP($D8,BS_SIMULADOR!$A:$A,BS_SIMULADOR!M:M,"")) | O8: =IF(COUNTBLANK(D8)=1,"",_xlfn.XLOOKUP(D8,BS_SIMULADOR!A:A,BS_SIMULADOR!N:N,"")) | P8: =IF(COUNTBLANK(D8)=1,"",_xlfn.XLOOKUP(D8,BS_SIMULADOR!A:A,BS_SIMULADOR!O:O,"")) | Q8: =IF(COUNTBLANK($D8)=1,"",_xlfn.XLOOKUP($D8,BS_SIMULADOR!$A:$A,BS_SIMULADOR!P:P,"")) | S8: =IFERROR(IF(COUNTBLANK(D8)=1,"",E8-L8)*(-1),"") | T8: =IFERROR(IF(COUNTBLANK($D8)=1,"",(_xlfn.XLOOKUP($D8,BS_CONSOLIDADO!$A:$A,BS_CONSOLIDADO!F:F,""))-(_xlfn.XLOOKUP($D8,BS_SIMULADOR!$A:$A,BS_SIMULADOR!F:F,"")))*(-1),"") | U8: =IFERROR(IF(COUNTBLANK(D8)=1,"",(_xlfn.XLOOKUP(D8,BS_CONSOLIDADO!A:A,BS_CONSOLIDADO!H:H,""))-(_xlfn.XLOOKUP(D8,BS_SIMULADOR!A:A,BS_SIMULADOR!H:H,"")))*(-1),"") | V8: =IFERROR(IF(COUNTBLANK(D8)=1,"",(_xlfn.XLOOKUP(D8,BS_CONSOLIDADO!A:A,BS_CONSOLIDADO!J:J,""))-(_xlfn.XLOOKUP(D8,BS_SIMULADOR!A:A,BS_SIMULADOR!J:J,"")))*(-1),"") | W8: =IFERROR(IF(COUNTBLANK($D8)=1,"",(_xlfn.XLOOKUP($D8,BS_CONSOLIDADO!$A:$A,BS_CONSOLIDADO!L:L,""))-(_xlfn.XLOOKUP($D8,BS_SIMULADOR!$A:$A,BS_SIMULADOR!L:L,"")))*(-1),"")
A9: Parceiro 4 | E9: =IF(COUNTBLANK(D9)=1,"",_xlfn.XLOOKUP(D9,BS_CONSOLIDADO!A:A,BS_CONSOLIDADO!D:D,"")) | F9: =IF(COUNTBLANK(D9)=1,"",_xlfn.XLOOKUP(D9,BS_CONSOLIDADO!A:A,BS_CONSOLIDADO!Q:Q,"")) | G9: =IF(COUNTBLANK($D9)=1,"",_xlfn.XLOOKUP($D9,BS_CONSOLIDADO!$A:$A,BS_CONSOLIDADO!M:M,"")) | H9: =IF(COUNTBLANK(D9)=1,"",_xlfn.XLOOKUP(D9,BS_CONSOLIDADO!A:A,BS_CONSOLIDADO!N:N,"")) | I9: =IF(COUNTBLANK(D9)=1,"",_xlfn.XLOOKUP(D9,BS_CONSOLIDADO!A:A,BS_CONSOLIDADO!O:O,"")) | J9: =IF(COUNTBLANK(D9)=1,"",_xlfn.XLOOKUP(D9,BS_CONSOLIDADO!A:A,BS_CONSOLIDADO!P:P,"")) | L9: =IF(COUNTBLANK(D9)=1,"",_xlfn.XLOOKUP(D9,BS_SIMULADOR!A:A,BS_SIMULADOR!D:D,"")) | M9: =IF(COUNTBLANK(D9)=1,"",_xlfn.XLOOKUP(D9,BS_SIMULADOR!A:A,BS_SIMULADOR!Q:Q,"")) | N9: =IF(COUNTBLANK($D9)=1,"",_xlfn.XLOOKUP($D9,BS_SIMULADOR!$A:$A,BS_SIMULADOR!M:M,"")) | O9: =IF(COUNTBLANK(D9)=1,"",_xlfn.XLOOKUP(D9,BS_SIMULADOR!A:A,BS_SIMULADOR!N:N,"")) | P9: =IF(COUNTBLANK(D9)=1,"",_xlfn.XLOOKUP(D9,BS_SIMULADOR!A:A,BS_SIMULADOR!O:O,"")) | Q9: =IF(COUNTBLANK($D9)=1,"",_xlfn.XLOOKUP($D9,BS_SIMULADOR!$A:$A,BS_SIMULADOR!P:P,"")) | S9: =IFERROR(IF(COUNTBLANK(D9)=1,"",E9-L9)*(-1),"") | T9: =IFERROR(IF(COUNTBLANK($D9)=1,"",(_xlfn.XLOOKUP($D9,BS_CONSOLIDADO!$A:$A,BS_CONSOLIDADO!F:F,""))-(_xlfn.XLOOKUP($D9,BS_SIMULADOR!$A:$A,BS_SIMULADOR!F:F,"")))*(-1),"") | U9: =IFERROR(IF(COUNTBLANK(D9)=1,"",(_xlfn.XLOOKUP(D9,BS_CONSOLIDADO!A:A,BS_CONSOLIDADO!H:H,""))-(_xlfn.XLOOKUP(D9,BS_SIMULADOR!A:A,BS_SIMULADOR!H:H,"")))*(-1),"") | V9: =IFERROR(IF(COUNTBLANK(D9)=1,"",(_xlfn.XLOOKUP(D9,BS_CONSOLIDADO!A:A,BS_CONSOLIDADO!J:J,""))-(_xlfn.XLOOKUP(D9,BS_SIMULADOR!A:A,BS_SIMULADOR!J:J,"")))*(-1),"") | W9: =IFERROR(IF(COUNTBLANK($D9)=1,"",(_xlfn.XLOOKUP($D9,BS_CONSOLIDADO!$A:$A,BS_CONSOLIDADO!L:L,""))-(_xlfn.XLOOKUP($D9,BS_SIMULADOR!$A:$A,BS_SIMULADOR!L:L,"")))*(-1),"")
A10: Parceiro 5 | E10: =IF(COUNTBLANK(D10)=1,"",_xlfn.XLOOKUP(D10,BS_CONSOLIDADO!A:A,BS_CONSOLIDADO!D:D,"")) | F10: =IF(COUNTBLANK(D10)=1,"",_xlfn.XLOOKUP(D10,BS_CONSOLIDADO!A:A,BS_CONSOLIDADO!Q:Q,"")) | G10: =IF(COUNTBLANK($D10)=1,"",_xlfn.XLOOKUP($D10,BS_CONSOLIDADO!$A:$A,BS_CONSOLIDADO!M:M,"")) | H10: =IF(COUNTBLANK(D10)=1,"",_xlfn.XLOOKUP(D10,BS_CONSOLIDADO!A:A,BS_CONSOLIDADO!N:N,"")) | I10: =IF(COUNTBLANK(D10)=1,"",_xlfn.XLOOKUP(D10,BS_CONSOLIDADO!A:A,BS_CONSOLIDADO!O:O,"")) | J10: =IF(COUNTBLANK(D10)=1,"",_xlfn.XLOOKUP(D10,BS_CONSOLIDADO!A:A,BS_CONSOLIDADO!P:P,"")) | L10: =IF(COUNTBLANK(D10)=1,"",_xlfn.XLOOKUP(D10,BS_SIMULADOR!A:A,BS_SIMULADOR!D:D,"")) | M10: =IF(COUNTBLANK(D10)=1,"",_xlfn.XLOOKUP(D10,BS_SIMULADOR!A:A,BS_SIMULADOR!Q:Q,"")) | N10: =IF(COUNTBLANK($D10)=1,"",_xlfn.XLOOKUP($D10,BS_SIMULADOR!$A:$A,BS_SIMULADOR!M:M,"")) | O10: =IF(COUNTBLANK(D10)=1,"",_xlfn.XLOOKUP(D10,BS_SIMULADOR!A:A,BS_SIMULADOR!N:N,"")) | P10: =IF(COUNTBLANK(D10)=1,"",_xlfn.XLOOKUP(D10,BS_SIMULADOR!A:A,BS_SIMULADOR!O:O,"")) | Q10: =IF(COUNTBLANK($D10)=1,"",_xlfn.XLOOKUP($D10,BS_SIMULADOR!$A:$A,BS_SIMULADOR!P:P,"")) | S10: =IFERROR(IF(COUNTBLANK(D10)=1,"",E10-L10)*(-1),"") | T10: =IFERROR(IF(COUNTBLANK($D10)=1,"",(_xlfn.XLOOKUP($D10,BS_CONSOLIDADO!$A:$A,BS_CONSOLIDADO!F:F,""))-(_xlfn.XLOOKUP($D10,BS_SIMULADOR!$A:$A,BS_SIMULADOR!F:F,"")))*(-1),"") | U10: =IFERROR(IF(COUNTBLANK(D10)=1,"",(_xlfn.XLOOKUP(D10,BS_CONSOLIDADO!A:A,BS_CONSOLIDADO!H:H,""))-(_xlfn.XLOOKUP(D10,BS_SIMULADOR!A:A,BS_SIMULADOR!H:H,"")))*(-1),"") | V10: =IFERROR(IF(COUNTBLANK(D10)=1,"",(_xlfn.XLOOKUP(D10,BS_CONSOLIDADO!A:A,BS_CONSOLIDADO!J:J,""))-(_xlfn.XLOOKUP(D10,BS_SIMULADOR!A:A,BS_SIMULADOR!J:J,"")))*(-1),"") | W10: =IFERROR(IF(COUNTBLANK($D10)=1,"",(_xlfn.XLOOKUP($D10,BS_CONSOLIDADO!$A:$A,BS_CONSOLIDADO!L:L,""))-(_xlfn.XLOOKUP($D10,BS_SIMULADOR!$A:$A,BS_SIMULADOR!L:L,"")))*(-1),"")
A11: Parceiro 6 | E11: =IF(COUNTBLANK(D11)=1,"",_xlfn.XLOOKUP(D11,BS_CONSOLIDADO!A:A,BS_CONSOLIDADO!D:D,"")) | F11: =IF(COUNTBLANK(D11)=1,"",_xlfn.XLOOKUP(D11,BS_CONSOLIDADO!A:A,BS_CONSOLIDADO!Q:Q,"")) | G11: =IF(COUNTBLANK($D11)=1,"",_xlfn.XLOOKUP($D11,BS_CONSOLIDADO!$A:$A,BS_CONSOLIDADO!M:M,"")) | H11: =IF(COUNTBLANK(D11)=1,"",_xlfn.XLOOKUP(D11,BS_CONSOLIDADO!A:A,BS_CONSOLIDADO!N:N,"")) | I11: =IF(COUNTBLANK(D11)=1,"",_xlfn.XLOOKUP(D11,BS_CONSOLIDADO!A:A,BS_CONSOLIDADO!O:O,"")) | J11: =IF(COUNTBLANK(D11)=1,"",_xlfn.XLOOKUP(D11,BS_CONSOLIDADO!A:A,BS_CONSOLIDADO!P:P,"")) | L11: =IF(COUNTBLANK(D11)=1,"",_xlfn.XLOOKUP(D11,BS_SIMULADOR!A:A,BS_SIMULADOR!D:D,"")) | M11: =IF(COUNTBLANK(D11)=1,"",_xlfn.XLOOKUP(D11,BS_SIMULADOR!A:A,BS_SIMULADOR!Q:Q,"")) | N11: =IF(COUNTBLANK($D11)=1,"",_xlfn.XLOOKUP($D11,BS_SIMULADOR!$A:$A,BS_SIMULADOR!M:M,"")) | O11: =IF(COUNTBLANK(D11)=1,"",_xlfn.XLOOKUP(D11,BS_SIMULADOR!A:A,BS_SIMULADOR!N:N,"")) | P11: =IF(COUNTBLANK(D11)=1,"",_xlfn.XLOOKUP(D11,BS_SIMULADOR!A:A,BS_SIMULADOR!O:O,"")) | Q11: =IF(COUNTBLANK($D11)=1,"",_xlfn.XLOOKUP($D11,BS_SIMULADOR!$A:$A,BS_SIMULADOR!P:P,"")) | S11: =IFERROR(IF(COUNTBLANK(D11)=1,"",E11-L11)*(-1),"") | T11: =IFERROR(IF(COUNTBLANK($D11)=1,"",(_xlfn.XLOOKUP($D11,BS_CONSOLIDADO!$A:$A,BS_CONSOLIDADO!F:F,""))-(_xlfn.XLOOKUP($D11,BS_SIMULADOR!$A:$A,BS_SIMULADOR!F:F,"")))*(-1),"") | U11: =IFERROR(IF(COUNTBLANK(D11)=1,"",(_xlfn.XLOOKUP(D11,BS_CONSOLIDADO!A:A,BS_CONSOLIDADO!H:H,""))-(_xlfn.XLOOKUP(D11,BS_SIMULADOR!A:A,BS_SIMULADOR!H:H,"")))*(-1),"") | V11: =IFERROR(IF(COUNTBLANK(D11)=1,"",(_xlfn.XLOOKUP(D11,BS_CONSOLIDADO!A:A,BS_CONSOLIDADO!J:J,""))-(_xlfn.XLOOKUP(D11,BS_SIMULADOR!A:A,BS_SIMULADOR!J:J,"")))*(-1),"") | W11: =IFERROR(IF(COUNTBLANK($D11)=1,"",(_xlfn.XLOOKUP($D11,BS_CONSOLIDADO!$A:$A,BS_CONSOLIDADO!L:L,""))-(_xlfn.XLOOKUP($D11,BS_SIMULADOR!$A:$A,BS_SIMULADOR!L:L,"")))*(-1),"")
A12: Parceiro 7 | E12: =IF(COUNTBLANK(D12)=1,"",_xlfn.XLOOKUP(D12,BS_CONSOLIDADO!A:A,BS_CONSOLIDADO!D:D,"")) | F12: =IF(COUNTBLANK(D12)=1,"",_xlfn.XLOOKUP(D12,BS_CONSOLIDADO!A:A,BS_CONSOLIDADO!Q:Q,"")) | G12: =IF(COUNTBLANK($D12)=1,"",_xlfn.XLOOKUP($D12,BS_CONSOLIDADO!$A:$A,BS_CONSOLIDADO!M:M,"")) | H12: =IF(COUNTBLANK(D12)=1,"",_xlfn.XLOOKUP(D12,BS_CONSOLIDADO!A:A,BS_CONSOLIDADO!N:N,"")) | I12: =IF(COUNTBLANK(D12)=1,"",_xlfn.XLOOKUP(D12,BS_CONSOLIDADO!A:A,BS_CONSOLIDADO!O:O,"")) | J12: =IF(COUNTBLANK(D12)=1,"",_xlfn.XLOOKUP(D12,BS_CONSOLIDADO!A:A,BS_CONSOLIDADO!P:P,"")) | L12: =IF(COUNTBLANK(D12)=1,"",_xlfn.XLOOKUP(D12,BS_SIMULADOR!A:A,BS_SIMULADOR!D:D,"")) | M12: =IF(COUNTBLANK(D12)=1,"",_xlfn.XLOOKUP(D12,BS_SIMULADOR!A:A,BS_SIMULADOR!Q:Q,"")) | N12: =IF(COUNTBLANK($D12)=1,"",_xlfn.XLOOKUP($D12,BS_SIMULADOR!$A:$A,BS_SIMULADOR!M:M,"")) | O12: =IF(COUNTBLANK(D12)=1,"",_xlfn.XLOOKUP(D12,BS_SIMULADOR!A:A,BS_SIMULADOR!N:N,"")) | P12: =IF(COUNTBLANK(D12)=1,"",_xlfn.XLOOKUP(D12,BS_SIMULADOR!A:A,BS_SIMULADOR!O:O,"")) | Q12: =IF(COUNTBLANK($D12)=1,"",_xlfn.XLOOKUP($D12,BS_SIMULADOR!$A:$A,BS_SIMULADOR!P:P,"")) | S12: =IFERROR(IF(COUNTBLANK(D12)=1,"",E12-L12)*(-1),"") | T12: =IFERROR(IF(COUNTBLANK($D12)=1,"",(_xlfn.XLOOKUP($D12,BS_CONSOLIDADO!$A:$A,BS_CONSOLIDADO!F:F,""))-(_xlfn.XLOOKUP($D12,BS_SIMULADOR!$A:$A,BS_SIMULADOR!F:F,"")))*(-1),"") | U12: =IFERROR(IF(COUNTBLANK(D12)=1,"",(_xlfn.XLOOKUP(D12,BS_CONSOLIDADO!A:A,BS_CONSOLIDADO!H:H,""))-(_xlfn.XLOOKUP(D12,BS_SIMULADOR!A:A,BS_SIMULADOR!H:H,"")))*(-1),"") | V12: =IFERROR(IF(COUNTBLANK(D12)=1,"",(_xlfn.XLOOKUP(D12,BS_CONSOLIDADO!A:A,BS_CONSOLIDADO!J:J,""))-(_xlfn.XLOOKUP(D12,BS_SIMULADOR!A:A,BS_SIMULADOR!J:J,"")))*(-1),"") | W12: =IFERROR(IF(COUNTBLANK($D12)=1,"",(_xlfn.XLOOKUP($D12,BS_CONSOLIDADO!$A:$A,BS_CONSOLIDADO!L:L,""))-(_xlfn.XLOOKUP($D12,BS_SIMULADOR!$A:$A,BS_SIMULADOR!L:L,"")))*(-1),"")
A13: Parceiro 8 | E13: =IF(COUNTBLANK(D13)=1,"",_xlfn.XLOOKUP(D13,BS_CONSOLIDADO!A:A,BS_CONSOLIDADO!D:D,"")) | F13: =IF(COUNTBLANK(D13)=1,"",_xlfn.XLOOKUP(D13,BS_CONSOLIDADO!A:A,BS_CONSOLIDADO!Q:Q,"")) | G13: =IF(COUNTBLANK($D13)=1,"",_xlfn.XLOOKUP($D13,BS_CONSOLIDADO!$A:$A,BS_CONSOLIDADO!M:M,"")) | H13: =IF(COUNTBLANK(D13)=1,"",_xlfn.XLOOKUP(D13,BS_CONSOLIDADO!A:A,BS_CONSOLIDADO!N:N,"")) | I13: =IF(COUNTBLANK(D13)=1,"",_xlfn.XLOOKUP(D13,BS_CONSOLIDADO!A:A,BS_CONSOLIDADO!O:O,"")) | J13: =IF(COUNTBLANK(D13)=1,"",_xlfn.XLOOKUP(D13,BS_CONSOLIDADO!A:A,BS_CONSOLIDADO!P:P,"")) | L13: =IF(COUNTBLANK(D13)=1,"",_xlfn.XLOOKUP(D13,BS_SIMULADOR!A:A,BS_SIMULADOR!D:D,"")) | M13: =IF(COUNTBLANK(D13)=1,"",_xlfn.XLOOKUP(D13,BS_SIMULADOR!A:A,BS_SIMULADOR!Q:Q,"")) | N13: =IF(COUNTBLANK($D13)=1,"",_xlfn.XLOOKUP($D13,BS_SIMULADOR!$A:$A,BS_SIMULADOR!M:M,"")) | O13: =IF(COUNTBLANK(D13)=1,"",_xlfn.XLOOKUP(D13,BS_SIMULADOR!A:A,BS_SIMULADOR!N:N,"")) | P13: =IF(COUNTBLANK(D13)=1,"",_xlfn.XLOOKUP(D13,BS_SIMULADOR!A:A,BS_SIMULADOR!O:O,"")) | Q13: =IF(COUNTBLANK($D13)=1,"",_xlfn.XLOOKUP($D13,BS_SIMULADOR!$A:$A,BS_SIMULADOR!P:P,"")) | S13: =IFERROR(IF(COUNTBLANK(D13)=1,"",E13-L13)*(-1),"") | T13: =IFERROR(IF(COUNTBLANK($D13)=1,"",(_xlfn.XLOOKUP($D13,BS_CONSOLIDADO!$A:$A,BS_CONSOLIDADO!F:F,""))-(_xlfn.XLOOKUP($D13,BS_SIMULADOR!$A:$A,BS_SIMULADOR!F:F,"")))*(-1),"") | U13: =IFERROR(IF(COUNTBLANK(D13)=1,"",(_xlfn.XLOOKUP(D13,BS_CONSOLIDADO!A:A,BS_CONSOLIDADO!H:H,""))-(_xlfn.XLOOKUP(D13,BS_SIMULADOR!A:A,BS_SIMULADOR!H:H,"")))*(-1),"") | V13: =IFERROR(IF(COUNTBLANK(D13)=1,"",(_xlfn.XLOOKUP(D13,BS_CONSOLIDADO!A:A,BS_CONSOLIDADO!J:J,""))-(_xlfn.XLOOKUP(D13,BS_SIMULADOR!A:A,BS_SIMULADOR!J:J,"")))*(-1),"") | W13: =IFERROR(IF(COUNTBLANK($D13)=1,"",(_xlfn.XLOOKUP($D13,BS_CONSOLIDADO!$A:$A,BS_CONSOLIDADO!L:L,""))-(_xlfn.XLOOKUP($D13,BS_SIMULADOR!$A:$A,BS_SIMULADOR!L:L,"")))*(-1),"")
A14: Parceiro 9 | E14: =IF(COUNTBLANK(D14)=1,"",_xlfn.XLOOKUP(D14,BS_CONSOLIDADO!A:A,BS_CONSOLIDADO!D:D,"")) | F14: =IF(COUNTBLANK(D14)=1,"",_xlfn.XLOOKUP(D14,BS_CONSOLIDADO!A:A,BS_CONSOLIDADO!Q:Q,"")) | G14: =IF(COUNTBLANK($D14)=1,"",_xlfn.XLOOKUP($D14,BS_CONSOLIDADO!$A:$A,BS_CONSOLIDADO!M:M,"")) | H14: =IF(COUNTBLANK(D14)=1,"",_xlfn.XLOOKUP(D14,BS_CONSOLIDADO!A:A,BS_CONSOLIDADO!N:N,"")) | I14: =IF(COUNTBLANK(D14)=1,"",_xlfn.XLOOKUP(D14,BS_CONSOLIDADO!A:A,BS_CONSOLIDADO!O:O,"")) | J14: =IF(COUNTBLANK(D14)=1,"",_xlfn.XLOOKUP(D14,BS_CONSOLIDADO!A:A,BS_CONSOLIDADO!P:P,"")) | L14: =IF(COUNTBLANK(D14)=1,"",_xlfn.XLOOKUP(D14,BS_SIMULADOR!A:A,BS_SIMULADOR!D:D,"")) | M14: =IF(COUNTBLANK(D14)=1,"",_xlfn.XLOOKUP(D14,BS_SIMULADOR!A:A,BS_SIMULADOR!Q:Q,"")) | N14: =IF(COUNTBLANK($D14)=1,"",_xlfn.XLOOKUP($D14,BS_SIMULADOR!$A:$A,BS_SIMULADOR!M:M,"")) | O14: =IF(COUNTBLANK(D14)=1,"",_xlfn.XLOOKUP(D14,BS_SIMULADOR!A:A,BS_SIMULADOR!N:N,"")) | P14: =IF(COUNTBLANK(D14)=1,"",_xlfn.XLOOKUP(D14,BS_SIMULADOR!A:A,BS_SIMULADOR!O:O,"")) | Q14: =IF(COUNTBLANK($D14)=1,"",_xlfn.XLOOKUP($D14,BS_SIMULADOR!$A:$A,BS_SIMULADOR!P:P,"")) | S14: =IFERROR(IF(COUNTBLANK(D14)=1,"",E14-L14)*(-1),"") | T14: =IFERROR(IF(COUNTBLANK($D14)=1,"",(_xlfn.XLOOKUP($D14,BS_CONSOLIDADO!$A:$A,BS_CONSOLIDADO!F:F,""))-(_xlfn.XLOOKUP($D14,BS_SIMULADOR!$A:$A,BS_SIMULADOR!F:F,"")))*(-1),"") | U14: =IFERROR(IF(COUNTBLANK(D14)=1,"",(_xlfn.XLOOKUP(D14,BS_CONSOLIDADO!A:A,BS_CONSOLIDADO!H:H,""))-(_xlfn.XLOOKUP(D14,BS_SIMULADOR!A:A,BS_SIMULADOR!H:H,"")))*(-1),"") | V14: =IFERROR(IF(COUNTBLANK(D14)=1,"",(_xlfn.XLOOKUP(D14,BS_CONSOLIDADO!A:A,BS_CONSOLIDADO!J:J,""))-(_xlfn.XLOOKUP(D14,BS_SIMULADOR!A:A,BS_SIMULADOR!J:J,"")))*(-1),"") | W14: =IFERROR(IF(COUNTBLANK($D14)=1,"",(_xlfn.XLOOKUP($D14,BS_CONSOLIDADO!$A:$A,BS_CONSOLIDADO!L:L,""))-(_xlfn.XLOOKUP($D14,BS_SIMULADOR!$A:$A,BS_SIMULADOR!L:L,"")))*(-1),"")
A15: Parceiro 10 | E15: =IF(COUNTBLANK(D15)=1,"",_xlfn.XLOOKUP(D15,BS_CONSOLIDADO!A:A,BS_CONSOLIDADO!D:D,"")) | F15: =IF(COUNTBLANK(D15)=1,"",_xlfn.XLOOKUP(D15,BS_CONSOLIDADO!A:A,BS_CONSOLIDADO!Q:Q,"")) | G15: =IF(COUNTBLANK($D15)=1,"",_xlfn.XLOOKUP($D15,BS_CONSOLIDADO!$A:$A,BS_CONSOLIDADO!M:M,"")) | H15: =IF(COUNTBLANK(D15)=1,"",_xlfn.XLOOKUP(D15,BS_CONSOLIDADO!A:A,BS_CONSOLIDADO!N:N,"")) | I15: =IF(COUNTBLANK(D15)=1,"",_xlfn.XLOOKUP(D15,BS_CONSOLIDADO!A:A,BS_CONSOLIDADO!O:O,"")) | J15: =IF(COUNTBLANK(D15)=1,"",_xlfn.XLOOKUP(D15,BS_CONSOLIDADO!A:A,BS_CONSOLIDADO!P:P,"")) | L15: =IF(COUNTBLANK(D15)=1,"",_xlfn.XLOOKUP(D15,BS_SIMULADOR!A:A,BS_SIMULADOR!D:D,"")) | M15: =IF(COUNTBLANK(D15)=1,"",_xlfn.XLOOKUP(D15,BS_SIMULADOR!A:A,BS_SIMULADOR!Q:Q,"")) | N15: =IF(COUNTBLANK($D15)=1,"",_xlfn.XLOOKUP($D15,BS_SIMULADOR!$A:$A,BS_SIMULADOR!M:M,"")) | O15: =IF(COUNTBLANK(D15)=1,"",_xlfn.XLOOKUP(D15,BS_SIMULADOR!A:A,BS_SIMULADOR!N:N,"")) | P15: =IF(COUNTBLANK(D15)=1,"",_xlfn.XLOOKUP(D15,BS_SIMULADOR!A:A,BS_SIMULADOR!O:O,"")) | Q15: =IF(COUNTBLANK($D15)=1,"",_xlfn.XLOOKUP($D15,BS_SIMULADOR!$A:$A,BS_SIMULADOR!P:P,"")) | S15: =IFERROR(IF(COUNTBLANK(D15)=1,"",E15-L15)*(-1),"") | T15: =IFERROR(IF(COUNTBLANK($D15)=1,"",(_xlfn.XLOOKUP($D15,BS_CONSOLIDADO!$A:$A,BS_CONSOLIDADO!F:F,""))-(_xlfn.XLOOKUP($D15,BS_SIMULADOR!$A:$A,BS_SIMULADOR!F:F,"")))*(-1),"") | U15: =IFERROR(IF(COUNTBLANK(D15)=1,"",(_xlfn.XLOOKUP(D15,BS_CONSOLIDADO!A:A,BS_CONSOLIDADO!H:H,""))-(_xlfn.XLOOKUP(D15,BS_SIMULADOR!A:A,BS_SIMULADOR!H:H,"")))*(-1),"") | V15: =IFERROR(IF(COUNTBLANK(D15)=1,"",(_xlfn.XLOOKUP(D15,BS_CONSOLIDADO!A:A,BS_CONSOLIDADO!J:J,""))-(_xlfn.XLOOKUP(D15,BS_SIMULADOR!A:A,BS_SIMULADOR!J:J,"")))*(-1),"") | W15: =IFERROR(IF(COUNTBLANK($D15)=1,"",(_xlfn.XLOOKUP($D15,BS_CONSOLIDADO!$A:$A,BS_CONSOLIDADO!L:L,""))-(_xlfn.XLOOKUP($D15,BS_SIMULADOR!$A:$A,BS_SIMULADOR!L:L,"")))*(-1),"")
A16: Parceiro 11 | E16: =IF(COUNTBLANK(D16)=1,"",_xlfn.XLOOKUP(D16,BS_CONSOLIDADO!A:A,BS_CONSOLIDADO!D:D,"")) | F16: =IF(COUNTBLANK(D16)=1,"",_xlfn.XLOOKUP(D16,BS_CONSOLIDADO!A:A,BS_CONSOLIDADO!Q:Q,"")) | G16: =IF(COUNTBLANK($D16)=1,"",_xlfn.XLOOKUP($D16,BS_CONSOLIDADO!$A:$A,BS_CONSOLIDADO!M:M,"")) | H16: =IF(COUNTBLANK(D16)=1,"",_xlfn.XLOOKUP(D16,BS_CONSOLIDADO!A:A,BS_CONSOLIDADO!N:N,"")) | I16: =IF(COUNTBLANK(D16)=1,"",_xlfn.XLOOKUP(D16,BS_CONSOLIDADO!A:A,BS_CONSOLIDADO!O:O,"")) | J16: =IF(COUNTBLANK(D16)=1,"",_xlfn.XLOOKUP(D16,BS_CONSOLIDADO!A:A,BS_CONSOLIDADO!P:P,"")) | L16: =IF(COUNTBLANK(D16)=1,"",_xlfn.XLOOKUP(D16,BS_SIMULADOR!A:A,BS_SIMULADOR!D:D,"")) | M16: =IF(COUNTBLANK(D16)=1,"",_xlfn.XLOOKUP(D16,BS_SIMULADOR!A:A,BS_SIMULADOR!Q:Q,"")) | N16: =IF(COUNTBLANK($D16)=1,"",_xlfn.XLOOKUP($D16,BS_SIMULADOR!$A:$A,BS_SIMULADOR!M:M,"")) | O16: =IF(COUNTBLANK(D16)=1,"",_xlfn.XLOOKUP(D16,BS_SIMULADOR!A:A,BS_SIMULADOR!N:N,"")) | P16: =IF(COUNTBLANK(D16)=1,"",_xlfn.XLOOKUP(D16,BS_SIMULADOR!A:A,BS_SIMULADOR!O:O,"")) | Q16: =IF(COUNTBLANK($D16)=1,"",_xlfn.XLOOKUP($D16,BS_SIMULADOR!$A:$A,BS_SIMULADOR!P:P,"")) | S16: =IFERROR(IF(COUNTBLANK(D16)=1,"",E16-L16)*(-1),"") | T16: =IFERROR(IF(COUNTBLANK($D16)=1,"",(_xlfn.XLOOKUP($D16,BS_CONSOLIDADO!$A:$A,BS_CONSOLIDADO!F:F,""))-(_xlfn.XLOOKUP($D16,BS_SIMULADOR!$A:$A,BS_SIMULADOR!F:F,"")))*(-1),"") | U16: =IFERROR(IF(COUNTBLANK(D16)=1,"",(_xlfn.XLOOKUP(D16,BS_CONSOLIDADO!A:A,BS_CONSOLIDADO!H:H,""))-(_xlfn.XLOOKUP(D16,BS_SIMULADOR!A:A,BS_SIMULADOR!H:H,"")))*(-1),"") | V16: =IFERROR(IF(COUNTBLANK(D16)=1,"",(_xlfn.XLOOKUP(D16,BS_CONSOLIDADO!A:A,BS_CONSOLIDADO!J:J,""))-(_xlfn.XLOOKUP(D16,BS_SIMULADOR!A:A,BS_SIMULADOR!J:J,"")))*(-1),"") | W16: =IFERROR(IF(COUNTBLANK($D16)=1,"",(_xlfn.XLOOKUP($D16,BS_CONSOLIDADO!$A:$A,BS_CONSOLIDADO!L:L,""))-(_xlfn.XLOOKUP($D16,BS_SIMULADOR!$A:$A,BS_SIMULADOR!L:L,"")))*(-1),"")
A17: Parceiro 12 | E17: =IF(COUNTBLANK(D17)=1,"",_xlfn.XLOOKUP(D17,BS_CONSOLIDADO!A:A,BS_CONSOLIDADO!D:D,"")) | F17: =IF(COUNTBLANK(D17)=1,"",_xlfn.XLOOKUP(D17,BS_CONSOLIDADO!A:A,BS_CONSOLIDADO!Q:Q,"")) | G17: =IF(COUNTBLANK($D17)=1,"",_xlfn.XLOOKUP($D17,BS_CONSOLIDADO!$A:$A,BS_CONSOLIDADO!M:M,"")) | H17: =IF(COUNTBLANK(D17)=1,"",_xlfn.XLOOKUP(D17,BS_CONSOLIDADO!A:A,BS_CONSOLIDADO!N:N,"")) | I17: =IF(COUNTBLANK(D17)=1,"",_xlfn.XLOOKUP(D17,BS_CONSOLIDADO!A:A,BS_CONSOLIDADO!O:O,"")) | J17: =IF(COUNTBLANK(D17)=1,"",_xlfn.XLOOKUP(D17,BS_CONSOLIDADO!A:A,BS_CONSOLIDADO!P:P,"")) | L17: =IF(COUNTBLANK(D17)=1,"",_xlfn.XLOOKUP(D17,BS_SIMULADOR!A:A,BS_SIMULADOR!D:D,"")) | M17: =IF(COUNTBLANK(D17)=1,"",_xlfn.XLOOKUP(D17,BS_SIMULADOR!A:A,BS_SIMULADOR!Q:Q,"")) | N17: =IF(COUNTBLANK($D17)=1,"",_xlfn.XLOOKUP($D17,BS_SIMULADOR!$A:$A,BS_SIMULADOR!M:M,"")) | O17: =IF(COUNTBLANK(D17)=1,"",_xlfn.XLOOKUP(D17,BS_SIMULADOR!A:A,BS_SIMULADOR!N:N,"")) | P17: =IF(COUNTBLANK(D17)=1,"",_xlfn.XLOOKUP(D17,BS_SIMULADOR!A:A,BS_SIMULADOR!O:O,"")) | Q17: =IF(COUNTBLANK($D17)=1,"",_xlfn.XLOOKUP($D17,BS_SIMULADOR!$A:$A,BS_SIMULADOR!P:P,"")) | S17: =IFERROR(IF(COUNTBLANK(D17)=1,"",E17-L17)*(-1),"") | T17: =IFERROR(IF(COUNTBLANK($D17)=1,"",(_xlfn.XLOOKUP($D17,BS_CONSOLIDADO!$A:$A,BS_CONSOLIDADO!F:F,""))-(_xlfn.XLOOKUP($D17,BS_SIMULADOR!$A:$A,BS_SIMULADOR!F:F,"")))*(-1),"") | U17: =IFERROR(IF(COUNTBLANK(D17)=1,"",(_xlfn.XLOOKUP(D17,BS_CONSOLIDADO!A:A,BS_CONSOLIDADO!H:H,""))-(_xlfn.XLOOKUP(D17,BS_SIMULADOR!A:A,BS_SIMULADOR!H:H,"")))*(-1),"") | V17: =IFERROR(IF(COUNTBLANK(D17)=1,"",(_xlfn.XLOOKUP(D17,BS_CONSOLIDADO!A:A,BS_CONSOLIDADO!J:J,""))-(_xlfn.XLOOKUP(D17,BS_SIMULADOR!A:A,BS_SIMULADOR!J:J,"")))*(-1),"") | W17: =IFERROR(IF(COUNTBLANK($D17)=1,"",(_xlfn.XLOOKUP($D17,BS_CONSOLIDADO!$A:$A,BS_CONSOLIDADO!L:L,""))-(_xlfn.XLOOKUP($D17,BS_SIMULADOR!$A:$A,BS_SIMULADOR!L:L,"")))*(-1),"")
A18: Parceiro 13 | E18: =IF(COUNTBLANK(D18)=1,"",_xlfn.XLOOKUP(D18,BS_CONSOLIDADO!A:A,BS_CONSOLIDADO!D:D,"")) | F18: =IF(COUNTBLANK(D18)=1,"",_xlfn.XLOOKUP(D18,BS_CONSOLIDADO!A:A,BS_CONSOLIDADO!Q:Q,"")) | G18: =IF(COUNTBLANK($D18)=1,"",_xlfn.XLOOKUP($D18,BS_CONSOLIDADO!$A:$A,BS_CONSOLIDADO!M:M,"")) | H18: =IF(COUNTBLANK(D18)=1,"",_xlfn.XLOOKUP(D18,BS_CONSOLIDADO!A:A,BS_CONSOLIDADO!N:N,"")) | I18: =IF(COUNTBLANK(D18)=1,"",_xlfn.XLOOKUP(D18,BS_CONSOLIDADO!A:A,BS_CONSOLIDADO!O:O,"")) | J18: =IF(COUNTBLANK(D18)=1,"",_xlfn.XLOOKUP(D18,BS_CONSOLIDADO!A:A,BS_CONSOLIDADO!P:P,"")) | L18: =IF(COUNTBLANK(D18)=1,"",_xlfn.XLOOKUP(D18,BS_SIMULADOR!A:A,BS_SIMULADOR!D:D,"")) | M18: =IF(COUNTBLANK(D18)=1,"",_xlfn.XLOOKUP(D18,BS_SIMULADOR!A:A,BS_SIMULADOR!Q:Q,"")) | N18: =IF(COUNTBLANK($D18)=1,"",_xlfn.XLOOKUP($D18,BS_SIMULADOR!$A:$A,BS_SIMULADOR!M:M,"")) | O18: =IF(COUNTBLANK(D18)=1,"",_xlfn.XLOOKUP(D18,BS_SIMULADOR!A:A,BS_SIMULADOR!N:N,"")) | P18: =IF(COUNTBLANK(D18)=1,"",_xlfn.XLOOKUP(D18,BS_SIMULADOR!A:A,BS_SIMULADOR!O:O,"")) | Q18: =IF(COUNTBLANK($D18)=1,"",_xlfn.XLOOKUP($D18,BS_SIMULADOR!$A:$A,BS_SIMULADOR!P:P,"")) | S18: =IFERROR(IF(COUNTBLANK(D18)=1,"",E18-L18)*(-1),"") | T18: =IFERROR(IF(COUNTBLANK($D18)=1,"",(_xlfn.XLOOKUP($D18,BS_CONSOLIDADO!$A:$A,BS_CONSOLIDADO!F:F,""))-(_xlfn.XLOOKUP($D18,BS_SIMULADOR!$A:$A,BS_SIMULADOR!F:F,"")))*(-1),"") | U18: =IFERROR(IF(COUNTBLANK(D18)=1,"",(_xlfn.XLOOKUP(D18,BS_CONSOLIDADO!A:A,BS_CONSOLIDADO!H:H,""))-(_xlfn.XLOOKUP(D18,BS_SIMULADOR!A:A,BS_SIMULADOR!H:H,"")))*(-1),"") | V18: =IFERROR(IF(COUNTBLANK(D18)=1,"",(_xlfn.XLOOKUP(D18,BS_CONSOLIDADO!A:A,BS_CONSOLIDADO!J:J,""))-(_xlfn.XLOOKUP(D18,BS_SIMULADOR!A:A,BS_SIMULADOR!J:J,"")))*(-1),"") | W18: =IFERROR(IF(COUNTBLANK($D18)=1,"",(_xlfn.XLOOKUP($D18,BS_CONSOLIDADO!$A:$A,BS_CONSOLIDADO!L:L,""))-(_xlfn.XLOOKUP($D18,BS_SIMULADOR!$A:$A,BS_SIMULADOR!L:L,"")))*(-1),"")
... A20: Parceiro 15 | E20: =IF(COUNTBLANK(D20)=1,"",_xlfn.XLOOKUP(D20,BS_CONSOLIDADO!A:A,BS_CONSOLIDADO!D:D,"")) | F20: =IF(COUNTBLANK(D20)=1,"",_xlfn.XLOOKUP(D20,BS_CONSOLIDADO!A:A,BS_CONSOLIDADO!Q:Q,"")) | G20: =IF(COUNTBLANK($D20)=1,"",_xlfn.XLOOKUP($D20,BS_CONSOLIDADO!$A:$A,BS_CONSOLIDADO!M:M,"")) | H20: =IF(COUNTBLANK(D20)=1,"",_xlfn.XLOOKUP(D20,BS_CONSOLIDADO!A:A,BS_CONSOLIDADO!N:N,"")) | I20: =IF(COUNTBLANK(D20)=1,"",_xlfn.XLOOKUP(D20,BS_CONSOLIDADO!A:A,BS_CONSOLIDADO!O:O,"")) | J20: =IF(COUNTBLANK(D20)=1,"",_xlfn.XLOOKUP(D20,BS_CONSOLIDADO!A:A,BS_CONSOLIDADO!P:P,"")) | L20: =IF(COUNTBLANK(D20)=1,"",_xlfn.XLOOKUP(D20,BS_SIMULADOR!A:A,BS_SIMULADOR!D:D,"")) | M20: =IF(COUNTBLANK(D20)=1,"",_xlfn.XLOOKUP(D20,BS_SIMULADOR!A:A,BS_SIMULADOR!Q:Q,"")) | N20: =IF(COUNTBLANK($D20)=1,"",_xlfn.XLOOKUP($D20,BS_SIMULADOR!$A:$A,BS_SIMULADOR!M:M,"")) | O20: =IF(COUNTBLANK(D20)=1,"",_xlfn.XLOOKUP(D20,BS_SIMULADOR!A:A,BS_SIMULADOR!N:N,"")) | P20: =IF(COUNTBLANK(D20)=1,"",_xlfn.XLOOKUP(D20,BS_SIMULADOR!A:A,BS_SIMULADOR!O:O,"")) | Q20: =IF(COUNTBLANK($D20)=1,"",_xlfn.XLOOKUP($D20,BS_SIMULADOR!$A:$A,BS_SIMULADOR!P:P,"")) | S20: =IFERROR(IF(COUNTBLANK(D20)=1,"",E20-L20)*(-1),"") | T20: =IFERROR(IF(COUNTBLANK($D20)=1,"",(_xlfn.XLOOKUP($D20,BS_CONSOLIDADO!$A:$A,BS_CONSOLIDADO!F:F,""))-(_xlfn.XLOOKUP($D20,BS_SIMULADOR!$A:$A,BS_SIMULADOR!F:F,"")))*(-1),"") | U20: =IFERROR(IF(COUNTBLANK(D20)=1,"",(_xlfn.XLOOKUP(D20,BS_CONSOLIDADO!A:A,BS_CONSOLIDADO!H:H,""))-(_xlfn.XLOOKUP(D20,BS_SIMULADOR!A:A,BS_SIMULADOR!H:H,"")))*(-1),"") | V20: =IFERROR(IF(COUNTBLANK(D20)=1,"",(_xlfn.XLOOKUP(D20,BS_CONSOLIDADO!A:A,BS_CONSOLIDADO!J:J,""))-(_xlfn.XLOOKUP(D20,BS_SIMULADOR!A:A,BS_SIMULADOR!J:J,"")))*(-1),"") | W20: =IFERROR(IF(COUNTBLANK($D20)=1,"",(_xlfn.XLOOKUP($D20,BS_CONSOLIDADO!$A:$A,BS_CONSOLIDADO!L:L,""))-(_xlfn.XLOOKUP($D20,BS_SIMULADOR!$A:$A,BS_SIMULADOR!L:L,"")))*(-1),"")
A21: Parceiro 16 | E21: =IF(COUNTBLANK(D21)=1,"",_xlfn.XLOOKUP(D21,BS_CONSOLIDADO!A:A,BS_CONSOLIDADO!D:D,"")) | F21: =IF(COUNTBLANK(D21)=1,"",_xlfn.XLOOKUP(D21,BS_CONSOLIDADO!A:A,BS_CONSOLIDADO!Q:Q,"")) | G21: =IF(COUNTBLANK($D21)=1,"",_xlfn.XLOOKUP($D21,BS_CONSOLIDADO!$A:$A,BS_CONSOLIDADO!M:M,"")) | H21: =IF(COUNTBLANK(D21)=1,"",_xlfn.XLOOKUP(D21,BS_CONSOLIDADO!A:A,BS_CONSOLIDADO!N:N,"")) | I21: =IF(COUNTBLANK(D21)=1,"",_xlfn.XLOOKUP(D21,BS_CONSOLIDADO!A:A,BS_CONSOLIDADO!O:O,"")) | J21: =IF(COUNTBLANK(D21)=1,"",_xlfn.XLOOKUP(D21,BS_CONSOLIDADO!A:A,BS_CONSOLIDADO!P:P,"")) | L21: =IF(COUNTBLANK(D21)=1,"",_xlfn.XLOOKUP(D21,BS_SIMULADOR!A:A,BS_SIMULADOR!D:D,"")) | M21: =IF(COUNTBLANK(D21)=1,"",_xlfn.XLOOKUP(D21,BS_SIMULADOR!A:A,BS_SIMULADOR!Q:Q,"")) | N21: =IF(COUNTBLANK($D21)=1,"",_xlfn.XLOOKUP($D21,BS_SIMULADOR!$A:$A,BS_SIMULADOR!M:M,"")) | O21: =IF(COUNTBLANK(D21)=1,"",_xlfn.XLOOKUP(D21,BS_SIMULADOR!A:A,BS_SIMULADOR!N:N,"")) | P21: =IF(COUNTBLANK(D21)=1,"",_xlfn.XLOOKUP(D21,BS_SIMULADOR!A:A,BS_SIMULADOR!O:O,"")) | Q21: =IF(COUNTBLANK($D21)=1,"",_xlfn.XLOOKUP($D21,BS_SIMULADOR!$A:$A,BS_SIMULADOR!P:P,"")) | S21: =IFERROR(IF(COUNTBLANK(D21)=1,"",E21-L21)*(-1),"") | T21: =IFERROR(IF(COUNTBLANK($D21)=1,"",(_xlfn.XLOOKUP($D21,BS_CONSOLIDADO!$A:$A,BS_CONSOLIDADO!F:F,""))-(_xlfn.XLOOKUP($D21,BS_SIMULADOR!$A:$A,BS_SIMULADOR!F:F,"")))*(-1),"") | V21: =IFERROR(IF(COUNTBLANK(D21)=1,"",(_xlfn.XLOOKUP(D21,BS_CONSOLIDADO!A:A,BS_CONSOLIDADO!J:J,""))-(_xlfn.XLOOKUP(D21,BS_SIMULADOR!A:A,BS_SIMULADOR!J:J,"")))*(-1),"") | W21: =IFERROR(IF(COUNTBLANK($D21)=1,"",(_xlfn.XLOOKUP($D21,BS_CONSOLIDADO!$A:$A,BS_CONSOLIDADO!L:L,""))-(_xlfn.XLOOKUP($D21,BS_SIMULADOR!$A:$A,BS_SIMULADOR!L:L,"")))*(-1),"")
A22: Parceiro 17 | B22: e1 | E22: =IF(COUNTBLANK(D22)=1,"",_xlfn.XLOOKUP(D22,BS_CONSOLIDADO!A:A,BS_CONSOLIDADO!D:D,"")) | F22: =IF(COUNTBLANK(D22)=1,"",_xlfn.XLOOKUP(D22,BS_CONSOLIDADO!A:A,BS_CONSOLIDADO!Q:Q,"")) | G22: =IF(COUNTBLANK($D22)=1,"",_xlfn.XLOOKUP($D22,BS_CONSOLIDADO!$A:$A,BS_CONSOLIDADO!M:M,"")) | H22: =IF(COUNTBLANK(D22)=1,"",_xlfn.XLOOKUP(D22,BS_CONSOLIDADO!A:A,BS_CONSOLIDADO!N:N,"")) | I22: =IF(COUNTBLANK(D22)=1,"",_xlfn.XLOOKUP(D22,BS_CONSOLIDADO!A:A,BS_CONSOLIDADO!O:O,"")) | J22: =IF(COUNTBLANK(D22)=1,"",_xlfn.XLOOKUP(D22,BS_CONSOLIDADO!A:A,BS_CONSOLIDADO!P:P,"")) | L22: =IF(COUNTBLANK(D22)=1,"",_xlfn.XLOOKUP(D22,BS_SIMULADOR!A:A,BS_SIMULADOR!D:D,"")) | M22: =IF(COUNTBLANK(D22)=1,"",_xlfn.XLOOKUP(D22,BS_SIMULADOR!A:A,BS_SIMULADOR!Q:Q,"")) | N22: =IF(COUNTBLANK($D22)=1,"",_xlfn.XLOOKUP($D22,BS_SIMULADOR!$A:$A,BS_SIMULADOR!M:M,"")) | O22: =IF(COUNTBLANK(D22)=1,"",_xlfn.XLOOKUP(D22,BS_SIMULADOR!A:A,BS_SIMULADOR!N:N,"")) | P22: =IF(COUNTBLANK(D22)=1,"",_xlfn.XLOOKUP(D22,BS_SIMULADOR!A:A,BS_SIMULADOR!O:O,"")) | Q22: =IF(COUNTBLANK($D22)=1,"",_xlfn.XLOOKUP($D22,BS_SIMULADOR!$A:$A,BS_SIMULADOR!P:P,"")) | S22: =IFERROR(IF(COUNTBLANK(D22)=1,"",E22-L22)*(-1),"") | T22: =IFERROR(IF(COUNTBLANK($D22)=1,"",(_xlfn.XLOOKUP($D22,BS_CONSOLIDADO!$A:$A,BS_CONSOLIDADO!F:F,""))-(_xlfn.XLOOKUP($D22,BS_SIMULADOR!$A:$A,BS_SIMULADOR!F:F,"")))*(-1),"") | U22: =IFERROR(IF(COUNTBLANK(D22)=1,"",(_xlfn.XLOOKUP(D22,BS_CONSOLIDADO!A:A,BS_CONSOLIDADO!H:H,""))-(_xlfn.XLOOKUP(D22,BS_SIMULADOR!A:A,BS_SIMULADOR!H:H,"")))*(-1),"") | V22: =IFERROR(IF(COUNTBLANK(D22)=1,"",(_xlfn.XLOOKUP(D22,BS_CONSOLIDADO!A:A,BS_CONSOLIDADO!J:J,""))-(_xlfn.XLOOKUP(D22,BS_SIMULADOR!A:A,BS_SIMULADOR!J:J,"")))*(-1),"") | W22: =IFERROR(IF(COUNTBLANK($D22)=1,"",(_xlfn.XLOOKUP($D22,BS_CONSOLIDADO!$A:$A,BS_CONSOLIDADO!L:L,""))-(_xlfn.XLOOKUP($D22,BS_SIMULADOR!$A:$A,BS_SIMULADOR!L:L,"")))*(-1),"")
A23: Parceiro 18 | E23: =IF(COUNTBLANK(D23)=1,"",_xlfn.XLOOKUP(D23,BS_CONSOLIDADO!A:A,BS_CONSOLIDADO!D:D,"")) | F23: =IF(COUNTBLANK(D23)=1,"",_xlfn.XLOOKUP(D23,BS_CONSOLIDADO!A:A,BS_CONSOLIDADO!Q:Q,"")) | G23: =IF(COUNTBLANK($D23)=1,"",_xlfn.XLOOKUP($D23,BS_CONSOLIDADO!$A:$A,BS_CONSOLIDADO!M:M,"")) | H23: =IF(COUNTBLANK(D23)=1,"",_xlfn.XLOOKUP(D23,BS_CONSOLIDADO!A:A,BS_CONSOLIDADO!N:N,"")) | I23: =IF(COUNTBLANK(D23)=1,"",_xlfn.XLOOKUP(D23,BS_CONSOLIDADO!A:A,BS_CONSOLIDADO!O:O,"")) | J23: =IF(COUNTBLANK(D23)=1,"",_xlfn.XLOOKUP(D23,BS_CONSOLIDADO!A:A,BS_CONSOLIDADO!P:P,"")) | L23: =IF(COUNTBLANK(D23)=1,"",_xlfn.XLOOKUP(D23,BS_SIMULADOR!A:A,BS_SIMULADOR!D:D,"")) | M23: =IF(COUNTBLANK(D23)=1,"",_xlfn.XLOOKUP(D23,BS_SIMULADOR!A:A,BS_SIMULADOR!Q:Q,"")) | N23: =IF(COUNTBLANK($D23)=1,"",_xlfn.XLOOKUP($D23,BS_SIMULADOR!$A:$A,BS_SIMULADOR!M:M,"")) | O23: =IF(COUNTBLANK(D23)=1,"",_xlfn.XLOOKUP(D23,BS_SIMULADOR!A:A,BS_SIMULADOR!N:N,"")) | P23: =IF(COUNTBLANK(D23)=1,"",_xlfn.XLOOKUP(D23,BS_SIMULADOR!A:A,BS_SIMULADOR!O:O,"")) | Q23: =IF(COUNTBLANK($D23)=1,"",_xlfn.XLOOKUP($D23,BS_SIMULADOR!$A:$A,BS_SIMULADOR!P:P,"")) | S23: =IFERROR(IF(COUNTBLANK(D23)=1,"",E23-L23)*(-1),"") | T23: =IFERROR(IF(COUNTBLANK($D23)=1,"",(_xlfn.XLOOKUP($D23,BS_CONSOLIDADO!$A:$A,BS_CONSOLIDADO!F:F,""))-(_xlfn.XLOOKUP($D23,BS_SIMULADOR!$A:$A,BS_SIMULADOR!F:F,"")))*(-1),"") | U23: =IFERROR(IF(COUNTBLANK(D23)=1,"",(_xlfn.XLOOKUP(D23,BS_CONSOLIDADO!A:A,BS_CONSOLIDADO!H:H,""))-(_xlfn.XLOOKUP(D23,BS_SIMULADOR!A:A,BS_SIMULADOR!H:H,"")))*(-1),"") | V23: =IFERROR(IF(COUNTBLANK(D23)=1,"",(_xlfn.XLOOKUP(D23,BS_CONSOLIDADO!A:A,BS_CONSOLIDADO!J:J,""))-(_xlfn.XLOOKUP(D23,BS_SIMULADOR!A:A,BS_SIMULADOR!J:J,"")))*(-1),"") | W23: =IFERROR(IF(COUNTBLANK($D23)=1,"",(_xlfn.XLOOKUP($D23,BS_CONSOLIDADO!$A:$A,BS_CONSOLIDADO!L:L,""))-(_xlfn.XLOOKUP($D23,BS_SIMULADOR!$A:$A,BS_SIMULADOR!L:L,"")))*(-1),"")
A24: Parceiro 19 | E24: =IF(COUNTBLANK(D24)=1,"",_xlfn.XLOOKUP(D24,BS_CONSOLIDADO!A:A,BS_CONSOLIDADO!D:D,"")) | F24: =IF(COUNTBLANK(D24)=1,"",_xlfn.XLOOKUP(D24,BS_CONSOLIDADO!A:A,BS_CONSOLIDADO!Q:Q,"")) | G24: =IF(COUNTBLANK($D24)=1,"",_xlfn.XLOOKUP($D24,BS_CONSOLIDADO!$A:$A,BS_CONSOLIDADO!M:M,"")) | H24: =IF(COUNTBLANK(D24)=1,"",_xlfn.XLOOKUP(D24,BS_CONSOLIDADO!A:A,BS_CONSOLIDADO!N:N,"")) | I24: =IF(COUNTBLANK(D24)=1,"",_xlfn.XLOOKUP(D24,BS_CONSOLIDADO!A:A,BS_CONSOLIDADO!O:O,"")) | J24: =IF(COUNTBLANK(D24)=1,"",_xlfn.XLOOKUP(D24,BS_CONSOLIDADO!A:A,BS_CONSOLIDADO!P:P,"")) | L24: =IF(COUNTBLANK(D24)=1,"",_xlfn.XLOOKUP(D24,BS_SIMULADOR!A:A,BS_SIMULADOR!D:D,"")) | M24: =IF(COUNTBLANK(D24)=1,"",_xlfn.XLOOKUP(D24,BS_SIMULADOR!A:A,BS_SIMULADOR!Q:Q,"")) | N24: =IF(COUNTBLANK($D24)=1,"",_xlfn.XLOOKUP($D24,BS_SIMULADOR!$A:$A,BS_SIMULADOR!M:M,"")) | O24: =IF(COUNTBLANK(D24)=1,"",_xlfn.XLOOKUP(D24,BS_SIMULADOR!A:A,BS_SIMULADOR!N:N,"")) | P24: =IF(COUNTBLANK(D24)=1,"",_xlfn.XLOOKUP(D24,BS_SIMULADOR!A:A,BS_SIMULADOR!O:O,"")) | Q24: =IF(COUNTBLANK($D24)=1,"",_xlfn.XLOOKUP($D24,BS_SIMULADOR!$A:$A,BS_SIMULADOR!P:P,"")) | S24: =IFERROR(IF(COUNTBLANK(D24)=1,"",E24-L24)*(-1),"") | T24: =IFERROR(IF(COUNTBLANK($D24)=1,"",(_xlfn.XLOOKUP($D24,BS_CONSOLIDADO!$A:$A,BS_CONSOLIDADO!F:F,""))-(_xlfn.XLOOKUP($D24,BS_SIMULADOR!$A:$A,BS_SIMULADOR!F:F,"")))*(-1),"") | U24: =IFERROR(IF(COUNTBLANK(D24)=1,"",(_xlfn.XLOOKUP(D24,BS_CONSOLIDADO!A:A,BS_CONSOLIDADO!H:H,""))-(_xlfn.XLOOKUP(D24,BS_SIMULADOR!A:A,BS_SIMULADOR!H:H,"")))*(-1),"") | V24: =IFERROR(IF(COUNTBLANK(D24)=1,"",(_xlfn.XLOOKUP(D24,BS_CONSOLIDADO!A:A,BS_CONSOLIDADO!J:J,""))-(_xlfn.XLOOKUP(D24,BS_SIMULADOR!A:A,BS_SIMULADOR!J:J,"")))*(-1),"") | W24: =IFERROR(IF(COUNTBLANK($D24)=1,"",(_xlfn.XLOOKUP($D24,BS_CONSOLIDADO!$A:$A,BS_CONSOLIDADO!L:L,""))-(_xlfn.XLOOKUP($D24,BS_SIMULADOR!$A:$A,BS_SIMULADOR!L:L,"")))*(-1),"")
A25: Parceiro 20 | E25: =IF(COUNTBLANK(D25)=1,"",_xlfn.XLOOKUP(D25,BS_CONSOLIDADO!A:A,BS_CONSOLIDADO!D:D,"")) | F25: =IF(COUNTBLANK(D25)=1,"",_xlfn.XLOOKUP(D25,BS_CONSOLIDADO!A:A,BS_CONSOLIDADO!Q:Q,"")) | G25: =IF(COUNTBLANK($D25)=1,"",_xlfn.XLOOKUP($D25,BS_CONSOLIDADO!$A:$A,BS_CONSOLIDADO!M:M,"")) | H25: =IF(COUNTBLANK(D25)=1,"",_xlfn.XLOOKUP(D25,BS_CONSOLIDADO!A:A,BS_CONSOLIDADO!N:N,"")) | I25: =IF(COUNTBLANK(D25)=1,"",_xlfn.XLOOKUP(D25,BS_CONSOLIDADO!A:A,BS_CONSOLIDADO!O:O,"")) | J25: =IF(COUNTBLANK(D25)=1,"",_xlfn.XLOOKUP(D25,BS_CONSOLIDADO!A:A,BS_CONSOLIDADO!P:P,"")) | L25: =IF(COUNTBLANK(D25)=1,"",_xlfn.XLOOKUP(D25,BS_SIMULADOR!A:A,BS_SIMULADOR!D:D,"")) | M25: =IF(COUNTBLANK(D25)=1,"",_xlfn.XLOOKUP(D25,BS_SIMULADOR!A:A,BS_SIMULADOR!Q:Q,"")) | N25: =IF(COUNTBLANK($D25)=1,"",_xlfn.XLOOKUP($D25,BS_SIMULADOR!$A:$A,BS_SIMULADOR!M:M,"")) | O25: =IF(COUNTBLANK(D25)=1,"",_xlfn.XLOOKUP(D25,BS_SIMULADOR!A:A,BS_SIMULADOR!N:N,"")) | P25: =IF(COUNTBLANK(D25)=1,"",_xlfn.XLOOKUP(D25,BS_SIMULADOR!A:A,BS_SIMULADOR!O:O,"")) | Q25: =IF(COUNTBLANK($D25)=1,"",_xlfn.XLOOKUP($D25,BS_SIMULADOR!$A:$A,BS_SIMULADOR!P:P,"")) | S25: =IFERROR(IF(COUNTBLANK(D25)=1,"",E25-L25)*(-1),"") | T25: =IFERROR(IF(COUNTBLANK($D25)=1,"",(_xlfn.XLOOKUP($D25,BS_CONSOLIDADO!$A:$A,BS_CONSOLIDADO!F:F,""))-(_xlfn.XLOOKUP($D25,BS_SIMULADOR!$A:$A,BS_SIMULADOR!F:F,"")))*(-1),"") | U25: =IFERROR(IF(COUNTBLANK(D25)=1,"",(_xlfn.XLOOKUP(D25,BS_CONSOLIDADO!A:A,BS_CONSOLIDADO!H:H,""))-(_xlfn.XLOOKUP(D25,BS_SIMULADOR!A:A,BS_SIMULADOR!H:H,"")))*(-1),"") | V25: =IFERROR(IF(COUNTBLANK(D25)=1,"",(_xlfn.XLOOKUP(D25,BS_CONSOLIDADO!A:A,BS_CONSOLIDADO!J:J,""))-(_xlfn.XLOOKUP(D25,BS_SIMULADOR!A:A,BS_SIMULADOR!J:J,"")))*(-1),"") | W25: =IFERROR(IF(COUNTBLANK($D25)=1,"",(_xlfn.XLOOKUP($D25,BS_CONSOLIDADO!$A:$A,BS_CONSOLIDADO!L:L,""))-(_xlfn.XLOOKUP($D25,BS_SIMULADOR!$A:$A,BS_SIMULADOR!L:L,"")))*(-1),"")
E26: =IF(COUNTBLANK(D26)=1,"",_xlfn.XLOOKUP(D26,BS_CONSOLIDADO!A:A,BS_CONSOLIDADO!D:D,"")) | F26: =IF(COUNTBLANK(D26)=1,"",_xlfn.XLOOKUP(D26,BS_CONSOLIDADO!A:A,BS_CONSOLIDADO!Q:Q,"")) | G26: =IF(COUNTBLANK($D26)=1,"",_xlfn.XLOOKUP($D26,BS_CONSOLIDADO!$A:$A,BS_CONSOLIDADO!M:M,"")) | H26: =IF(COUNTBLANK(D26)=1,"",_xlfn.XLOOKUP(D26,BS_CONSOLIDADO!A:A,BS_CONSOLIDADO!N:N,"")) | I26: =IF(COUNTBLANK(D26)=1,"",_xlfn.XLOOKUP(D26,BS_CONSOLIDADO!A:A,BS_CONSOLIDADO!O:O,"")) | J26: =IF(COUNTBLANK(D26)=1,"",_xlfn.XLOOKUP(D26,BS_CONSOLIDADO!A:A,BS_CONSOLIDADO!P:P,"")) | L26: =IF(COUNTBLANK(D26)=1,"",_xlfn.XLOOKUP(D26,BS_SIMULADOR!A:A,BS_SIMULADOR!D:D,"")) | M26: =IF(COUNTBLANK(D26)=1,"",_xlfn.XLOOKUP(D26,BS_SIMULADOR!A:A,BS_SIMULADOR!Q:Q,"")) | N26: =IF(COUNTBLANK($D26)=1,"",_xlfn.XLOOKUP($D26,BS_SIMULADOR!$A:$A,BS_SIMULADOR!M:M,"")) | O26: =IF(COUNTBLANK(D26)=1,"",_xlfn.XLOOKUP(D26,BS_SIMULADOR!A:A,BS_SIMULADOR!N:N,"")) | P26: =IF(COUNTBLANK(D26)=1,"",_xlfn.XLOOKUP(D26,BS_SIMULADOR!A:A,BS_SIMULADOR!O:O,"")) | Q26: =IF(COUNTBLANK($D26)=1,"",_xlfn.XLOOKUP($D26,BS_SIMULADOR!$A:$A,BS_SIMULADOR!P:P,"")) | S26: =IFERROR(IF(COUNTBLANK(D26)=1,"",E26-L26)*(-1),"") | T26: =IFERROR(IF(COUNTBLANK($D26)=1,"",(_xlfn.XLOOKUP($D26,BS_CONSOLIDADO!$A:$A,BS_CONSOLIDADO!F:F,""))-(_xlfn.XLOOKUP($D26,BS_SIMULADOR!$A:$A,BS_SIMULADOR!F:F,"")))*(-1),"") | U26: =IFERROR(IF(COUNTBLANK(D26)=1,"",(_xlfn.XLOOKUP(D26,BS_CONSOLIDADO!A:A,BS_CONSOLIDADO!H:H,""))-(_xlfn.XLOOKUP(D26,BS_SIMULADOR!A:A,BS_SIMULADOR!H:H,"")))*(-1),"") | V26: =IFERROR(IF(COUNTBLANK(D26)=1,"",(_xlfn.XLOOKUP(D26,BS_CONSOLIDADO!A:A,BS_CONSOLIDADO!J:J,""))-(_xlfn.XLOOKUP(D26,BS_SIMULADOR!A:A,BS_SIMULADOR!J:J,"")))*(-1),"") | W26: =IFERROR(IF(COUNTBLANK($D26)=1,"",(_xlfn.XLOOKUP($D26,BS_CONSOLIDADO!$A:$A,BS_CONSOLIDADO!L:L,""))-(_xlfn.XLOOKUP($D26,BS_SIMULADOR!$A:$A,BS_SIMULADOR!L:L,"")))*(-1),"")
E27: =IF(COUNTBLANK(D27)=1,"",_xlfn.XLOOKUP(D27,BS_CONSOLIDADO!A:A,BS_CONSOLIDADO!D:D,"")) | F27: =IF(COUNTBLANK(D27)=1,"",_xlfn.XLOOKUP(D27,BS_CONSOLIDADO!A:A,BS_CONSOLIDADO!Q:Q,"")) | G27: =IF(COUNTBLANK($D27)=1,"",_xlfn.XLOOKUP($D27,BS_CONSOLIDADO!$A:$A,BS_CONSOLIDADO!M:M,"")) | H27: =IF(COUNTBLANK(D27)=1,"",_xlfn.XLOOKUP(D27,BS_CONSOLIDADO!A:A,BS_CONSOLIDADO!N:N,"")) | I27: =IF(COUNTBLANK(D27)=1,"",_xlfn.XLOOKUP(D27,BS_CONSOLIDADO!A:A,BS_CONSOLIDADO!O:O,"")) | J27: =IF(COUNTBLANK(D27)=1,"",_xlfn.XLOOKUP(D27,BS_CONSOLIDADO!A:A,BS_CONSOLIDADO!P:P,"")) | L27: =IF(COUNTBLANK(D27)=1,"",_xlfn.XLOOKUP(D27,BS_SIMULADOR!A:A,BS_SIMULADOR!D:D,"")) | M27: =IF(COUNTBLANK(D27)=1,"",_xlfn.XLOOKUP(D27,BS_SIMULADOR!A:A,BS_SIMULADOR!Q:Q,"")) | N27: =IF(COUNTBLANK($D27)=1,"",_xlfn.XLOOKUP($D27,BS_SIMULADOR!$A:$A,BS_SIMULADOR!M:M,"")) | O27: =IF(COUNTBLANK(D27)=1,"",_xlfn.XLOOKUP(D27,BS_SIMULADOR!A:A,BS_SIMULADOR!N:N,"")) | P27: =IF(COUNTBLANK(D27)=1,"",_xlfn.XLOOKUP(D27,BS_SIMULADOR!A:A,BS_SIMULADOR!O:O,"")) | Q27: =IF(COUNTBLANK($D27)=1,"",_xlfn.XLOOKUP($D27,BS_SIMULADOR!$A:$A,BS_SIMULADOR!P:P,"")) | S27: =IFERROR(IF(COUNTBLANK(D27)=1,"",E27-L27)*(-1),"") | T27: =IFERROR(IF(COUNTBLANK($D27)=1,"",(_xlfn.XLOOKUP($D27,BS_CONSOLIDADO!$A:$A,BS_CONSOLIDADO!F:F,""))-(_xlfn.XLOOKUP($D27,BS_SIMULADOR!$A:$A,BS_SIMULADOR!F:F,"")))*(-1),"") | U27: =IFERROR(IF(COUNTBLANK(D27)=1,"",(_xlfn.XLOOKUP(D27,BS_CONSOLIDADO!A:A,BS_CONSOLIDADO!H:H,""))-(_xlfn.XLOOKUP(D27,BS_SIMULADOR!A:A,BS_SIMULADOR!H:H,"")))*(-1),"") | V27: =IFERROR(IF(COUNTBLANK(D27)=1,"",(_xlfn.XLOOKUP(D27,BS_CONSOLIDADO!A:A,BS_CONSOLIDADO!J:J,""))-(_xlfn.XLOOKUP(D27,BS_SIMULADOR!A:A,BS_SIMULADOR!J:J,"")))*(-1),"") | W27: =IFERROR(IF(COUNTBLANK($D27)=1,"",(_xlfn.XLOOKUP($D27,BS_CONSOLIDADO!$A:$A,BS_CONSOLIDADO!L:L,""))-(_xlfn.XLOOKUP($D27,BS_SIMULADOR!$A:$A,BS_SIMULADOR!L:L,"")))*(-1),"")
E28: =IF(COUNTBLANK(D28)=1,"",_xlfn.XLOOKUP(D28,BS_CONSOLIDADO!A:A,BS_CONSOLIDADO!D:D,"")) | F28: =IF(COUNTBLANK(D28)=1,"",_xlfn.XLOOKUP(D28,BS_CONSOLIDADO!A:A,BS_CONSOLIDADO!Q:Q,"")) | G28: =IF(COUNTBLANK($D28)=1,"",_xlfn.XLOOKUP($D28,BS_CONSOLIDADO!$A:$A,BS_CONSOLIDADO!M:M,"")) | H28: =IF(COUNTBLANK(D28)=1,"",_xlfn.XLOOKUP(D28,BS_CONSOLIDADO!A:A,BS_CONSOLIDADO!N:N,"")) | I28: =IF(COUNTBLANK(D28)=1,"",_xlfn.XLOOKUP(D28,BS_CONSOLIDADO!A:A,BS_CONSOLIDADO!O:O,"")) | J28: =IF(COUNTBLANK(D28)=1,"",_xlfn.XLOOKUP(D28,BS_CONSOLIDADO!A:A,BS_CONSOLIDADO!P:P,"")) | L28: =IF(COUNTBLANK(D28)=1,"",_xlfn.XLOOKUP(D28,BS_SIMULADOR!A:A,BS_SIMULADOR!D:D,"")) | M28: =IF(COUNTBLANK(D28)=1,"",_xlfn.XLOOKUP(D28,BS_SIMULADOR!A:A,BS_SIMULADOR!Q:Q,"")) | N28: =IF(COUNTBLANK($D28)=1,"",_xlfn.XLOOKUP($D28,BS_SIMULADOR!$A:$A,BS_SIMULADOR!M:M,"")) | O28: =IF(COUNTBLANK(D28)=1,"",_xlfn.XLOOKUP(D28,BS_SIMULADOR!A:A,BS_SIMULADOR!N:N,"")) | P28: =IF(COUNTBLANK(D28)=1,"",_xlfn.XLOOKUP(D28,BS_SIMULADOR!A:A,BS_SIMULADOR!O:O,"")) | Q28: =IF(COUNTBLANK($D28)=1,"",_xlfn.XLOOKUP($D28,BS_SIMULADOR!$A:$A,BS_SIMULADOR!P:P,"")) | S28: =IFERROR(IF(COUNTBLANK(D28)=1,"",E28-L28)*(-1),"") | T28: =IFERROR(IF(COUNTBLANK($D28)=1,"",(_xlfn.XLOOKUP($D28,BS_CONSOLIDADO!$A:$A,BS_CONSOLIDADO!F:F,""))-(_xlfn.XLOOKUP($D28,BS_SIMULADOR!$A:$A,BS_SIMULADOR!F:F,"")))*(-1),"") | U28: =IFERROR(IF(COUNTBLANK(D28)=1,"",(_xlfn.XLOOKUP(D28,BS_CONSOLIDADO!A:A,BS_CONSOLIDADO!H:H,""))-(_xlfn.XLOOKUP(D28,BS_SIMULADOR!A:A,BS_SIMULADOR!H:H,"")))*(-1),"") | V28: =IFERROR(IF(COUNTBLANK(D28)=1,"",(_xlfn.XLOOKUP(D28,BS_CONSOLIDADO!A:A,BS_CONSOLIDADO!J:J,""))-(_xlfn.XLOOKUP(D28,BS_SIMULADOR!A:A,BS_SIMULADOR!J:J,"")))*(-1),"") | W28: =IFERROR(IF(COUNTBLANK($D28)=1,"",(_xlfn.XLOOKUP($D28,BS_CONSOLIDADO!$A:$A,BS_CONSOLIDADO!L:L,""))-(_xlfn.XLOOKUP($D28,BS_SIMULADOR!$A:$A,BS_SIMULADOR!L:L,"")))*(-1),"")
E29: =IF(COUNTBLANK(D29)=1,"",_xlfn.XLOOKUP(D29,BS_CONSOLIDADO!A:A,BS_CONSOLIDADO!D:D,"")) | F29: =IF(COUNTBLANK(D29)=1,"",_xlfn.XLOOKUP(D29,BS_CONSOLIDADO!A:A,BS_CONSOLIDADO!Q:Q,"")) | G29: =IF(COUNTBLANK($D29)=1,"",_xlfn.XLOOKUP($D29,BS_CONSOLIDADO!$A:$A,BS_CONSOLIDADO!M:M,"")) | H29: =IF(COUNTBLANK(D29)=1,"",_xlfn.XLOOKUP(D29,BS_CONSOLIDADO!A:A,BS_CONSOLIDADO!N:N,"")) | I29: =IF(COUNTBLANK(D29)=1,"",_xlfn.XLOOKUP(D29,BS_CONSOLIDADO!A:A,BS_CONSOLIDADO!O:O,"")) | J29: =IF(COUNTBLANK(D29)=1,"",_xlfn.XLOOKUP(D29,BS_CONSOLIDADO!A:A,BS_CONSOLIDADO!P:P,"")) | L29: =IF(COUNTBLANK(D29)=1,"",_xlfn.XLOOKUP(D29,BS_SIMULADOR!A:A,BS_SIMULADOR!D:D,"")) | M29: =IF(COUNTBLANK(D29)=1,"",_xlfn.XLOOKUP(D29,BS_SIMULADOR!A:A,BS_SIMULADOR!Q:Q,"")) | N29: =IF(COUNTBLANK($D29)=1,"",_xlfn.XLOOKUP($D29,BS_SIMULADOR!$A:$A,BS_SIMULADOR!M:M,"")) | O29: =IF(COUNTBLANK(D29)=1,"",_xlfn.XLOOKUP(D29,BS_SIMULADOR!A:A,BS_SIMULADOR!N:N,"")) | P29: =IF(COUNTBLANK(D29)=1,"",_xlfn.XLOOKUP(D29,BS_SIMULADOR!A:A,BS_SIMULADOR!O:O,"")) | Q29: =IF(COUNTBLANK($D29)=1,"",_xlfn.XLOOKUP($D29,BS_SIMULADOR!$A:$A,BS_SIMULADOR!P:P,"")) | S29: =IFERROR(IF(COUNTBLANK(D29)=1,"",E29-L29)*(-1),"") | T29: =IFERROR(IF(COUNTBLANK($D29)=1,"",(_xlfn.XLOOKUP($D29,BS_CONSOLIDADO!$A:$A,BS_CONSOLIDADO!F:F,""))-(_xlfn.XLOOKUP($D29,BS_SIMULADOR!$A:$A,BS_SIMULADOR!F:F,"")))*(-1),"") | U29: =IFERROR(IF(COUNTBLANK(D29)=1,"",(_xlfn.XLOOKUP(D29,BS_CONSOLIDADO!A:A,BS_CONSOLIDADO!H:H,""))-(_xlfn.XLOOKUP(D29,BS_SIMULADOR!A:A,BS_SIMULADOR!H:H,"")))*(-1),"") | V29: =IFERROR(IF(COUNTBLANK(D29)=1,"",(_xlfn.XLOOKUP(D29,BS_CONSOLIDADO!A:A,BS_CONSOLIDADO!J:J,""))-(_xlfn.XLOOKUP(D29,BS_SIMULADOR!A:A,BS_SIMULADOR!J:J,"")))*(-1),"") | W29: =IFERROR(IF(COUNTBLANK($D29)=1,"",(_xlfn.XLOOKUP($D29,BS_CONSOLIDADO!$A:$A,BS_CONSOLIDADO!L:L,""))-(_xlfn.XLOOKUP($D29,BS_SIMULADOR!$A:$A,BS_SIMULADOR!L:L,"")))*(-1),"")
E30: =IF(COUNTBLANK(D30)=1,"",_xlfn.XLOOKUP(D30,BS_CONSOLIDADO!A:A,BS_CONSOLIDADO!D:D,"")) | F30: =IF(COUNTBLANK(D30)=1,"",_xlfn.XLOOKUP(D30,BS_CONSOLIDADO!A:A,BS_CONSOLIDADO!Q:Q,"")) | G30: =IF(COUNTBLANK($D30)=1,"",_xlfn.XLOOKUP($D30,BS_CONSOLIDADO!$A:$A,BS_CONSOLIDADO!M:M,"")) | H30: =IF(COUNTBLANK(D30)=1,"",_xlfn.XLOOKUP(D30,BS_CONSOLIDADO!A:A,BS_CONSOLIDADO!N:N,"")) | I30: =IF(COUNTBLANK(D30)=1,"",_xlfn.XLOOKUP(D30,BS_CONSOLIDADO!A:A,BS_CONSOLIDADO!O:O,"")) | J30: =IF(COUNTBLANK(D30)=1,"",_xlfn.XLOOKUP(D30,BS_CONSOLIDADO!A:A,BS_CONSOLIDADO!P:P,"")) | L30: =IF(COUNTBLANK(D30)=1,"",_xlfn.XLOOKUP(D30,BS_SIMULADOR!A:A,BS_SIMULADOR!D:D,"")) | M30: =IF(COUNTBLANK(D30)=1,"",_xlfn.XLOOKUP(D30,BS_SIMULADOR!A:A,BS_SIMULADOR!Q:Q,"")) | N30: =IF(COUNTBLANK($D30)=1,"",_xlfn.XLOOKUP($D30,BS_SIMULADOR!$A:$A,BS_SIMULADOR!M:M,"")) | O30: =IF(COUNTBLANK(D30)=1,"",_xlfn.XLOOKUP(D30,BS_SIMULADOR!A:A,BS_SIMULADOR!N:N,"")) | P30: =IF(COUNTBLANK(D30)=1,"",_xlfn.XLOOKUP(D30,BS_SIMULADOR!A:A,BS_SIMULADOR!O:O,"")) | Q30: =IF(COUNTBLANK($D30)=1,"",_xlfn.XLOOKUP($D30,BS_SIMULADOR!$A:$A,BS_SIMULADOR!P:P,"")) | S30: =IFERROR(IF(COUNTBLANK(D30)=1,"",E30-L30)*(-1),"") | T30: =IFERROR(IF(COUNTBLANK($D30)=1,"",(_xlfn.XLOOKUP($D30,BS_CONSOLIDADO!$A:$A,BS_CONSOLIDADO!F:F,""))-(_xlfn.XLOOKUP($D30,BS_SIMULADOR!$A:$A,BS_SIMULADOR!F:F,"")))*(-1),"") | U30: =IFERROR(IF(COUNTBLANK(D30)=1,"",(_xlfn.XLOOKUP(D30,BS_CONSOLIDADO!A:A,BS_CONSOLIDADO!H:H,""))-(_xlfn.XLOOKUP(D30,BS_SIMULADOR!A:A,BS_SIMULADOR!H:H,"")))*(-1),"") | V30: =IFERROR(IF(COUNTBLANK(D30)=1,"",(_xlfn.XLOOKUP(D30,BS_CONSOLIDADO!A:A,BS_CONSOLIDADO!J:J,""))-(_xlfn.XLOOKUP(D30,BS_SIMULADOR!A:A,BS_SIMULADOR!J:J,"")))*(-1),"") | W30: =IFERROR(IF(COUNTBLANK($D30)=1,"",(_xlfn.XLOOKUP($D30,BS_CONSOLIDADO!$A:$A,BS_CONSOLIDADO!L:L,""))-(_xlfn.XLOOKUP($D30,BS_SIMULADOR!$A:$A,BS_SIMULADOR!L:L,"")))*(-1),"")
E31: =IF(COUNTBLANK(D31)=1,"",_xlfn.XLOOKUP(D31,BS_CONSOLIDADO!A:A,BS_CONSOLIDADO!D:D,"")) | F31: =IF(COUNTBLANK(D31)=1,"",_xlfn.XLOOKUP(D31,BS_CONSOLIDADO!A:A,BS_CONSOLIDADO!Q:Q,"")) | G31: =IF(COUNTBLANK($D31)=1,"",_xlfn.XLOOKUP($D31,BS_CONSOLIDADO!$A:$A,BS_CONSOLIDADO!M:M,"")) | H31: =IF(COUNTBLANK(D31)=1,"",_xlfn.XLOOKUP(D31,BS_CONSOLIDADO!A:A,BS_CONSOLIDADO!N:N,"")) | I31: =IF(COUNTBLANK(D31)=1,"",_xlfn.XLOOKUP(D31,BS_CONSOLIDADO!A:A,BS_CONSOLIDADO!O:O,"")) | J31: =IF(COUNTBLANK(D31)=1,"",_xlfn.XLOOKUP(D31,BS_CONSOLIDADO!A:A,BS_CONSOLIDADO!P:P,"")) | L31: =IF(COUNTBLANK(D31)=1,"",_xlfn.XLOOKUP(D31,BS_SIMULADOR!A:A,BS_SIMULADOR!D:D,"")) | M31: =IF(COUNTBLANK(D31)=1,"",_xlfn.XLOOKUP(D31,BS_SIMULADOR!A:A,BS_SIMULADOR!Q:Q,"")) | N31: =IF(COUNTBLANK($D31)=1,"",_xlfn.XLOOKUP($D31,BS_SIMULADOR!$A:$A,BS_SIMULADOR!M:M,"")) | O31: =IF(COUNTBLANK(D31)=1,"",_xlfn.XLOOKUP(D31,BS_SIMULADOR!A:A,BS_SIMULADOR!N:N,"")) | P31: =IF(COUNTBLANK(D31)=1,"",_xlfn.XLOOKUP(D31,BS_SIMULADOR!A:A,BS_SIMULADOR!O:O,"")) | Q31: =IF(COUNTBLANK($D31)=1,"",_xlfn.XLOOKUP($D31,BS_SIMULADOR!$A:$A,BS_SIMULADOR!P:P,"")) | S31: =IFERROR(IF(COUNTBLANK(D31)=1,"",E31-L31)*(-1),"") | T31: =IFERROR(IF(COUNTBLANK($D31)=1,"",(_xlfn.XLOOKUP($D31,BS_CONSOLIDADO!$A:$A,BS_CONSOLIDADO!F:F,""))-(_xlfn.XLOOKUP($D31,BS_SIMULADOR!$A:$A,BS_SIMULADOR!F:F,"")))*(-1),"") | U31: =IFERROR(IF(COUNTBLANK(D31)=1,"",(_xlfn.XLOOKUP(D31,BS_CONSOLIDADO!A:A,BS_CONSOLIDADO!H:H,""))-(_xlfn.XLOOKUP(D31,BS_SIMULADOR!A:A,BS_SIMULADOR!H:H,"")))*(-1),"") | V31: =IFERROR(IF(COUNTBLANK(D31)=1,"",(_xlfn.XLOOKUP(D31,BS_CONSOLIDADO!A:A,BS_CONSOLIDADO!J:J,""))-(_xlfn.XLOOKUP(D31,BS_SIMULADOR!A:A,BS_SIMULADOR!J:J,"")))*(-1),"") | W31: =IFERROR(IF(COUNTBLANK($D31)=1,"",(_xlfn.XLOOKUP($D31,BS_CONSOLIDADO!$A:$A,BS_CONSOLIDADO!L:L,""))-(_xlfn.XLOOKUP($D31,BS_SIMULADOR!$A:$A,BS_SIMULADOR!L:L,"")))*(-1),"")
E32: =IF(COUNTBLANK(D32)=1,"",_xlfn.XLOOKUP(D32,BS_CONSOLIDADO!A:A,BS_CONSOLIDADO!D:D,"")) | F32: =IF(COUNTBLANK(D32)=1,"",_xlfn.XLOOKUP(D32,BS_CONSOLIDADO!A:A,BS_CONSOLIDADO!Q:Q,"")) | G32: =IF(COUNTBLANK($D32)=1,"",_xlfn.XLOOKUP($D32,BS_CONSOLIDADO!$A:$A,BS_CONSOLIDADO!M:M,"")) | H32: =IF(COUNTBLANK(D32)=1,"",_xlfn.XLOOKUP(D32,BS_CONSOLIDADO!A:A,BS_CONSOLIDADO!N:N,"")) | I32: =IF(COUNTBLANK(D32)=1,"",_xlfn.XLOOKUP(D32,BS_CONSOLIDADO!A:A,BS_CONSOLIDADO!O:O,"")) | J32: =IF(COUNTBLANK(D32)=1,"",_xlfn.XLOOKUP(D32,BS_CONSOLIDADO!A:A,BS_CONSOLIDADO!P:P,"")) | L32: =IF(COUNTBLANK(D32)=1,"",_xlfn.XLOOKUP(D32,BS_SIMULADOR!A:A,BS_SIMULADOR!D:D,"")) | M32: =IF(COUNTBLANK(D32)=1,"",_xlfn.XLOOKUP(D32,BS_SIMULADOR!A:A,BS_SIMULADOR!Q:Q,"")) | N32: =IF(COUNTBLANK($D32)=1,"",_xlfn.XLOOKUP($D32,BS_SIMULADOR!$A:$A,BS_SIMULADOR!M:M,"")) | O32: =IF(COUNTBLANK(D32)=1,"",_xlfn.XLOOKUP(D32,BS_SIMULADOR!A:A,BS_SIMULADOR!N:N,"")) | P32: =IF(COUNTBLANK(D32)=1,"",_xlfn.XLOOKUP(D32,BS_SIMULADOR!A:A,BS_SIMULADOR!O:O,"")) | Q32: =IF(COUNTBLANK($D32)=1,"",_xlfn.XLOOKUP($D32,BS_SIMULADOR!$A:$A,BS_SIMULADOR!P:P,"")) | S32: =IFERROR(IF(COUNTBLANK(D32)=1,"",E32-L32)*(-1),"") | T32: =IFERROR(IF(COUNTBLANK($D32)=1,"",(_xlfn.XLOOKUP($D32,BS_CONSOLIDADO!$A:$A,BS_CONSOLIDADO!F:F,""))-(_xlfn.XLOOKUP($D32,BS_SIMULADOR!$A:$A,BS_SIMULADOR!F:F,"")))*(-1),"") | U32: =IFERROR(IF(COUNTBLANK(D32)=1,"",(_xlfn.XLOOKUP(D32,BS_CONSOLIDADO!A:A,BS_CONSOLIDADO!H:H,""))-(_xlfn.XLOOKUP(D32,BS_SIMULADOR!A:A,BS_SIMULADOR!H:H,"")))*(-1),"") | V32: =IFERROR(IF(COUNTBLANK(D32)=1,"",(_xlfn.XLOOKUP(D32,BS_CONSOLIDADO!A:A,BS_CONSOLIDADO!J:J,""))-(_xlfn.XLOOKUP(D32,BS_SIMULADOR!A:A,BS_SIMULADOR!J:J,"")))*(-1),"") | W32: =IFERROR(IF(COUNTBLANK($D32)=1,"",(_xlfn.XLOOKUP($D32,BS_CONSOLIDADO!$A:$A,BS_CONSOLIDADO!L:L,""))-(_xlfn.XLOOKUP($D32,BS_SIMULADOR!$A:$A,BS_SIMULADOR!L:L,"")))*(-1),"")
E33: =IF(COUNTBLANK(D33)=1,"",_xlfn.XLOOKUP(D33,BS_CONSOLIDADO!A:A,BS_CONSOLIDADO!D:D,"")) | F33: =IF(COUNTBLANK(D33)=1,"",_xlfn.XLOOKUP(D33,BS_CONSOLIDADO!A:A,BS_CONSOLIDADO!Q:Q,"")) | G33: =IF(COUNTBLANK($D33)=1,"",_xlfn.XLOOKUP($D33,BS_CONSOLIDADO!$A:$A,BS_CONSOLIDADO!M:M,"")) | H33: =IF(COUNTBLANK(D33)=1,"",_xlfn.XLOOKUP(D33,BS_CONSOLIDADO!A:A,BS_CONSOLIDADO!N:N,"")) | I33: =IF(COUNTBLANK(D33)=1,"",_xlfn.XLOOKUP(D33,BS_CONSOLIDADO!A:A,BS_CONSOLIDADO!O:O,"")) | J33: =IF(COUNTBLANK(D33)=1,"",_xlfn.XLOOKUP(D33,BS_CONSOLIDADO!A:A,BS_CONSOLIDADO!P:P,"")) | L33: =IF(COUNTBLANK(D33)=1,"",_xlfn.XLOOKUP(D33,BS_SIMULADOR!A:A,BS_SIMULADOR!D:D,"")) | M33: =IF(COUNTBLANK(D33)=1,"",_xlfn.XLOOKUP(D33,BS_SIMULADOR!A:A,BS_SIMULADOR!Q:Q,"")) | N33: =IF(COUNTBLANK($D33)=1,"",_xlfn.XLOOKUP($D33,BS_SIMULADOR!$A:$A,BS_SIMULADOR!M:M,"")) | O33: =IF(COUNTBLANK(D33)=1,"",_xlfn.XLOOKUP(D33,BS_SIMULADOR!A:A,BS_SIMULADOR!N:N,"")) | P33: =IF(COUNTBLANK(D33)=1,"",_xlfn.XLOOKUP(D33,BS_SIMULADOR!A:A,BS_SIMULADOR!O:O,"")) | Q33: =IF(COUNTBLANK($D33)=1,"",_xlfn.XLOOKUP($D33,BS_SIMULADOR!$A:$A,BS_SIMULADOR!P:P,"")) | S33: =IFERROR(IF(COUNTBLANK(D33)=1,"",E33-L33)*(-1),"") | T33: =IFERROR(IF(COUNTBLANK($D33)=1,"",(_xlfn.XLOOKUP($D33,BS_CONSOLIDADO!$A:$A,BS_CONSOLIDADO!F:F,""))-(_xlfn.XLOOKUP($D33,BS_SIMULADOR!$A:$A,BS_SIMULADOR!F:F,"")))*(-1),"") | U33: =IFERROR(IF(COUNTBLANK(D33)=1,"",(_xlfn.XLOOKUP(D33,BS_CONSOLIDADO!A:A,BS_CONSOLIDADO!H:H,""))-(_xlfn.XLOOKUP(D33,BS_SIMULADOR!A:A,BS_SIMULADOR!H:H,"")))*(-1),"") | V33: =IFERROR(IF(COUNTBLANK(D33)=1,"",(_xlfn.XLOOKUP(D33,BS_CONSOLIDADO!A:A,BS_CONSOLIDADO!J:J,""))-(_xlfn.XLOOKUP(D33,BS_SIMULADOR!A:A,BS_SIMULADOR!J:J,"")))*(-1),"") | W33: =IFERROR(IF(COUNTBLANK($D33)=1,"",(_xlfn.XLOOKUP($D33,BS_CONSOLIDADO!$A:$A,BS_CONSOLIDADO!L:L,""))-(_xlfn.XLOOKUP($D33,BS_SIMULADOR!$A:$A,BS_SIMULADOR!L:L,"")))*(-1),"")
E34: =IF(COUNTBLANK(D34)=1,"",_xlfn.XLOOKUP(D34,BS_CONSOLIDADO!A:A,BS_CONSOLIDADO!D:D,"")) | F34: =IF(COUNTBLANK(D34)=1,"",_xlfn.XLOOKUP(D34,BS_CONSOLIDADO!A:A,BS_CONSOLIDADO!Q:Q,"")) | G34: =IF(COUNTBLANK($D34)=1,"",_xlfn.XLOOKUP($D34,BS_CONSOLIDADO!$A:$A,BS_CONSOLIDADO!M:M,"")) | H34: =IF(COUNTBLANK(D34)=1,"",_xlfn.XLOOKUP(D34,BS_CONSOLIDADO!A:A,BS_CONSOLIDADO!N:N,"")) | I34: =IF(COUNTBLANK(D34)=1,"",_xlfn.XLOOKUP(D34,BS_CONSOLIDADO!A:A,BS_CONSOLIDADO!O:O,"")) | J34: =IF(COUNTBLANK(D34)=1,"",_xlfn.XLOOKUP(D34,BS_CONSOLIDADO!A:A,BS_CONSOLIDADO!P:P,"")) | L34: =IF(COUNTBLANK(D34)=1,"",_xlfn.XLOOKUP(D34,BS_SIMULADOR!A:A,BS_SIMULADOR!D:D,"")) | M34: =IF(COUNTBLANK(D34)=1,"",_xlfn.XLOOKUP(D34,BS_SIMULADOR!A:A,BS_SIMULADOR!Q:Q,"")) | N34: =IF(COUNTBLANK($D34)=1,"",_xlfn.XLOOKUP($D34,BS_SIMULADOR!$A:$A,BS_SIMULADOR!M:M,"")) | O34: =IF(COUNTBLANK(D34)=1,"",_xlfn.XLOOKUP(D34,BS_SIMULADOR!A:A,BS_SIMULADOR!N:N,"")) | P34: =IF(COUNTBLANK(D34)=1,"",_xlfn.XLOOKUP(D34,BS_SIMULADOR!A:A,BS_SIMULADOR!O:O,"")) | Q34: =IF(COUNTBLANK($D34)=1,"",_xlfn.XLOOKUP($D34,BS_SIMULADOR!$A:$A,BS_SIMULADOR!P:P,"")) | S34: =IFERROR(IF(COUNTBLANK(D34)=1,"",E34-L34)*(-1),"") | T34: =IFERROR(IF(COUNTBLANK($D34)=1,"",(_xlfn.XLOOKUP($D34,BS_CONSOLIDADO!$A:$A,BS_CONSOLIDADO!F:F,""))-(_xlfn.XLOOKUP($D34,BS_SIMULADOR!$A:$A,BS_SIMULADOR!F:F,"")))*(-1),"") | U34: =IFERROR(IF(COUNTBLANK(D34)=1,"",(_xlfn.XLOOKUP(D34,BS_CONSOLIDADO!A:A,BS_CONSOLIDADO!H:H,""))-(_xlfn.XLOOKUP(D34,BS_SIMULADOR!A:A,BS_SIMULADOR!H:H,"")))*(-1),"") | V34: =IFERROR(IF(COUNTBLANK(D34)=1,"",(_xlfn.XLOOKUP(D34,BS_CONSOLIDADO!A:A,BS_CONSOLIDADO!J:J,""))-(_xlfn.XLOOKUP(D34,BS_SIMULADOR!A:A,BS_SIMULADOR!J:J,"")))*(-1),"") | W34: =IFERROR(IF(COUNTBLANK($D34)=1,"",(_xlfn.XLOOKUP($D34,BS_CONSOLIDADO!$A:$A,BS_CONSOLIDADO!L:L,""))-(_xlfn.XLOOKUP($D34,BS_SIMULADOR!$A:$A,BS_SIMULADOR!L:L,"")))*(-1),"")
E35: =IF(COUNTBLANK(D35)=1,"",_xlfn.XLOOKUP(D35,BS_CONSOLIDADO!A:A,BS_CONSOLIDADO!D:D,"")) | F35: =IF(COUNTBLANK(D35)=1,"",_xlfn.XLOOKUP(D35,BS_CONSOLIDADO!A:A,BS_CONSOLIDADO!Q:Q,"")) | G35: =IF(COUNTBLANK($D35)=1,"",_xlfn.XLOOKUP($D35,BS_CONSOLIDADO!$A:$A,BS_CONSOLIDADO!M:M,"")) | H35: =IF(COUNTBLANK(D35)=1,"",_xlfn.XLOOKUP(D35,BS_CONSOLIDADO!A:A,BS_CONSOLIDADO!N:N,"")) | I35: =IF(COUNTBLANK(D35)=1,"",_xlfn.XLOOKUP(D35,BS_CONSOLIDADO!A:A,BS_CONSOLIDADO!O:O,"")) | J35: =IF(COUNTBLANK(D34)=1,"",_xlfn.XLOOKUP(D34,BS_CONSOLIDADO!A:A,BS_CONSOLIDADO!P:P,"")) | L35: =IF(COUNTBLANK(D35)=1,"",_xlfn.XLOOKUP(D35,BS_SIMULADOR!A:A,BS_SIMULADOR!D:D,"")) | M35: =IF(COUNTBLANK(D35)=1,"",_xlfn.XLOOKUP(D35,BS_SIMULADOR!A:A,BS_SIMULADOR!Q:Q,"")) | N35: =IF(COUNTBLANK($D35)=1,"",_xlfn.XLOOKUP($D35,BS_SIMULADOR!$A:$A,BS_SIMULADOR!M:M,"")) | O35: =IF(COUNTBLANK(D35)=1,"",_xlfn.XLOOKUP(D35,BS_SIMULADOR!A:A,BS_SIMULADOR!N:N,"")) | P35: =IF(COUNTBLANK(D35)=1,"",_xlfn.XLOOKUP(D35,BS_SIMULADOR!A:A,BS_SIMULADOR!O:O,"")) | Q35: =IF(COUNTBLANK($D35)=1,"",_xlfn.XLOOKUP($D35,BS_SIMULADOR!$A:$A,BS_SIMULADOR!P:P,"")) | S35: =IFERROR(IF(COUNTBLANK(D35)=1,"",E35-L35)*(-1),"") | T35: =IFERROR(IF(COUNTBLANK($D35)=1,"",(_xlfn.XLOOKUP($D35,BS_CONSOLIDADO!$A:$A,BS_CONSOLIDADO!F:F,""))-(_xlfn.XLOOKUP($D35,BS_SIMULADOR!$A:$A,BS_SIMULADOR!F:F,"")))*(-1),"") | U35: =IFERROR(IF(COUNTBLANK(D35)=1,"",(_xlfn.XLOOKUP(D35,BS_CONSOLIDADO!A:A,BS_CONSOLIDADO!H:H,""))-(_xlfn.XLOOKUP(D35,BS_SIMULADOR!A:A,BS_SIMULADOR!H:H,"")))*(-1),"") | V35: =IFERROR(IF(COUNTBLANK(D35)=1,"",(_xlfn.XLOOKUP(D35,BS_CONSOLIDADO!A:A,BS_CONSOLIDADO!J:J,""))-(_xlfn.XLOOKUP(D35,BS_SIMULADOR!A:A,BS_SIMULADOR!J:J,"")))*(-1),"") | W35: =IFERROR(IF(COUNTBLANK($D35)=1,"",(_xlfn.XLOOKUP($D35,BS_CONSOLIDADO!$A:$A,BS_CONSOLIDADO!L:L,""))-(_xlfn.XLOOKUP($D35,BS_SIMULADOR!$A:$A,BS_SIMULADOR!L:L,"")))*(-1),"")
E36: =IF(COUNTBLANK(D36)=1,"",_xlfn.XLOOKUP(D36,BS_CONSOLIDADO!A:A,BS_CONSOLIDADO!D:D,"")) | F36: =IF(COUNTBLANK(D36)=1,"",_xlfn.XLOOKUP(D36,BS_CONSOLIDADO!A:A,BS_CONSOLIDADO!Q:Q,"")) | G36: =IF(COUNTBLANK($D36)=1,"",_xlfn.XLOOKUP($D36,BS_CONSOLIDADO!$A:$A,BS_CONSOLIDADO!M:M,"")) | H36: =IF(COUNTBLANK(D36)=1,"",_xlfn.XLOOKUP(D36,BS_CONSOLIDADO!A:A,BS_CONSOLIDADO!N:N,"")) | I36: =IF(COUNTBLANK(D36)=1,"",_xlfn.XLOOKUP(D36,BS_CONSOLIDADO!A:A,BS_CONSOLIDADO!O:O,"")) | J36: =IF(COUNTBLANK(D36)=1,"",_xlfn.XLOOKUP(D36,BS_CONSOLIDADO!A:A,BS_CONSOLIDADO!P:P,"")) | L36: =IF(COUNTBLANK(D36)=1,"",_xlfn.XLOOKUP(D36,BS_SIMULADOR!A:A,BS_SIMULADOR!D:D,"")) | M36: =IF(COUNTBLANK(D36)=1,"",_xlfn.XLOOKUP(D36,BS_SIMULADOR!A:A,BS_SIMULADOR!Q:Q,"")) | N36: =IF(COUNTBLANK($D36)=1,"",_xlfn.XLOOKUP($D36,BS_SIMULADOR!$A:$A,BS_SIMULADOR!M:M,"")) | O36: =IF(COUNTBLANK(D36)=1,"",_xlfn.XLOOKUP(D36,BS_SIMULADOR!A:A,BS_SIMULADOR!N:N,"")) | P36: =IF(COUNTBLANK(D36)=1,"",_xlfn.XLOOKUP(D36,BS_SIMULADOR!A:A,BS_SIMULADOR!O:O,"")) | Q36: =IF(COUNTBLANK($D36)=1,"",_xlfn.XLOOKUP($D36,BS_SIMULADOR!$A:$A,BS_SIMULADOR!P:P,"")) | S36: =IFERROR(IF(COUNTBLANK(D36)=1,"",E36-L36)*(-1),"") | T36: =IFERROR(IF(COUNTBLANK($D36)=1,"",(_xlfn.XLOOKUP($D36,BS_CONSOLIDADO!$A:$A,BS_CONSOLIDADO!F:F,""))-(_xlfn.XLOOKUP($D36,BS_SIMULADOR!$A:$A,BS_SIMULADOR!F:F,"")))*(-1),"") | U36: =IFERROR(IF(COUNTBLANK(D36)=1,"",(_xlfn.XLOOKUP(D36,BS_CONSOLIDADO!A:A,BS_CONSOLIDADO!H:H,""))-(_xlfn.XLOOKUP(D36,BS_SIMULADOR!A:A,BS_SIMULADOR!H:H,"")))*(-1),"") | V36: =IFERROR(IF(COUNTBLANK(D36)=1,"",(_xlfn.XLOOKUP(D36,BS_CONSOLIDADO!A:A,BS_CONSOLIDADO!J:J,""))-(_xlfn.XLOOKUP(D36,BS_SIMULADOR!A:A,BS_SIMULADOR!J:J,"")))*(-1),"") | W36: =IFERROR(IF(COUNTBLANK($D36)=1,"",(_xlfn.XLOOKUP($D36,BS_CONSOLIDADO!$A:$A,BS_CONSOLIDADO!L:L,""))-(_xlfn.XLOOKUP($D36,BS_SIMULADOR!$A:$A,BS_SIMULADOR!L:L,"")))*(-1),"")
E37: =IF(COUNTBLANK(D37)=1,"",_xlfn.XLOOKUP(D37,BS_CONSOLIDADO!A:A,BS_CONSOLIDADO!D:D,"")) | F37: =IF(COUNTBLANK(D37)=1,"",_xlfn.XLOOKUP(D37,BS_CONSOLIDADO!A:A,BS_CONSOLIDADO!Q:Q,"")) | G37: =IF(COUNTBLANK($D37)=1,"",_xlfn.XLOOKUP($D37,BS_CONSOLIDADO!$A:$A,BS_CONSOLIDADO!M:M,"")) | H37: =IF(COUNTBLANK(D37)=1,"",_xlfn.XLOOKUP(D37,BS_CONSOLIDADO!A:A,BS_CONSOLIDADO!N:N,"")) | I37: =IF(COUNTBLANK(D37)=1,"",_xlfn.XLOOKUP(D37,BS_CONSOLIDADO!A:A,BS_CONSOLIDADO!O:O,"")) | J37: =IF(COUNTBLANK(D37)=1,"",_xlfn.XLOOKUP(D37,BS_CONSOLIDADO!A:A,BS_CONSOLIDADO!P:P,"")) | L37: =IF(COUNTBLANK(D37)=1,"",_xlfn.XLOOKUP(D37,BS_SIMULADOR!A:A,BS_SIMULADOR!D:D,"")) | M37: =IF(COUNTBLANK(D37)=1,"",_xlfn.XLOOKUP(D37,BS_SIMULADOR!A:A,BS_SIMULADOR!Q:Q,"")) | N37: =IF(COUNTBLANK($D37)=1,"",_xlfn.XLOOKUP($D37,BS_SIMULADOR!$A:$A,BS_SIMULADOR!M:M,"")) | O37: =IF(COUNTBLANK(D37)=1,"",_xlfn.XLOOKUP(D37,BS_SIMULADOR!A:A,BS_SIMULADOR!N:N,"")) | P37: =IF(COUNTBLANK(D37)=1,"",_xlfn.XLOOKUP(D37,BS_SIMULADOR!A:A,BS_SIMULADOR!O:O,"")) | Q37: =IF(COUNTBLANK($D37)=1,"",_xlfn.XLOOKUP($D37,BS_SIMULADOR!$A:$A,BS_SIMULADOR!P:P,"")) | S37: =IFERROR(IF(COUNTBLANK(D37)=1,"",E37-L37)*(-1),"") | T37: =IFERROR(IF(COUNTBLANK($D37)=1,"",(_xlfn.XLOOKUP($D37,BS_CONSOLIDADO!$A:$A,BS_CONSOLIDADO!F:F,""))-(_xlfn.XLOOKUP($D37,BS_SIMULADOR!$A:$A,BS_SIMULADOR!F:F,"")))*(-1),"") | U37: =IFERROR(IF(COUNTBLANK(D37)=1,"",(_xlfn.XLOOKUP(D37,BS_CONSOLIDADO!A:A,BS_CONSOLIDADO!H:H,""))-(_xlfn.XLOOKUP(D37,BS_SIMULADOR!A:A,BS_SIMULADOR!H:H,"")))*(-1),"") | V37: =IFERROR(IF(COUNTBLANK(D37)=1,"",(_xlfn.XLOOKUP(D37,BS_CONSOLIDADO!A:A,BS_CONSOLIDADO!J:J,""))-(_xlfn.XLOOKUP(D37,BS_SIMULADOR!A:A,BS_SIMULADOR!J:J,"")))*(-1),"") | W37: =IFERROR(IF(COUNTBLANK($D37)=1,"",(_xlfn.XLOOKUP($D37,BS_CONSOLIDADO!$A:$A,BS_CONSOLIDADO!L:L,""))-(_xlfn.XLOOKUP($D37,BS_SIMULADOR!$A:$A,BS_SIMULADOR!L:L,"")))*(-1),"")
E38: =IF(COUNTBLANK(D38)=1,"",_xlfn.XLOOKUP(D38,BS_CONSOLIDADO!A:A,BS_CONSOLIDADO!D:D,"")) | F38: =IF(COUNTBLANK(D38)=1,"",_xlfn.XLOOKUP(D38,BS_CONSOLIDADO!A:A,BS_CONSOLIDADO!Q:Q,"")) | G38: =IF(COUNTBLANK($D38)=1,"",_xlfn.XLOOKUP($D38,BS_CONSOLIDADO!$A:$A,BS_CONSOLIDADO!M:M,"")) | H38: =IF(COUNTBLANK(D38)=1,"",_xlfn.XLOOKUP(D38,BS_CONSOLIDADO!A:A,BS_CONSOLIDADO!N:N,"")) | I38: =IF(COUNTBLANK(D38)=1,"",_xlfn.XLOOKUP(D38,BS_CONSOLIDADO!A:A,BS_CONSOLIDADO!O:O,"")) | J38: =IF(COUNTBLANK(D38)=1,"",_xlfn.XLOOKUP(D38,BS_CONSOLIDADO!A:A,BS_CONSOLIDADO!P:P,"")) | L38: =IF(COUNTBLANK(D38)=1,"",_xlfn.XLOOKUP(D38,BS_SIMULADOR!A:A,BS_SIMULADOR!D:D,"")) | M38: =IF(COUNTBLANK(D38)=1,"",_xlfn.XLOOKUP(D38,BS_SIMULADOR!A:A,BS_SIMULADOR!Q:Q,"")) | N38: =IF(COUNTBLANK($D38)=1,"",_xlfn.XLOOKUP($D38,BS_SIMULADOR!$A:$A,BS_SIMULADOR!M:M,"")) | O38: =IF(COUNTBLANK(D38)=1,"",_xlfn.XLOOKUP(D38,BS_SIMULADOR!A:A,BS_SIMULADOR!N:N,"")) | P38: =IF(COUNTBLANK(D38)=1,"",_xlfn.XLOOKUP(D38,BS_SIMULADOR!A:A,BS_SIMULADOR!O:O,"")) | Q38: =IF(COUNTBLANK($D38)=1,"",_xlfn.XLOOKUP($D38,BS_SIMULADOR!$A:$A,BS_SIMULADOR!P:P,"")) | S38: =IFERROR(IF(COUNTBLANK(D38)=1,"",E38-L38)*(-1),"") | T38: =IFERROR(IF(COUNTBLANK($D38)=1,"",(_xlfn.XLOOKUP($D38,BS_CONSOLIDADO!$A:$A,BS_CONSOLIDADO!F:F,""))-(_xlfn.XLOOKUP($D38,BS_SIMULADOR!$A:$A,BS_SIMULADOR!F:F,"")))*(-1),"") | U38: =IFERROR(IF(COUNTBLANK(D38)=1,"",(_xlfn.XLOOKUP(D38,BS_CONSOLIDADO!A:A,BS_CONSOLIDADO!H:H,""))-(_xlfn.XLOOKUP(D38,BS_SIMULADOR!A:A,BS_SIMULADOR!H:H,"")))*(-1),"") | V38: =IFERROR(IF(COUNTBLANK(D38)=1,"",(_xlfn.XLOOKUP(D38,BS_CONSOLIDADO!A:A,BS_CONSOLIDADO!J:J,""))-(_xlfn.XLOOKUP(D38,BS_SIMULADOR!A:A,BS_SIMULADOR!J:J,"")))*(-1),"") | W38: =IFERROR(IF(COUNTBLANK($D38)=1,"",(_xlfn.XLOOKUP($D38,BS_CONSOLIDADO!$A:$A,BS_CONSOLIDADO!L:L,""))-(_xlfn.XLOOKUP($D38,BS_SIMULADOR!$A:$A,BS_SIMULADOR!L:L,"")))*(-1),"")
E39: =IF(COUNTBLANK(D39)=1,"",_xlfn.XLOOKUP(D39,BS_CONSOLIDADO!A:A,BS_CONSOLIDADO!D:D,"")) | F39: =IF(COUNTBLANK(D39)=1,"",_xlfn.XLOOKUP(D39,BS_CONSOLIDADO!A:A,BS_CONSOLIDADO!Q:Q,"")) | G39: =IF(COUNTBLANK($D39)=1,"",_xlfn.XLOOKUP($D39,BS_CONSOLIDADO!$A:$A,BS_CONSOLIDADO!M:M,"")) | H39: =IF(COUNTBLANK(D39)=1,"",_xlfn.XLOOKUP(D39,BS_CONSOLIDADO!A:A,BS_CONSOLIDADO!N:N,"")) | I39: =IF(COUNTBLANK(D39)=1,"",_xlfn.XLOOKUP(D39,BS_CONSOLIDADO!A:A,BS_CONSOLIDADO!O:O,"")) | J39: =IF(COUNTBLANK(D39)=1,"",_xlfn.XLOOKUP(D39,BS_CONSOLIDADO!A:A,BS_CONSOLIDADO!P:P,"")) | L39: =IF(COUNTBLANK(D39)=1,"",_xlfn.XLOOKUP(D39,BS_SIMULADOR!A:A,BS_SIMULADOR!D:D,"")) | M39: =IF(COUNTBLANK(D39)=1,"",_xlfn.XLOOKUP(D39,BS_SIMULADOR!A:A,BS_SIMULADOR!Q:Q,"")) | N39: =IF(COUNTBLANK($D39)=1,"",_xlfn.XLOOKUP($D39,BS_SIMULADOR!$A:$A,BS_SIMULADOR!M:M,"")) | O39: =IF(COUNTBLANK(D39)=1,"",_xlfn.XLOOKUP(D39,BS_SIMULADOR!A:A,BS_SIMULADOR!N:N,"")) | P39: =IF(COUNTBLANK(D39)=1,"",_xlfn.XLOOKUP(D39,BS_SIMULADOR!A:A,BS_SIMULADOR!O:O,"")) | Q39: =IF(COUNTBLANK($D39)=1,"",_xlfn.XLOOKUP($D39,BS_SIMULADOR!$A:$A,BS_SIMULADOR!P:P,"")) | S39: =IFERROR(IF(COUNTBLANK(D39)=1,"",E39-L39)*(-1),"") | T39: =IFERROR(IF(COUNTBLANK($D39)=1,"",(_xlfn.XLOOKUP($D39,BS_CONSOLIDADO!$A:$A,BS_CONSOLIDADO!F:F,""))-(_xlfn.XLOOKUP($D39,BS_SIMULADOR!$A:$A,BS_SIMULADOR!F:F,"")))*(-1),"") | U39: =IFERROR(IF(COUNTBLANK(D39)=1,"",(_xlfn.XLOOKUP(D39,BS_CONSOLIDADO!A:A,BS_CONSOLIDADO!H:H,""))-(_xlfn.XLOOKUP(D39,BS_SIMULADOR!A:A,BS_SIMULADOR!H:H,"")))*(-1),"") | V39: =IFERROR(IF(COUNTBLANK(D39)=1,"",(_xlfn.XLOOKUP(D39,BS_CONSOLIDADO!A:A,BS_CONSOLIDADO!J:J,""))-(_xlfn.XLOOKUP(D39,BS_SIMULADOR!A:A,BS_SIMULADOR!J:J,"")))*(-1),"") | W39: =IFERROR(IF(COUNTBLANK($D39)=1,"",(_xlfn.XLOOKUP($D39,BS_CONSOLIDADO!$A:$A,BS_CONSOLIDADO!L:L,""))-(_xlfn.XLOOKUP($D39,BS_SIMULADOR!$A:$A,BS_SIMULADOR!L:L,"")))*(-1),"")
E40: =IF(COUNTBLANK(D40)=1,"",_xlfn.XLOOKUP(D40,BS_CONSOLIDADO!A:A,BS_CONSOLIDADO!D:D,"")) | F40: =IF(COUNTBLANK(D40)=1,"",_xlfn.XLOOKUP(D40,BS_CONSOLIDADO!A:A,BS_CONSOLIDADO!Q:Q,"")) | G40: =IF(COUNTBLANK($D40)=1,"",_xlfn.XLOOKUP($D40,BS_CONSOLIDADO!$A:$A,BS_CONSOLIDADO!M:M,"")) | H40: =IF(COUNTBLANK(D40)=1,"",_xlfn.XLOOKUP(D40,BS_CONSOLIDADO!A:A,BS_CONSOLIDADO!N:N,"")) | I40: =IF(COUNTBLANK(D40)=1,"",_xlfn.XLOOKUP(D40,BS_CONSOLIDADO!A:A,BS_CONSOLIDADO!O:O,"")) | J40: =IF(COUNTBLANK(D40)=1,"",_xlfn.XLOOKUP(D40,BS_CONSOLIDADO!A:A,BS_CONSOLIDADO!P:P,"")) | L40: =IF(COUNTBLANK(D40)=1,"",_xlfn.XLOOKUP(D40,BS_SIMULADOR!A:A,BS_SIMULADOR!D:D,"")) | M40: =IF(COUNTBLANK(D40)=1,"",_xlfn.XLOOKUP(D40,BS_SIMULADOR!A:A,BS_SIMULADOR!Q:Q,"")) | N40: =IF(COUNTBLANK($D40)=1,"",_xlfn.XLOOKUP($D40,BS_SIMULADOR!$A:$A,BS_SIMULADOR!M:M,"")) | O40: =IF(COUNTBLANK(D40)=1,"",_xlfn.XLOOKUP(D40,BS_SIMULADOR!A:A,BS_SIMULADOR!N:N,"")) | P40: =IF(COUNTBLANK(D40)=1,"",_xlfn.XLOOKUP(D40,BS_SIMULADOR!A:A,BS_SIMULADOR!O:O,"")) | Q40: =IF(COUNTBLANK($D40)=1,"",_xlfn.XLOOKUP($D40,BS_SIMULADOR!$A:$A,BS_SIMULADOR!P:P,"")) | S40: =IFERROR(IF(COUNTBLANK(D40)=1,"",E40-L40)*(-1),"") | T40: =IFERROR(IF(COUNTBLANK($D40)=1,"",(_xlfn.XLOOKUP($D40,BS_CONSOLIDADO!$A:$A,BS_CONSOLIDADO!F:F,""))-(_xlfn.XLOOKUP($D40,BS_SIMULADOR!$A:$A,BS_SIMULADOR!F:F,"")))*(-1),"") | U40: =IFERROR(IF(COUNTBLANK(D40)=1,"",(_xlfn.XLOOKUP(D40,BS_CONSOLIDADO!A:A,BS_CONSOLIDADO!H:H,""))-(_xlfn.XLOOKUP(D40,BS_SIMULADOR!A:A,BS_SIMULADOR!H:H,"")))*(-1),"") | V40: =IFERROR(IF(COUNTBLANK(D40)=1,"",(_xlfn.XLOOKUP(D40,BS_CONSOLIDADO!A:A,BS_CONSOLIDADO!J:J,""))-(_xlfn.XLOOKUP(D40,BS_SIMULADOR!A:A,BS_SIMULADOR!J:J,"")))*(-1),"") | W40: =IFERROR(IF(COUNTBLANK($D40)=1,"",(_xlfn.XLOOKUP($D40,BS_CONSOLIDADO!$A:$A,BS_CONSOLIDADO!L:L,""))-(_xlfn.XLOOKUP($D40,BS_SIMULADOR!$A:$A,BS_SIMULADOR!L:L,"")))*(-1),"")
E41: =IF(COUNTBLANK(D41)=1,"",_xlfn.XLOOKUP(D41,BS_CONSOLIDADO!A:A,BS_CONSOLIDADO!D:D,"")) | F41: =IF(COUNTBLANK(D41)=1,"",_xlfn.XLOOKUP(D41,BS_CONSOLIDADO!A:A,BS_CONSOLIDADO!Q:Q,"")) | G41: =IF(COUNTBLANK($D41)=1,"",_xlfn.XLOOKUP($D41,BS_CONSOLIDADO!$A:$A,BS_CONSOLIDADO!M:M,"")) | H41: =IF(COUNTBLANK(D41)=1,"",_xlfn.XLOOKUP(D41,BS_CONSOLIDADO!A:A,BS_CONSOLIDADO!N:N,"")) | I41: =IF(COUNTBLANK(D41)=1,"",_xlfn.XLOOKUP(D41,BS_CONSOLIDADO!A:A,BS_CONSOLIDADO!O:O,"")) | J41: =IF(COUNTBLANK(D41)=1,"",_xlfn.XLOOKUP(D41,BS_CONSOLIDADO!A:A,BS_CONSOLIDADO!P:P,"")) | L41: =IF(COUNTBLANK(D41)=1,"",_xlfn.XLOOKUP(D41,BS_SIMULADOR!A:A,BS_SIMULADOR!D:D,"")) | M41: =IF(COUNTBLANK(D41)=1,"",_xlfn.XLOOKUP(D41,BS_SIMULADOR!A:A,BS_SIMULADOR!Q:Q,"")) | N41: =IF(COUNTBLANK($D41)=1,"",_xlfn.XLOOKUP($D41,BS_SIMULADOR!$A:$A,BS_SIMULADOR!M:M,"")) | O41: =IF(COUNTBLANK(D41)=1,"",_xlfn.XLOOKUP(D41,BS_SIMULADOR!A:A,BS_SIMULADOR!N:N,"")) | P41: =IF(COUNTBLANK(D41)=1,"",_xlfn.XLOOKUP(D41,BS_SIMULADOR!A:A,BS_SIMULADOR!O:O,"")) | Q41: =IF(COUNTBLANK($D41)=1,"",_xlfn.XLOOKUP($D41,BS_SIMULADOR!$A:$A,BS_SIMULADOR!P:P,"")) | S41: =IFERROR(IF(COUNTBLANK(D41)=1,"",E41-L41)*(-1),"") | T41: =IFERROR(IF(COUNTBLANK($D41)=1,"",(_xlfn.XLOOKUP($D41,BS_CONSOLIDADO!$A:$A,BS_CONSOLIDADO!F:F,""))-(_xlfn.XLOOKUP($D41,BS_SIMULADOR!$A:$A,BS_SIMULADOR!F:F,"")))*(-1),"") | U41: =IFERROR(IF(COUNTBLANK(D41)=1,"",(_xlfn.XLOOKUP(D41,BS_CONSOLIDADO!A:A,BS_CONSOLIDADO!H:H,""))-(_xlfn.XLOOKUP(D41,BS_SIMULADOR!A:A,BS_SIMULADOR!H:H,"")))*(-1),"") | V41: =IFERROR(IF(COUNTBLANK(D41)=1,"",(_xlfn.XLOOKUP(D41,BS_CONSOLIDADO!A:A,BS_CONSOLIDADO!J:J,""))-(_xlfn.XLOOKUP(D41,BS_SIMULADOR!A:A,BS_SIMULADOR!J:J,"")))*(-1),"") | W41: =IFERROR(IF(COUNTBLANK($D41)=1,"",(_xlfn.XLOOKUP($D41,BS_CONSOLIDADO!$A:$A,BS_CONSOLIDADO!L:L,""))-(_xlfn.XLOOKUP($D41,BS_SIMULADOR!$A:$A,BS_SIMULADOR!L:L,"")))*(-1),"")
E42: =IF(COUNTBLANK(D42)=1,"",_xlfn.XLOOKUP(D42,BS_CONSOLIDADO!A:A,BS_CONSOLIDADO!D:D,"")) | F42: =IF(COUNTBLANK(D42)=1,"",_xlfn.XLOOKUP(D42,BS_CONSOLIDADO!A:A,BS_CONSOLIDADO!Q:Q,"")) | G42: =IF(COUNTBLANK($D42)=1,"",_xlfn.XLOOKUP($D42,BS_CONSOLIDADO!$A:$A,BS_CONSOLIDADO!M:M,"")) | H42: =IF(COUNTBLANK(D42)=1,"",_xlfn.XLOOKUP(D42,BS_CONSOLIDADO!A:A,BS_CONSOLIDADO!N:N,"")) | I42: =IF(COUNTBLANK(D42)=1,"",_xlfn.XLOOKUP(D42,BS_CONSOLIDADO!A:A,BS_CONSOLIDADO!O:O,"")) | J42: =IF(COUNTBLANK(D42)=1,"",_xlfn.XLOOKUP(D42,BS_CONSOLIDADO!A:A,BS_CONSOLIDADO!P:P,"")) | L42: =IF(COUNTBLANK(D42)=1,"",_xlfn.XLOOKUP(D42,BS_SIMULADOR!A:A,BS_SIMULADOR!D:D,"")) | M42: =IF(COUNTBLANK(D42)=1,"",_xlfn.XLOOKUP(D42,BS_SIMULADOR!A:A,BS_SIMULADOR!Q:Q,"")) | N42: =IF(COUNTBLANK($D42)=1,"",_xlfn.XLOOKUP($D42,BS_SIMULADOR!$A:$A,BS_SIMULADOR!M:M,"")) | O42: =IF(COUNTBLANK(D42)=1,"",_xlfn.XLOOKUP(D42,BS_SIMULADOR!A:A,BS_SIMULADOR!N:N,"")) | P42: =IF(COUNTBLANK(D42)=1,"",_xlfn.XLOOKUP(D42,BS_SIMULADOR!A:A,BS_SIMULADOR!O:O,"")) | Q42: =IF(COUNTBLANK($D42)=1,"",_xlfn.XLOOKUP($D42,BS_SIMULADOR!$A:$A,BS_SIMULADOR!P:P,"")) | S42: =IFERROR(IF(COUNTBLANK(D42)=1,"",E42-L42)*(-1),"") | T42: =IFERROR(IF(COUNTBLANK($D42)=1,"",(_xlfn.XLOOKUP($D42,BS_CONSOLIDADO!$A:$A,BS_CONSOLIDADO!F:F,""))-(_xlfn.XLOOKUP($D42,BS_SIMULADOR!$A:$A,BS_SIMULADOR!F:F,"")))*(-1),"") | U42: =IFERROR(IF(COUNTBLANK(D42)=1,"",(_xlfn.XLOOKUP(D42,BS_CONSOLIDADO!A:A,BS_CONSOLIDADO!H:H,""))-(_xlfn.XLOOKUP(D42,BS_SIMULADOR!A:A,BS_SIMULADOR!H:H,"")))*(-1),"") | V42: =IFERROR(IF(COUNTBLANK(D42)=1,"",(_xlfn.XLOOKUP(D42,BS_CONSOLIDADO!A:A,BS_CONSOLIDADO!J:J,""))-(_xlfn.XLOOKUP(D42,BS_SIMULADOR!A:A,BS_SIMULADOR!J:J,"")))*(-1),"") | W42: =IFERROR(IF(COUNTBLANK($D42)=1,"",(_xlfn.XLOOKUP($D42,BS_CONSOLIDADO!$A:$A,BS_CONSOLIDADO!L:L,""))-(_xlfn.XLOOKUP($D42,BS_SIMULADOR!$A:$A,BS_SIMULADOR!L:L,"")))*(-1),"")
E43: =IF(COUNTBLANK(D43)=1,"",_xlfn.XLOOKUP(D43,BS_CONSOLIDADO!A:A,BS_CONSOLIDADO!D:D,"")) | F43: =IF(COUNTBLANK(D43)=1,"",_xlfn.XLOOKUP(D43,BS_CONSOLIDADO!A:A,BS_CONSOLIDADO!Q:Q,"")) | G43: =IF(COUNTBLANK($D43)=1,"",_xlfn.XLOOKUP($D43,BS_CONSOLIDADO!$A:$A,BS_CONSOLIDADO!M:M,"")) | H43: =IF(COUNTBLANK(D43)=1,"",_xlfn.XLOOKUP(D43,BS_CONSOLIDADO!A:A,BS_CONSOLIDADO!N:N,"")) | I43: =IF(COUNTBLANK(D43)=1,"",_xlfn.XLOOKUP(D43,BS_CONSOLIDADO!A:A,BS_CONSOLIDADO!O:O,"")) | J43: =IF(COUNTBLANK(D43)=1,"",_xlfn.XLOOKUP(D43,BS_CONSOLIDADO!A:A,BS_CONSOLIDADO!P:P,"")) | L43: =IF(COUNTBLANK(D43)=1,"",_xlfn.XLOOKUP(D43,BS_SIMULADOR!A:A,BS_SIMULADOR!D:D,"")) | M43: =IF(COUNTBLANK(D43)=1,"",_xlfn.XLOOKUP(D43,BS_SIMULADOR!A:A,BS_SIMULADOR!Q:Q,"")) | N43: =IF(COUNTBLANK($D43)=1,"",_xlfn.XLOOKUP($D43,BS_SIMULADOR!$A:$A,BS_SIMULADOR!M:M,"")) | O43: =IF(COUNTBLANK(D43)=1,"",_xlfn.XLOOKUP(D43,BS_SIMULADOR!A:A,BS_SIMULADOR!N:N,"")) | P43: =IF(COUNTBLANK(D43)=1,"",_xlfn.XLOOKUP(D43,BS_SIMULADOR!A:A,BS_SIMULADOR!O:O,"")) | Q43: =IF(COUNTBLANK($D43)=1,"",_xlfn.XLOOKUP($D43,BS_SIMULADOR!$A:$A,BS_SIMULADOR!P:P,"")) | S43: =IFERROR(IF(COUNTBLANK(D43)=1,"",E43-L43)*(-1),"") | T43: =IFERROR(IF(COUNTBLANK($D43)=1,"",(_xlfn.XLOOKUP($D43,BS_CONSOLIDADO!$A:$A,BS_CONSOLIDADO!F:F,""))-(_xlfn.XLOOKUP($D43,BS_SIMULADOR!$A:$A,BS_SIMULADOR!F:F,"")))*(-1),"") | U43: =IFERROR(IF(COUNTBLANK(D43)=1,"",(_xlfn.XLOOKUP(D43,BS_CONSOLIDADO!A:A,BS_CONSOLIDADO!H:H,""))-(_xlfn.XLOOKUP(D43,BS_SIMULADOR!A:A,BS_SIMULADOR!H:H,"")))*(-1),"") | V43: =IFERROR(IF(COUNTBLANK(D43)=1,"",(_xlfn.XLOOKUP(D43,BS_CONSOLIDADO!A:A,BS_CONSOLIDADO!J:J,""))-(_xlfn.XLOOKUP(D43,BS_SIMULADOR!A:A,BS_SIMULADOR!J:J,"")))*(-1),"") | W43: =IFERROR(IF(COUNTBLANK($D43)=1,"",(_xlfn.XLOOKUP($D43,BS_CONSOLIDADO!$A:$A,BS_CONSOLIDADO!L:L,""))-(_xlfn.XLOOKUP($D43,BS_SIMULADOR!$A:$A,BS_SIMULADOR!L:L,"")))*(-1),"")
E44: =IF(COUNTBLANK(D44)=1,"",_xlfn.XLOOKUP(D44,BS_CONSOLIDADO!A:A,BS_CONSOLIDADO!D:D,"")) | F44: =IF(COUNTBLANK(D44)=1,"",_xlfn.XLOOKUP(D44,BS_CONSOLIDADO!A:A,BS_CONSOLIDADO!Q:Q,"")) | G44: =IF(COUNTBLANK($D44)=1,"",_xlfn.XLOOKUP($D44,BS_CONSOLIDADO!$A:$A,BS_CONSOLIDADO!M:M,"")) | H44: =IF(COUNTBLANK(D44)=1,"",_xlfn.XLOOKUP(D44,BS_CONSOLIDADO!A:A,BS_CONSOLIDADO!N:N,"")) | I44: =IF(COUNTBLANK(D44)=1,"",_xlfn.XLOOKUP(D44,BS_CONSOLIDADO!A:A,BS_CONSOLIDADO!O:O,"")) | J44: =IF(COUNTBLANK(D44)=1,"",_xlfn.XLOOKUP(D44,BS_CONSOLIDADO!A:A,BS_CONSOLIDADO!P:P,"")) | L44: =IF(COUNTBLANK(D44)=1,"",_xlfn.XLOOKUP(D44,BS_SIMULADOR!A:A,BS_SIMULADOR!D:D,"")) | M44: =IF(COUNTBLANK(D44)=1,"",_xlfn.XLOOKUP(D44,BS_SIMULADOR!A:A,BS_SIMULADOR!Q:Q,"")) | N44: =IF(COUNTBLANK($D44)=1,"",_xlfn.XLOOKUP($D44,BS_SIMULADOR!$A:$A,BS_SIMULADOR!M:M,"")) | O44: =IF(COUNTBLANK(D44)=1,"",_xlfn.XLOOKUP(D44,BS_SIMULADOR!A:A,BS_SIMULADOR!N:N,"")) | P44: =IF(COUNTBLANK(D44)=1,"",_xlfn.XLOOKUP(D44,BS_SIMULADOR!A:A,BS_SIMULADOR!O:O,"")) | Q44: =IF(COUNTBLANK($D44)=1,"",_xlfn.XLOOKUP($D44,BS_SIMULADOR!$A:$A,BS_SIMULADOR!P:P,"")) | S44: =IFERROR(IF(COUNTBLANK(D44)=1,"",E44-L44)*(-1),"") | T44: =IFERROR(IF(COUNTBLANK($D44)=1,"",(_xlfn.XLOOKUP($D44,BS_CONSOLIDADO!$A:$A,BS_CONSOLIDADO!F:F,""))-(_xlfn.XLOOKUP($D44,BS_SIMULADOR!$A:$A,BS_SIMULADOR!F:F,"")))*(-1),"") | U44: =IFERROR(IF(COUNTBLANK(D44)=1,"",(_xlfn.XLOOKUP(D44,BS_CONSOLIDADO!A:A,BS_CONSOLIDADO!H:H,""))-(_xlfn.XLOOKUP(D44,BS_SIMULADOR!A:A,BS_SIMULADOR!H:H,"")))*(-1),"") | V44: =IFERROR(IF(COUNTBLANK(D44)=1,"",(_xlfn.XLOOKUP(D44,BS_CONSOLIDADO!A:A,BS_CONSOLIDADO!J:J,""))-(_xlfn.XLOOKUP(D44,BS_SIMULADOR!A:A,BS_SIMULADOR!J:J,"")))*(-1),"") | W44: =IFERROR(IF(COUNTBLANK($D44)=1,"",(_xlfn.XLOOKUP($D44,BS_CONSOLIDADO!$A:$A,BS_CONSOLIDADO!L:L,""))-(_xlfn.XLOOKUP($D44,BS_SIMULADOR!$A:$A,BS_SIMULADOR!L:L,"")))*(-1),"")
E45: =IF(COUNTBLANK(D45)=1,"",_xlfn.XLOOKUP(D45,BS_CONSOLIDADO!A:A,BS_CONSOLIDADO!D:D,"")) | F45: =IF(COUNTBLANK(D45)=1,"",_xlfn.XLOOKUP(D45,BS_CONSOLIDADO!A:A,BS_CONSOLIDADO!Q:Q,"")) | G45: =IF(COUNTBLANK($D45)=1,"",_xlfn.XLOOKUP($D45,BS_CONSOLIDADO!$A:$A,BS_CONSOLIDADO!M:M,"")) | H45: =IF(COUNTBLANK(D45)=1,"",_xlfn.XLOOKUP(D45,BS_CONSOLIDADO!A:A,BS_CONSOLIDADO!N:N,"")) | I45: =IF(COUNTBLANK(D45)=1,"",_xlfn.XLOOKUP(D45,BS_CONSOLIDADO!A:A,BS_CONSOLIDADO!O:O,"")) | J45: =IF(COUNTBLANK(D45)=1,"",_xlfn.XLOOKUP(D45,BS_CONSOLIDADO!A:A,BS_CONSOLIDADO!P:P,"")) | L45: =IF(COUNTBLANK(D45)=1,"",_xlfn.XLOOKUP(D45,BS_SIMULADOR!A:A,BS_SIMULADOR!D:D,"")) | M45: =IF(COUNTBLANK(D45)=1,"",_xlfn.XLOOKUP(D45,BS_SIMULADOR!A:A,BS_SIMULADOR!Q:Q,"")) | N45: =IF(COUNTBLANK($D45)=1,"",_xlfn.XLOOKUP($D45,BS_SIMULADOR!$A:$A,BS_SIMULADOR!M:M,"")) | O45: =IF(COUNTBLANK(D45)=1,"",_xlfn.XLOOKUP(D45,BS_SIMULADOR!A:A,BS_SIMULADOR!N:N,"")) | P45: =IF(COUNTBLANK(D45)=1,"",_xlfn.XLOOKUP(D45,BS_SIMULADOR!A:A,BS_SIMULADOR!O:O,"")) | Q45: =IF(COUNTBLANK($D45)=1,"",_xlfn.XLOOKUP($D45,BS_SIMULADOR!$A:$A,BS_SIMULADOR!P:P,"")) | S45: =IFERROR(IF(COUNTBLANK(D45)=1,"",E45-L45)*(-1),"") | T45: =IFERROR(IF(COUNTBLANK($D45)=1,"",(_xlfn.XLOOKUP($D45,BS_CONSOLIDADO!$A:$A,BS_CONSOLIDADO!F:F,""))-(_xlfn.XLOOKUP($D45,BS_SIMULADOR!$A:$A,BS_SIMULADOR!F:F,"")))*(-1),"") | U45: =IFERROR(IF(COUNTBLANK(D45)=1,"",(_xlfn.XLOOKUP(D45,BS_CONSOLIDADO!A:A,BS_CONSOLIDADO!H:H,""))-(_xlfn.XLOOKUP(D45,BS_SIMULADOR!A:A,BS_SIMULADOR!H:H,"")))*(-1),"") | V45: =IFERROR(IF(COUNTBLANK(D45)=1,"",(_xlfn.XLOOKUP(D45,BS_CONSOLIDADO!A:A,BS_CONSOLIDADO!J:J,""))-(_xlfn.XLOOKUP(D45,BS_SIMULADOR!A:A,BS_SIMULADOR!J:J,"")))*(-1),"") | W45: =IFERROR(IF(COUNTBLANK($D45)=1,"",(_xlfn.XLOOKUP($D45,BS_CONSOLIDADO!$A:$A,BS_CONSOLIDADO!L:L,""))-(_xlfn.XLOOKUP($D45,BS_SIMULADOR!$A:$A,BS_SIMULADOR!L:L,"")))*(-1),"")
E46: =IF(COUNTBLANK(D46)=1,"",_xlfn.XLOOKUP(D46,BS_CONSOLIDADO!A:A,BS_CONSOLIDADO!D:D,"")) | F46: =IF(COUNTBLANK(D46)=1,"",_xlfn.XLOOKUP(D46,BS_CONSOLIDADO!A:A,BS_CONSOLIDADO!Q:Q,"")) | G46: =IF(COUNTBLANK($D46)=1,"",_xlfn.XLOOKUP($D46,BS_CONSOLIDADO!$A:$A,BS_CONSOLIDADO!M:M,"")) | H46: =IF(COUNTBLANK(D46)=1,"",_xlfn.XLOOKUP(D46,BS_CONSOLIDADO!A:A,BS_CONSOLIDADO!N:N,"")) | I46: =IF(COUNTBLANK(D46)=1,"",_xlfn.XLOOKUP(D46,BS_CONSOLIDADO!A:A,BS_CONSOLIDADO!O:O,"")) | J46: =IF(COUNTBLANK(D46)=1,"",_xlfn.XLOOKUP(D46,BS_CONSOLIDADO!A:A,BS_CONSOLIDADO!P:P,"")) | L46: =IF(COUNTBLANK(D46)=1,"",_xlfn.XLOOKUP(D46,BS_SIMULADOR!A:A,BS_SIMULADOR!D:D,"")) | M46: =IF(COUNTBLANK(D46)=1,"",_xlfn.XLOOKUP(D46,BS_SIMULADOR!A:A,BS_SIMULADOR!Q:Q,"")) | N46: =IF(COUNTBLANK($D46)=1,"",_xlfn.XLOOKUP($D46,BS_SIMULADOR!$A:$A,BS_SIMULADOR!M:M,"")) | O46: =IF(COUNTBLANK(D46)=1,"",_xlfn.XLOOKUP(D46,BS_SIMULADOR!A:A,BS_SIMULADOR!N:N,"")) | P46: =IF(COUNTBLANK(D46)=1,"",_xlfn.XLOOKUP(D46,BS_SIMULADOR!A:A,BS_SIMULADOR!O:O,"")) | Q46: =IF(COUNTBLANK($D46)=1,"",_xlfn.XLOOKUP($D46,BS_SIMULADOR!$A:$A,BS_SIMULADOR!P:P,"")) | S46: =IFERROR(IF(COUNTBLANK(D46)=1,"",E46-L46)*(-1),"") | T46: =IFERROR(IF(COUNTBLANK($D46)=1,"",(_xlfn.XLOOKUP($D46,BS_CONSOLIDADO!$A:$A,BS_CONSOLIDADO!F:F,""))-(_xlfn.XLOOKUP($D46,BS_SIMULADOR!$A:$A,BS_SIMULADOR!F:F,"")))*(-1),"") | U46: =IFERROR(IF(COUNTBLANK(D46)=1,"",(_xlfn.XLOOKUP(D46,BS_CONSOLIDADO!A:A,BS_CONSOLIDADO!H:H,""))-(_xlfn.XLOOKUP(D46,BS_SIMULADOR!A:A,BS_SIMULADOR!H:H,"")))*(-1),"") | V46: =IFERROR(IF(COUNTBLANK(D46)=1,"",(_xlfn.XLOOKUP(D46,BS_CONSOLIDADO!A:A,BS_CONSOLIDADO!J:J,""))-(_xlfn.XLOOKUP(D46,BS_SIMULADOR!A:A,BS_SIMULADOR!J:J,"")))*(-1),"") | W46: =IFERROR(IF(COUNTBLANK($D46)=1,"",(_xlfn.XLOOKUP($D46,BS_CONSOLIDADO!$A:$A,BS_CONSOLIDADO!L:L,""))-(_xlfn.XLOOKUP($D46,BS_SIMULADOR!$A:$A,BS_SIMULADOR!L:L,"")))*(-1),"")
E47: =IF(COUNTBLANK(D47)=1,"",_xlfn.XLOOKUP(D47,BS_CONSOLIDADO!A:A,BS_CONSOLIDADO!D:D,"")) | F47: =IF(COUNTBLANK(D47)=1,"",_xlfn.XLOOKUP(D47,BS_CONSOLIDADO!A:A,BS_CONSOLIDADO!Q:Q,"")) | G47: =IF(COUNTBLANK($D47)=1,"",_xlfn.XLOOKUP($D47,BS_CONSOLIDADO!$A:$A,BS_CONSOLIDADO!M:M,"")) | H47: =IF(COUNTBLANK(D47)=1,"",_xlfn.XLOOKUP(D47,BS_CONSOLIDADO!A:A,BS_CONSOLIDADO!N:N,"")) | I47: =IF(COUNTBLANK(D47)=1,"",_xlfn.XLOOKUP(D47,BS_CONSOLIDADO!A:A,BS_CONSOLIDADO!O:O,"")) | J47: =IF(COUNTBLANK(D47)=1,"",_xlfn.XLOOKUP(D47,BS_CONSOLIDADO!A:A,BS_CONSOLIDADO!P:P,"")) | L47: =IF(COUNTBLANK(D47)=1,"",_xlfn.XLOOKUP(D47,BS_SIMULADOR!A:A,BS_SIMULADOR!D:D,"")) | M47: =IF(COUNTBLANK(D47)=1,"",_xlfn.XLOOKUP(D47,BS_SIMULADOR!A:A,BS_SIMULADOR!Q:Q,"")) | N47: =IF(COUNTBLANK($D47)=1,"",_xlfn.XLOOKUP($D47,BS_SIMULADOR!$A:$A,BS_SIMULADOR!M:M,"")) | O47: =IF(COUNTBLANK(D47)=1,"",_xlfn.XLOOKUP(D47,BS_SIMULADOR!A:A,BS_SIMULADOR!N:N,"")) | P47: =IF(COUNTBLANK(D47)=1,"",_xlfn.XLOOKUP(D47,BS_SIMULADOR!A:A,BS_SIMULADOR!O:O,"")) | Q47: =IF(COUNTBLANK($D47)=1,"",_xlfn.XLOOKUP($D47,BS_SIMULADOR!$A:$A,BS_SIMULADOR!P:P,"")) | S47: =IFERROR(IF(COUNTBLANK(D47)=1,"",E47-L47)*(-1),"") | T47: =IFERROR(IF(COUNTBLANK($D47)=1,"",(_xlfn.XLOOKUP($D47,BS_CONSOLIDADO!$A:$A,BS_CONSOLIDADO!F:F,""))-(_xlfn.XLOOKUP($D47,BS_SIMULADOR!$A:$A,BS_SIMULADOR!F:F,"")))*(-1),"") | U47: =IFERROR(IF(COUNTBLANK(D47)=1,"",(_xlfn.XLOOKUP(D47,BS_CONSOLIDADO!A:A,BS_CONSOLIDADO!H:H,""))-(_xlfn.XLOOKUP(D47,BS_SIMULADOR!A:A,BS_SIMULADOR!H:H,"")))*(-1),"") | V47: =IFERROR(IF(COUNTBLANK(D47)=1,"",(_xlfn.XLOOKUP(D47,BS_CONSOLIDADO!A:A,BS_CONSOLIDADO!J:J,""))-(_xlfn.XLOOKUP(D47,BS_SIMULADOR!A:A,BS_SIMULADOR!J:J,"")))*(-1),"") | W47: =IFERROR(IF(COUNTBLANK($D47)=1,"",(_xlfn.XLOOKUP($D47,BS_CONSOLIDADO!$A:$A,BS_CONSOLIDADO!L:L,""))-(_xlfn.XLOOKUP($D47,BS_SIMULADOR!$A:$A,BS_SIMULADOR!L:L,"")))*(-1),"")
... E400: =IF(COUNTBLANK(D400)=1,"",_xlfn.XLOOKUP(D400,BS_CONSOLIDADO!A:A,BS_CONSOLIDADO!D:D,"")) | F400: =IF(COUNTBLANK(D400)=1,"",_xlfn.XLOOKUP(D400,BS_CONSOLIDADO!A:A,BS_CONSOLIDADO!Q:Q,"")) | G400: =IF(COUNTBLANK($D400)=1,"",_xlfn.XLOOKUP($D400,BS_CONSOLIDADO!$A:$A,BS_CONSOLIDADO!M:M,"")) | H400: =IF(COUNTBLANK(D400)=1,"",_xlfn.XLOOKUP(D400,BS_CONSOLIDADO!A:A,BS_CONSOLIDADO!N:N,"")) | I400: =IF(COUNTBLANK(D400)=1,"",_xlfn.XLOOKUP(D400,BS_CONSOLIDADO!A:A,BS_CONSOLIDADO!O:O,"")) | J400: =IF(COUNTBLANK(D400)=1,"",_xlfn.XLOOKUP(D400,BS_CONSOLIDADO!A:A,BS_CONSOLIDADO!P:P,"")) | L400: =IF(COUNTBLANK(D400)=1,"",_xlfn.XLOOKUP(D400,BS_SIMULADOR!A:A,BS_SIMULADOR!D:D,"")) | M400: =IF(COUNTBLANK(D400)=1,"",_xlfn.XLOOKUP(D400,BS_SIMULADOR!A:A,BS_SIMULADOR!Q:Q,"")) | N400: =IF(COUNTBLANK($D400)=1,"",_xlfn.XLOOKUP($D400,BS_SIMULADOR!$A:$A,BS_SIMULADOR!M:M,"")) | O400: =IF(COUNTBLANK(D400)=1,"",_xlfn.XLOOKUP(D400,BS_SIMULADOR!A:A,BS_SIMULADOR!N:N,"")) | P400: =IF(COUNTBLANK(D400)=1,"",_xlfn.XLOOKUP(D400,BS_SIMULADOR!A:A,BS_SIMULADOR!O:O,"")) | Q400: =IF(COUNTBLANK($D400)=1,"",_xlfn.XLOOKUP($D400,BS_SIMULADOR!$A:$A,BS_SIMULADOR!P:P,"")) | S400: =IFERROR(IF(COUNTBLANK(D400)=1,"",E400-L400)*(-1),"") | T400: =IFERROR(IF(COUNTBLANK($D400)=1,"",(_xlfn.XLOOKUP($D400,BS_CONSOLIDADO!$A:$A,BS_CONSOLIDADO!F:F,""))-(_xlfn.XLOOKUP($D400,BS_SIMULADOR!$A:$A,BS_SIMULADOR!F:F,"")))*(-1),"") | U400: =IFERROR(IF(COUNTBLANK(D400)=1,"",(_xlfn.XLOOKUP(D400,BS_CONSOLIDADO!A:A,BS_CONSOLIDADO!H:H,""))-(_xlfn.XLOOKUP(D400,BS_SIMULADOR!A:A,BS_SIMULADOR!H:H,"")))*(-1),"") | V400: =IFERROR(IF(COUNTBLANK(D400)=1,"",(_xlfn.XLOOKUP(D400,BS_CONSOLIDADO!A:A,BS_CONSOLIDADO!J:J,""))-(_xlfn.XLOOKUP(D400,BS_SIMULADOR!A:A,BS_SIMULADOR!J:J,"")))*(-1),"") | W400: =IFERROR(IF(COUNTBLANK($D400)=1,"",(_xlfn.XLOOKUP($D400,BS_CONSOLIDADO!$A:$A,BS_CONSOLIDADO!L:L,""))-(_xlfn.XLOOKUP($D400,BS_SIMULADOR!$A:$A,BS_SIMULADOR!L:L,"")))*(-1),"")

Sheet Simulador_Faixas
D1: ANTES | K1: DEPOIS | R1: DELTA
D2: # Efeti | E2: Txa Apr | F2: %FPD $ | G2: %O30M2 $ | H2: %O30M3 $ | I2: %O60M6 $ | K2: # Efeti | L2: Txa Apr | M2: %FPD $ | N2: %O30M2 $ | O2: %O30M3 $ | P2: %O60M6 $ | R2: Δ Efeti | S2: Δ $ Vl. Primeira Fatura | T2: Δ $ Saldo Mob 2 | U2: Δ $ Saldo Mob 3 | V2: Δ $ Saldo Mob 6
C3: GERAL | D3: 7559 | E3: 0.17993221 | F3: 0.10580333 | G3: 0.086896166 | H3: 0.13901439 | I3: 0.19584709 | K3: 6837 | L3: 0.16285742 | M3: 0.10569189 | N3: 0.086774282 | O3: 0.13876042 | P3: 0.19126756 | R3: -722 | S3: -238106.75 | T3: -1018413.7 | U3: -858595.4 | V3: -854699.89
A4: Pareceiros Selecionados
A5: Parceiro 17 | B5: Classificação | C5: Parceiros Selecionados | D5: # Efeti | E5: Txa Apr | F5: %FPD $ | G5: %O30M2 $ | H5: %O30M3 $ | I5: %O60M6 $ | K5: # Efeti | L5: Txa Apr | M5: %FPD $ | N5: %O30M2 $ | O5: %O30M3 $ | P5: %O60M6 $ | R5: Δ Efeti | S5: Δ $ Vl. Primeira Fatura | T5: Δ $ Saldo Mob 2 | U5: Δ $ Saldo Mob 3 | V5: Δ $ Saldo Mob 6
B6: A1 | C6: Parceiro 17 | D6: 943 | E6: 0.2099882 | F6: 0.1082029 | G6: 0.092431944 | H6: 0.16626681 | I6: 0.23754568 | K6: 22 | L6: 0.005898545 | M6: 0.23370333 | N6: 0.22230086 | O6: 0.32779764 | P6: 0.17979202 | R6: -921 | S6: -290558.32 | T6: -1278122.4 | U6: -1062958.6 | V6: -1023019.5
B7: A2 | C7: Parceiro 17 | D7: 943 | E7: 0.2099882 | F7: 0.1082029 | G7: 0.092431944 | H7: 0.16626681 | I7: 0.23754568 | K7: 141 | L7: 0.031327828 | M7: 0.13790186 | N7: 0.14525144 | O7: 0.34856668 | P7: 0.14421221 | R7: -802 | S7: -258083.45 | T7: -1141842.8 | U7: -956446.65 | V7: -973027.12
B8: B1 | C8: Parceiro 17 | D8: 943 | E8: 0.2099882 | F8: 0.1082029 | G8: 0.092431944 | H8: 0.16626681 | I8: 0.23754568 | K8: 221 | L8: 0.050858566 | M8: 0.11226351 | N8: 0.10556353 | O8: 0.25585724 | P8: 0.12757907 | R8: -722 | S8: -238106.75 | T8: -1018413.7 | U8: -858595.4 | V8: -854699.89
B9: B2 | C9: Parceiro 17 | D9: 943 | E9: 0.2099882 | F9: 0.1082029 | G9: 0.092431944 | H9: 0.16626681 | I9: 0.23754568 | K9: 396 | L9: 0.089133569 | M9: 0.10267987 | N9: 0.08638749 | O9: 0.17145704 | P9: 0.19510141 | R9: -547 | S9: -189254.2 | T9: -790143.59 | U9: -658849.8 | V9: -652687.67
B10: B3 | C10: Parceiro 17 | D10: 943 | E10: 0.2099882 | F10: 0.1082029 | G10: 0.092431944 | H10: 0.16626681 | I10: 0.23754568 | K10: 507 | L10: 0.11377638 | M10: 0.098377684 | N10: 0.091831921 | O10: 0.1649867 | P10: 0.19241717 | R10: -436 | S10: -154744.53 | T10: -650346.6 | U10: -531404.44 | V10: -488571.74
B11: C1 | C11: Parceiro 17 | D11: 943 | E11: 0.2099882 | F11: 0.1082029 | G11: 0.092431944 | H11: 0.16626681 | I11: 0.23754568 | K11: 638 | L11: 0.14130292 | M11: 0.09389288 | N11: 0.077427803 | O11: 0.1425228 | P11: 0.18809305 | R11: -305 | S11: -111678.2 | T11: -428485.68 | U11: -351324.07 | V11: -471626.9
B12: C2 | C12: Parceiro 17 | D12: 943 | E12: 0.2099882 | F12: 0.1082029 | G12: 0.092431944 | H12: 0.16626681 | I12: 0.23754568 | K12: 779 | L12: 0.17289291 | M12: 0.091124663 | N12: 0.075794068 | O12: 0.14206531 | P12: 0.20818473 | R12: -164 | S12: -62782.58 | T12: -238731.36 | U12: -188846.83 | V12: -275332.92
B13: D1 | C13: Parceiro 17 | D13: 943 | E13: 0.2099882 | F13: 0.1082029 | G13: 0.092431944 | H13: 0.16626681 | I13: 0.23754568 | K13: 937 | L13: 0.20775986 | M13: 0.10831653 | N13: 0.091729951 | O13: 0.16380518 | P13: 0.23984251 | R13: -6 | S13: -10922.73 | T13: -41768.27 | U13: -31140.46 | V13: -35350.41
B14: D2 | C14: Parceiro 17 | D14: 943 | E14: 0.2099882 | F14: 0.1082029 | G14: 0.092431944 | H14: 0.16626681 | I14: 0.23754568 | K14: 941 | L14: 0.20946389 | M14: 0.10763425 | N14: 0.091734964 | O14: 0.16337919 | P14: 0.23751709 | R14: -2 | S14: -5711.16 | T14: -16913.54 | U14: -11495.43 | V14: -20345.71

Sheet BS_CONSOLIDADO
B3: # Propostas Total | C3: # Propostas Aprovadas | D3: # Propostas Efetivadas | E3: $ Vl. FPD | F3: $ Vl. Primeira Fatura | G3: $ Saldo O30M2 | H3: $ Saldo Mob 2 | I3: $ Saldo O30M3 | J3: $ Saldo Mob 3 | K3: $ Saldo O60M6 | L3: $ Saldo Mob 6 | M3: %FPD $ | N3: %OVER30M2 | O3: %OVER30M3 | P3: %OVER60M6 | Q3: Txa Ap | R3: Txa Efe
A4: GERAL | B4: =SUM(bs_propostas!D:D) -> 71099 | C4: =SUM(bs_propostas!E:E) -> 12793 | D4: =SUM(bs_propostas!F:F) -> 7559 | E4: =SUM(E6:E399) -> 350007.53 | F4: =SUM(F6:F399) -> 3308095.7 | G4: =SUM(G6:G399) -> 1539148.4 | H4: =SUM(H6:H399) -> 17712500 | I4: =SUM(I6:I399) -> 2253966.7 | J4: =SUM(J6:J399) -> 16213909 | K4: =SUM(K6:K399) -> 4022577.3 | L4: =SUM(L6:L399) -> 19589780 | M4: =IFERROR(E4/F4,"") -> 0.10580333 | N4: =IFERROR(G4/H4,"") -> 0.086896166 | O4: =IFERROR(I4/J4,"") -> 0.13901439 | P4: =IFERROR(K4/L4,"") -> 0.20534061 | Q4: =C4/B4 -> 0.17993221 | R4: =D4/C4 -> 0.59087001
A5: {=_xlfn.UNIQUE(_xlfn._xlws.FILTER(bs_propostas!A:A, bs_propostas!A:A <> ""))} -> Parceiro
A6: Parceiro 1 | B6: =IFERROR(SUMIF(bs_propostas!$A:$A,BS_CONSOLIDADO!$A6,bs_propostas!D:D),"") -> 613 | C6: =IFERROR(SUMIF(bs_propostas!$A:$A,BS_CONSOLIDADO!$A6,bs_propostas!E:E),"") -> 111 | D6: =IFERROR(SUMIF(bs_propostas!$A:$A,BS_CONSOLIDADO!$A6,bs_propostas!F:F),"") -> 66 | E6: =IFERROR(SUMIF(bs_30M2!$A:$A,BS_CONSOLIDADO!$A6,bs_30M2!AN:AN),"") -> 1810.35 | F6: =IFERROR(SUMIF(bs_30M2!$A:$A,BS_CONSOLIDADO!$A6,bs_30M2!AI:AI),"") -> 27388.2 | G6: =IFERROR(SUMIF(bs_30M2!$A:$A,BS_CONSOLIDADO!$A6,bs_30M2!AP:AP),"") -> 15725.72 | H6: =IFERROR(SUMIF(bs_30M2!$A:$A,BS_CONSOLIDADO!$A6,bs_30M2!AK:AK),"") -> 163484.59 | I6: =IFERROR(SUMIF(bs_30M3!$A:$A,BS_CONSOLIDADO!$A6,bs_30M3!AQ:AQ),"") -> 20811.44 | J6: =IFERROR(SUMIF(bs_30M3!$A:$A,BS_CONSOLIDADO!$A6,bs_30M3!AL:AL),"") -> 141173.48 | K6: =IFERROR(SUMIF(bs_60M6!$A:$A,BS_CONSOLIDADO!$A6,bs_60M6!AR:AR),"") -> 38518.93 | L6: =IFERROR(SUMIF(bs_60M6!$A:$A,BS_CONSOLIDADO!$A6,bs_60M6!AM:AM),"") -> 178146.24 | N6: =IFERROR(G6/H6,"") -> 0.09619084 | O6: =IFERROR(I6/J6,"") -> 0.14741749 | P6: =IFERROR(K6/L6,"") -> 0.21622084 | Q6: =IFERROR(C6/B6,"") -> 0.18107667 | R6: =IFERROR(D6/C6,"") -> 0.59459459
A7: Parceiro 2 | B7: =IFERROR(SUMIF(bs_propostas!A:A,BS_CONSOLIDADO!A7,bs_propostas!D:D),"") -> 705 | C7: =IFERROR(SUMIF(bs_propostas!$A:$A,BS_CONSOLIDADO!$A7,bs_propostas!E:E),"") -> 138 | D7: =IFERROR(SUMIF(bs_propostas!$A:$A,BS_CONSOLIDADO!$A7,bs_propostas!F:F),"") -> 83 | E7: =IFERROR(SUMIF(bs_30M2!$A:$A,BS_CONSOLIDADO!$A7,bs_30M2!AN:AN),"") -> 5171.66 | F7: =IFERROR(SUMIF(bs_30M2!$A:$A,BS_CONSOLIDADO!$A7,bs_30M2!AI:AI),"") -> 46149.54 | G7: =IFERROR(SUMIF(bs_30M2!$A:$A,BS_CONSOLIDADO!$A7,bs_30M2!AP:AP),"") -> 32705.02 | H7: =IFERROR(SUMIF(bs_30M2!$A:$A,BS_CONSOLIDADO!$A7,bs_30M2!AK:AK),"") -> 261039.93 | I7: =IFERROR(SUMIF(bs_30M3!$A:$A,BS_CONSOLIDADO!$A7,bs_30M3!AQ:AQ),"") -> 62657.93 | J7: =IFERROR(SUMIF(bs_30M3!$A:$A,BS_CONSOLIDADO!$A7,bs_30M3!AL:AL),"") -> 287946.26 | K7: =IFERROR(SUMIF(bs_60M6!$A:$A,BS_CONSOLIDADO!$A7,bs_60M6!AR:AR),"") -> 79041.65 | L7: =IFERROR(SUMIF(bs_60M6!$A:$A,BS_CONSOLIDADO!$A7,bs_60M6!AM:AM),"") -> 238068.32 | M7: =IFERROR(E7/F7,"") -> 0.11206309 | N7: =IFERROR(G7/H7,"") -> 0.12528742 | O7: =IFERROR(I7/J7,"") -> 0.21760286 | P7: =IFERROR(K7/L7,"") -> 0.33201247 | Q7: =IFERROR(C7/B7,"") -> 0.19574468 | R7: =IFERROR(D7/C7,"") -> 0.60144928
A8: Parceiro 3 | B8: =IFERROR(SUMIF(bs_propostas!A:A,BS_CONSOLIDADO!A8,bs_propostas!D:D),"") -> 2581 | C8: =IFERROR(SUMIF(bs_propostas!$A:$A,BS_CONSOLIDADO!$A8,bs_propostas!E:E),"") -> 532 | D8: =IFERROR(SUMIF(bs_propostas!$A:$A,BS_CONSOLIDADO!$A8,bs_propostas!F:F),"") -> 288 | E8: =IFERROR(SUMIF(bs_30M2!$A:$A,BS_CONSOLIDADO!$A8,bs_30M2!AN:AN),"") -> 17497.79 | F8: =IFERROR(SUMIF(bs_30M2!$A:$A,BS_CONSOLIDADO!$A8,bs_30M2!AI:AI),"") -> 148062.4 | G8: =IFERROR(SUMIF(bs_30M2!$A:$A,BS_CONSOLIDADO!$A8,bs_30M2!AP:AP),"") -> 77306.08 | H8: =IFERROR(SUMIF(bs_30M2!$A:$A,BS_CONSOLIDADO!$A8,bs_30M2!AK:AK),"") -> 806458.27 | I8: =IFERROR(SUMIF(bs_30M3!$A:$A,BS_CONSOLIDADO!$A8,bs_30M3!AQ:AQ),"") -> 125482.89 | J8: =IFERROR(SUMIF(bs_30M3!$A:$A,BS_CONSOLIDADO!$A8,bs_30M3!AL:AL),"") -> 772019.92 | K8: =IFERROR(SUMIF(bs_60M6!$A:$A,BS_CONSOLIDADO!$A8,bs_60M6!AR:AR),"") -> 135551.51 | L8: =IFERROR(SUMIF(bs_60M6!$A:$A,BS_CONSOLIDADO!$A8,bs_60M6!AM:AM),"") -> 745012.81 | M8: =IFERROR(E8/F8,"") -> 0.11817848 | N8: =IFERROR(G8/H8,"") -> 0.095858748 | O8: =IFERROR(I8/J8,"") -> 0.16253841 | P8: =IFERROR(K8/L8,"") -> 0.18194521 | Q8: =IFERROR(C8/B8,"") -> 0.20612166 | R8: =IFERROR(D8/C8,"") -> 0.54135338
A9: Parceiro 4 | B9: =IFERROR(SUMIF(bs_propostas!A:A,BS_CONSOLIDADO!A9,bs_propostas!D:D),"") -> 855 | C9: =IFERROR(SUMIF(bs_propostas!$A:$A,BS_CONSOLIDADO!$A9,bs_propostas!E:E),"") -> 154 | D9: =IFERROR(SUMIF(bs_propostas!$A:$A,BS_CONSOLIDADO!$A9,bs_propostas!F:F),"") -> 92 | E9: =IFERROR(SUMIF(bs_30M2!$A:$A,BS_CONSOLIDADO!$A9,bs_30M2!AN:AN),"") -> 7459.67 | F9: =IFERROR(SUMIF(bs_30M2!$A:$A,BS_CONSOLIDADO!$A9,bs_30M2!AI:AI),"") -> 54447.74 | G9: =IFERROR(SUMIF(bs_30M2!$A:$A,BS_CONSOLIDADO!$A9,bs_30M2!AP:AP),"") -> 17223.27 | H9: =IFERROR(SUMIF(bs_30M2!$A:$A,BS_CONSOLIDADO!$A9,bs_30M2!AK:AK),"") -> 258713.71 | I9: =IFERROR(SUMIF(bs_30M3!$A:$A,BS_CONSOLIDADO!$A9,bs_30M3!AQ:AQ),"") -> 24373.34 | J9: =IFERROR(SUMIF(bs_30M3!$A:$A,BS_CONSOLIDADO!$A9,bs_30M3!AL:AL),"") -> 237774.34 | K9: =IFERROR(SUMIF(bs_60M6!$A:$A,BS_CONSOLIDADO!$A9,bs_60M6!AR:AR),"") -> 36739.55 | L9: =IFERROR(SUMIF(bs_60M6!$A:$A,BS_CONSOLIDADO!$A9,bs_60M6!AM:AM),"") -> 176015.55 | M9: =IFERROR(E9/F9,"") -> 0.13700605 | N9: =IFERROR(G9/H9,"") -> 0.066572699 | O9: =IFERROR(I9/J9,"") -> 0.10250618 | P9: =IFERROR(K9/L9,"") -> 0.208729 | Q9: =IFERROR(C9/B9,"") -> 0.18011696 | R9: =IFERROR(D9/C9,"") -> 0.5974026
A10: Parceiro 5 | B10: =IFERROR(SUMIF(bs_propostas!A:A,BS_CONSOLIDADO!A10,bs_propostas!D:D),"") -> 1046 | C10: =IFERROR(SUMIF(bs_propostas!$A:$A,BS_CONSOLIDADO!$A10,bs_propostas!E:E),"") -> 237 | D10: =IFERROR(SUMIF(bs_propostas!$A:$A,BS_CONSOLIDADO!$A10,bs_propostas!F:F),"") -> 140 | E10: =IFERROR(SUMIF(bs_30M2!$A:$A,BS_CONSOLIDADO!$A10,bs_30M2!AN:AN),"") -> 1342.84 | F10: =IFERROR(SUMIF(bs_30M2!$A:$A,BS_CONSOLIDADO!$A10,bs_30M2!AI:AI),"") -> 51234.36 | G10: =IFERROR(SUMIF(bs_30M2!$A:$A,BS_CONSOLIDADO!$A10,bs_30M2!AP:AP),"") -> 9141.87 | H10: =IFERROR(SUMIF(bs_30M2!$A:$A,BS_CONSOLIDADO!$A10,bs_30M2!AK:AK),"") -> 287339.25 | I10: =IFERROR(SUMIF(bs_30M3!$A:$A,BS_CONSOLIDADO!$A10,bs_30M3!AQ:AQ),"") -> 14806.78 | J10: =IFERROR(SUMIF(bs_30M3!$A:$A,BS_CONSOLIDADO!$A10,bs_30M3!AL:AL),"") -> 244923.04 | K10: =IFERROR(SUMIF(bs_60M6!$A:$A,BS_CONSOLIDADO!$A10,bs_60M6!AR:AR),"") -> 14700.52 | L10: =IFERROR(SUMIF(bs_60M6!$A:$A,BS_CONSOLIDADO!$A10,bs_60M6!AM:AM),"") -> 259726.47 | M10: =IFERROR(E10/F10,"") -> 0.026209755 | N10: =IFERROR(G10/H10,"") -> 0.031815598 | O10: =IFERROR(I10/J10,"") -> 0.060454827 | P10: =IFERROR(K10/L10,"") -> 0.056600007 | Q10: =IFERROR(C10/B10,"") -> 0.22657744 | R10: =IFERROR(D10/C10,"") -> 0.5907173
A11: Parceiro 6 | B11: =IFERROR(SUMIF(bs_propostas!A:A,BS_CONSOLIDADO!A11,bs_propostas!D:D),"") -> 936 | C11: =IFERROR(SUMIF(bs_propostas!$A:$A,BS_CONSOLIDADO!$A11,bs_propostas!E:E),"") -> 196 | D11: =IFERROR(SUMIF(bs_propostas!$A:$A,BS_CONSOLIDADO!$A11,bs_propostas!F:F),"") -> 80 | E11: =IFERROR(SUMIF(bs_30M2!$A:$A,BS_CONSOLIDADO!$A11,bs_30M2!AN:AN),"") -> 1655.12 | F11: =IFERROR(SUMIF(bs_30M2!$A:$A,BS_CONSOLIDADO!$A11,bs_30M2!AI:AI),"") -> 30044.29 | G11: =IFERROR(SUMIF(bs_30M2!$A:$A,BS_CONSOLIDADO!$A11,bs_30M2!AP:AP),"") -> 12129.98 | H11: =IFERROR(SUMIF(bs_30M2!$A:$A,BS_CONSOLIDADO!$A11,bs_30M2!AK:AK),"") -> 191435.37 | I11: =IFERROR(SUMIF(bs_30M3!$A:$A,BS_CONSOLIDADO!$A11,bs_30M3!AQ:AQ),"") -> 25989 | J11: =IFERROR(SUMIF(bs_30M3!$A:$A,BS_CONSOLIDADO!$A11,bs_30M3!AL:AL),"") -> 154352.13 | K11: =IFERROR(SUMIF(bs_60M6!$A:$A,BS_CONSOLIDADO!$A11,bs_60M6!AR:AR),"") -> 32888.38 | L11: =IFERROR(SUMIF(bs_60M6!$A:$A,BS_CONSOLIDADO!$A11,bs_60M6!AM:AM),"") -> 202246.13 | M11: =IFERROR(E11/F11,"") -> 0.055089336 | N11: =IFERROR(G11/H11,"") -> 0.063363317 | O11: =IFERROR(I11/J11,"") -> 0.16837474 | P11: =IFERROR(K11/L11,"") -> 0.16261562 | Q11: =IFERROR(C11/B11,"") -> 0.20940171 | R11: =IFERROR(D11/C11,"") -> 0.40816327
A12: Parceiro 7 | B12: =IFERROR(SUMIF(bs_propostas!A:A,BS_CONSOLIDADO!A12,bs_propostas!D:D),"") -> 243 | C12: =IFERROR(SUMIF(bs_propostas!$A:$A,BS_CONSOLIDADO!$A12,bs_propostas!E:E),"") -> 49 | D12: =IFERROR(SUMIF(bs_propostas!$A:$A,BS_CONSOLIDADO!$A12,bs_propostas!F:F),"") -> 33 | E12: =IFERROR(SUMIF(bs_30M2!$A:$A,BS_CONSOLIDADO!$A12,bs_30M2!AN:AN),"") -> 2962.85 | F12: =IFERROR(SUMIF(bs_30M2!$A:$A,BS_CONSOLIDADO!$A12,bs_30M2!AI:AI),"") -> 19720.84 | G12: =IFERROR(SUMIF(bs_30M2!$A:$A,BS_CONSOLIDADO!$A12,bs_30M2!AP:AP),"") -> 15559.39 | H12: =IFERROR(SUMIF(bs_30M2!$A:$A,BS_CONSOLIDADO!$A12,bs_30M2!AK:AK),"") -> 89266.51 | I12: =IFERROR(SUMIF(bs_30M3!$A:$A,BS_CONSOLIDADO!$A12,bs_30M3!AQ:AQ),"") -> 18156.42 | J12: =IFERROR(SUMIF(bs_30M3!$A:$A,BS_CONSOLIDADO!$A12,bs_30M3!AL:AL),"") -> 82002.52 | K12: =IFERROR(SUMIF(bs_60M6!$A:$A,BS_CONSOLIDADO!$A12,bs_60M6!AR:AR),"") -> 17669.5 | L12: =IFERROR(SUMIF(bs_60M6!$A:$A,BS_CONSOLIDADO!$A12,bs_60M6!AM:AM),"") -> 82551.62 | M12: =IFERROR(E12/F12,"") -> 0.15023954 | N12: =IFERROR(G12/H12,"") -> 0.17430266 | O12: =IFERROR(I12/J12,"") -> 0.22141295 | P12: =IFERROR(K12/L12,"") -> 0.21404183 | Q12: =IFERROR(C12/B12,"") -> 0.20164609 | R12: =IFERROR(D12/C12,"") -> 0.67346939
A13: Parceiro 8 | B13: =IFERROR(SUMIF(bs_propostas!A:A,BS_CONSOLIDADO!A13,bs_propostas!D:D),"") -> 6458 | C13: =IFERROR(SUMIF(bs_propostas!$A:$A,BS_CONSOLIDADO!$A13,bs_propostas!E:E),"") -> 835 | D13: =IFERROR(SUMIF(bs_propostas!$A:$A,BS_CONSOLIDADO!$A13,bs_propostas!F:F),"") -> 499 | E13: =IFERROR(SUMIF(bs_30M2!$A:$A,BS_CONSOLIDADO!$A13,bs_30M2!AN:AN),"") -> 26763.84 | F13: =IFERROR(SUMIF(bs_30M2!$A:$A,BS_CONSOLIDADO!$A13,bs_30M2!AI:AI),"") -> 219539.4 | G13: =IFERROR(SUMIF(bs_30M2!$A:$A,BS_CONSOLIDADO!$A13,bs_30M2!AP:AP),"") -> 136947.64 | H13: =IFERROR(SUMIF(bs_30M2!$A:$A,BS_CONSOLIDADO!$A13,bs_30M2!AK:AK),"") -> 1346669.6 | I13: =IFERROR(SUMIF(bs_30M3!$A:$A,BS_CONSOLIDADO!$A13,bs_30M3!AQ:AQ),"") -> 198476.84 | J13: =IFERROR(SUMIF(bs_30M3!$A:$A,BS_CONSOLIDADO!$A13,bs_30M3!AL:AL),"") -> 1235128.1 | K13: =IFERROR(SUMIF(bs_60M6!$A:$A,BS_CONSOLIDADO!$A13,bs_60M6!AR:AR),"") -> 426336.97 | L13: =IFERROR(SUMIF(bs_60M6!$A:$A,BS_CONSOLIDADO!$A13,bs_60M6!AM:AM),"") -> 1903300.7 | M13: =IFERROR(E13/F13,"") -> 0.12190905 | N13: =IFERROR(G13/H13,"") -> 0.10169357 | O13: =IFERROR(I13/J13,"") -> 0.16069333 | P13: =IFERROR(K13/L13,"") -> 0.22399874 | Q13: =IFERROR(C13/B13,"") -> 0.129297 | R13: =IFERROR(D13/C13,"") -> 0.59760479
A14: Parceiro 9 | B14: =IFERROR(SUMIF(bs_propostas!A:A,BS_CONSOLIDADO!A14,bs_propostas!D:D),"") -> 4195 | C14: =IFERROR(SUMIF(bs_propostas!$A:$A,BS_CONSOLIDADO!$A14,bs_propostas!E:E),"") -> 634 | D14: =IFERROR(SUMIF(bs_propostas!$A:$A,BS_CONSOLIDADO!$A14,bs_propostas!F:F),"") -> 418 | E14: =IFERROR(SUMIF(bs_30M2!$A:$A,BS_CONSOLIDADO!$A14,bs_30M2!AN:AN),"") -> 11685.16 | F14: =IFERROR(SUMIF(bs_30M2!$A:$A,BS_CONSOLIDADO!$A14,bs_30M2!AI:AI),"") -> 187226.47 | G14: =IFERROR(SUMIF(bs_30M2!$A:$A,BS_CONSOLIDADO!$A14,bs_30M2!AP:AP),"") -> 61706.85 | H14: =IFERROR(SUMIF(bs_30M2!$A:$A,BS_CONSOLIDADO!$A14,bs_30M2!AK:AK),"") -> 944946.56 | I14: =IFERROR(SUMIF(bs_30M3!$A:$A,BS_CONSOLIDADO!$A14,bs_30M3!AQ:AQ),"") -> 113199.44 | J14: =IFERROR(SUMIF(bs_30M3!$A:$A,BS_CONSOLIDADO!$A14,bs_30M3!AL:AL),"") -> 939327.57 | K14: =IFERROR(SUMIF(bs_60M6!$A:$A,BS_CONSOLIDADO!$A14,bs_60M6!AR:AR),"") -> 817423.65 | L14: =IFERROR(SUMIF(bs_60M6!$A:$A,BS_CONSOLIDADO!$A14,bs_60M6!AM:AM),"") -> 2983161.8 | M14: =IFERROR(E14/F14,"") -> 0.062411901 | N14: =IFERROR(G14/H14,"") -> 0.065301947 | O14: =IFERROR(I14/J14,"") -> 0.12051114 | P14: =IFERROR(K14/L14,"") -> 0.27401251 | Q14: =IFERROR(C14/B14,"") -> 0.1511323 | R14: =IFERROR(D14/C14,"") -> 0.65930599
A15: Parceiro 10 | B15: =IFERROR(SUMIF(bs_propostas!A:A,BS_CONSOLIDADO!A15,bs_propostas!D:D),"") -> 44683 | C15: =IFERROR(SUMIF(bs_propostas!$A:$A,BS_CONSOLIDADO!$A15,bs_propostas!E:E),"") -> 8116 | D15: =IFERROR(SUMIF(bs_propostas!$A:$A,BS_CONSOLIDADO!$A15,bs_propostas!F:F),"") -> 4812 | E15: =IFERROR(SUMIF(bs_30M2!$A:$A,BS_CONSOLIDADO!$A15,bs_30M2!AN:AN),"") -> 211075.37 | F15: =IFERROR(SUMIF(bs_30M2!$A:$A,BS_CONSOLIDADO!$A15,bs_30M2!AI:AI),"") -> 2115047.8 | G15: =IFERROR(SUMIF(bs_30M2!$A:$A,BS_CONSOLIDADO!$A15,bs_30M2!AP:AP),"") -> 944535.85 | H15: =IFERROR(SUMIF(bs_30M2!$A:$A,BS_CONSOLIDADO!$A15,bs_30M2!AK:AK),"") -> 11568801 | I15: =IFERROR(SUMIF(bs_30M3!$A:$A,BS_CONSOLIDADO!$A15,bs_30M3!AQ:AQ),"") -> 1322836.8 | J15: =IFERROR(SUMIF(bs_30M3!$A:$A,BS_CONSOLIDADO!$A15,bs_30M3!AL:AL),"") -> 10593676 | K15: =IFERROR(SUMIF(bs_60M6!$A:$A,BS_CONSOLIDADO!$A15,bs_60M6!AR:AR),"") -> 1952582.7 | L15: =IFERROR(SUMIF(bs_60M6!$A:$A,BS_CONSOLIDADO!$A15,bs_60M6!AM:AM),"") -> 11054465 | M15: =IFERROR(E15/F15,"") -> 0.099796973 | N15: =IFERROR(G15/H15,"") -> 0.081645094 | O15: =IFERROR(I15/J15,"") -> 0.12487042 | P15: =IFERROR(K15/L15,"") -> 0.17663295 | Q15: =IFERROR(C15/B15,"") -> 0.18163507 | R15: =IFERROR(D15/C15,"") -> 0.59290291
A16: Parceiro 11 | B16: =IFERROR(SUMIF(bs_propostas!A:A,BS_CONSOLIDADO!A16,bs_propostas!D:D),"") -> 35 | C16: =IFERROR(SUMIF(bs_propostas!$A:$A,BS_CONSOLIDADO!$A16,bs_propostas!E:E),"") -> 8 | D16: =IFERROR(SUMIF(bs_propostas!$A:$A,BS_CONSOLIDADO!$A16,bs_propostas!F:F),"") -> 4 | E16: =IFERROR(SUMIF(bs_30M2!$A:$A,BS_CONSOLIDADO!$A16,bs_30M2!AN:AN),"") -> 12861.25 | F16: =IFERROR(SUMIF(bs_30M2!$A:$A,BS_CONSOLIDADO!$A16,bs_30M2!AI:AI),"") -> 44299.69 | G16: =IFERROR(SUMIF(bs_30M2!$A:$A,BS_CONSOLIDADO!$A16,bs_30M2!AP:AP),"") -> 60274.3 | H16: =IFERROR(SUMIF(bs_30M2!$A:$A,BS_CONSOLIDADO!$A16,bs_30M2!AK:AK),"") -> 184159.11 | I16: =IFERROR(SUMIF(bs_30M3!$A:$A,BS_CONSOLIDADO!$A16,bs_30M3!AQ:AQ),"") -> 96535.39 | J16: =IFERROR(SUMIF(bs_30M3!$A:$A,BS_CONSOLIDADO!$A16,bs_30M3!AL:AL),"") -> 245413.82 | K16: =IFERROR(SUMIF(bs_60M6!$A:$A,BS_CONSOLIDADO!$A16,bs_60M6!AR:AR),"") -> 102956.78 | L16: =IFERROR(SUMIF(bs_60M6!$A:$A,BS_CONSOLIDADO!$A16,bs_60M6!AM:AM),"") -> 323056.47 | M16: =IFERROR(E16/F16,"") -> 0.2903237 | N16: =IFERROR(G16/H16,"") -> 0.3272947 | O16: =IFERROR(I16/J16,"") -> 0.39335759 | P16: =IFERROR(K16/L16,"") -> 0.31869592 | Q16: =IFERROR(C16/B16,"") -> 0.22857143 | R16: =IFERROR(D16/C16,"") -> 0.5
A17: Parceiro 12 | B17: =IFERROR(SUMIF(bs_propostas!A:A,BS_CONSOLIDADO!A17,bs_propostas!D:D),"") -> 43 | C17: =IFERROR(SUMIF(bs_propostas!$A:$A,BS_CONSOLIDADO!$A17,bs_propostas!E:E),"") -> 9 | D17: =IFERROR(SUMIF(bs_propostas!$A:$A,BS_CONSOLIDADO!$A17,bs_propostas!F:F),"") -> 4 | E17: =IFERROR(SUMIF(bs_30M2!$A:$A,BS_CONSOLIDADO!$A17,bs_30M2!AN:AN),"") -> 3980.15 | F17: =IFERROR(SUMIF(bs_30M2!$A:$A,BS_CONSOLIDADO!$A17,bs_30M2!AI:AI),"") -> 8950.67 | G17: =IFERROR(SUMIF(bs_30M2!$A:$A,BS_CONSOLIDADO!$A17,bs_30M2!AP:AP),"") -> 9075.54 | H17: =IFERROR(SUMIF(bs_30M2!$A:$A,BS_CONSOLIDADO!$A17,bs_30M2!AK:AK),"") -> 34368.2 | I17: =IFERROR(SUMIF(bs_30M3!$A:$A,BS_CONSOLIDADO!$A17,bs_30M3!AQ:AQ),"") -> 13574.99 | J17: =IFERROR(SUMIF(bs_30M3!$A:$A,BS_CONSOLIDADO!$A17,bs_30M3!AL:AL),"") -> 28699.78 | K17: =IFERROR(SUMIF(bs_60M6!$A:$A,BS_CONSOLIDADO!$A17,bs_60M6!AR:AR),"") -> 36529.2 | L17: =IFERROR(SUMIF(bs_60M6!$A:$A,BS_CONSOLIDADO!$A17,bs_60M6!AM:AM),"") -> 57724.48 | M17: =IFERROR(E17/F17,"") -> 0.44467621 | N17: =IFERROR(G17/H17,"") -> 0.26406795 | O17: =IFERROR(I17/J17,"") -> 0.47299979 | P17: =IFERROR(K17/L17,"") -> 0.63281991 | Q17: =IFERROR(C17/B17,"") -> 0.20930233 | R17: =IFERROR(D17/C17,"") -> 0.44444444
A18: Parceiro 13 | B18: =IFERROR(SUMIF(bs_propostas!A:A,BS_CONSOLIDADO!A18,bs_propostas!D:D),"") -> 535 | C18: =IFERROR(SUMIF(bs_propostas!$A:$A,BS_CONSOLIDADO!$A18,bs_propostas!E:E),"") -> 84 | D18: =IFERROR(SUMIF(bs_propostas!$A:$A,BS_CONSOLIDADO!$A18,bs_propostas!F:F),"") -> 47 | E18: =IFERROR(SUMIF(bs_30M2!$A:$A,BS_CONSOLIDADO!$A18,bs_30M2!AN:AN),"") -> 1387.47 | F18: =IFERROR(SUMIF(bs_30M2!$A:$A,BS_CONSOLIDADO!$A18,bs_30M2!AI:AI),"") -> 14178.34 | G18: =IFERROR(SUMIF(bs_30M2!$A:$A,BS_CONSOLIDADO!$A18,bs_30M2!AP:AP),"") -> 7781.25 | H18: =IFERROR(SUMIF(bs_30M2!$A:$A,BS_CONSOLIDADO!$A18,bs_30M2!AK:AK),"") -> 94040.61 | I18: =IFERROR(SUMIF(bs_30M3!$A:$A,BS_CONSOLIDADO!$A18,bs_30M3!AQ:AQ),"") -> 3163.38 | J18: =IFERROR(SUMIF(bs_30M3!$A:$A,BS_CONSOLIDADO!$A18,bs_30M3!AL:AL),"") -> 37145.02 | K18: =IFERROR(SUMIF(bs_60M6!$A:$A,BS_CONSOLIDADO!$A18,bs_60M6!AR:AR),"") -> 20067.52 | L18: =IFERROR(SUMIF(bs_60M6!$A:$A,BS_CONSOLIDADO!$A18,bs_60M6!AM:AM),"") -> 89797.81 | M18: =IFERROR(E18/F18,"") -> 0.097858423 | N18: =IFERROR(G18/H18,"") -> 0.082743508 | O18: =IFERROR(I18/J18,"") -> 0.085162964 | P18: =IFERROR(K18/L18,"") -> 0.22347449 | Q18: =IFERROR(C18/B18,"") -> 0.15700935 | R18: =IFERROR(D18/C18,"") -> 0.55952381
... A25: Parceiro 20 | B25: =IFERROR(SUMIF(bs_propostas!A:A,BS_CONSOLIDADO!A25,bs_propostas!D:D),"") -> 250 | C25: =IFERROR(SUMIF(bs_propostas!$A:$A,BS_CONSOLIDADO!$A25,bs_propostas!E:E),"") -> 34 | D25: =IFERROR(SUMIF(bs_propostas!$A:$A,BS_CONSOLIDADO!$A25,bs_propostas!F:F),"") -> 21 | E25: =IFERROR(SUMIF(bs_30M2!$A:$A,BS_CONSOLIDADO!$A25,bs_30M2!AN:AN),"") -> 5747.51 | F25: =IFERROR(SUMIF(bs_30M2!$A:$A,BS_CONSOLIDADO!$A25,bs_30M2!AI:AI),"") -> 18391.56 | G25: =IFERROR(SUMIF(bs_30M2!$A:$A,BS_CONSOLIDADO!$A25,bs_30M2!AP:AP),"") -> 3727.58 | H25: =IFERROR(SUMIF(bs_30M2!$A:$A,BS_CONSOLIDADO!$A25,bs_30M2!AK:AK),"") -> 88125.34 | I25: =IFERROR(SUMIF(bs_30M3!$A:$A,BS_CONSOLIDADO!$A25,bs_30M3!AQ:AQ),"") -> 11386.05 | J25: =IFERROR(SUMIF(bs_30M3!$A:$A,BS_CONSOLIDADO!$A25,bs_30M3!AL:AL),"") -> 59343.53 | K25: =IFERROR(SUMIF(bs_60M6!$A:$A,BS_CONSOLIDADO!$A25,bs_60M6!AR:AR),"") -> 0 | L25: =IFERROR(SUMIF(bs_60M6!$A:$A,BS_CONSOLIDADO!$A25,bs_60M6!AM:AM),"") -> 0 | M25: =IFERROR(E25/F25,"") -> 0.31250802 | N25: =IFERROR(G25/H25,"") -> 0.042298617 | O25: =IFERROR(I25/J25,"") -> 0.19186675 | P25: =IFERROR(K25/L25,"") | Q25: =IFERROR(C25/B25,"") -> 0.136 | R25: =IFERROR(D25/C25,"") -> 0.61764706
B26: =IFERROR(SUMIF(bs_propostas!A:A,BS_CONSOLIDADO!A26,bs_propostas!D:D),"") -> 0 | C26: =IFERROR(SUMIF(bs_propostas!$A:$A,BS_CONSOLIDADO!$A26,bs_propostas!E:E),"") -> 0 | D26: =IFERROR(SUMIF(bs_propostas!$A:$A,BS_CONSOLIDADO!$A26,bs_propostas!F:F),"") -> 0 | E26: =IFERROR(SUMIF(bs_30M2!$A:$A,BS_CONSOLIDADO!$A26,bs_30M2!AN:AN),"") -> 0 | F26: =IFERROR(SUMIF(bs_30M2!$A:$A,BS_CONSOLIDADO!$A26,bs_30M2!AI:AI),"") -> 0 | G26: =IFERROR(SUMIF(bs_30M2!$A:$A,BS_CONSOLIDADO!$A26,bs_30M2!AP:AP),"") -> 0 | H26: =IFERROR(SUMIF(bs_30M2!$A:$A,BS_CONSOLIDADO!$A26,bs_30M2!AK:AK),"") -> 0 | I26: =IFERROR(SUMIF(bs_30M3!$A:$A,BS_CONSOLIDADO!$A26,bs_30M3!AQ:AQ),"") -> 0 | J26: =IFERROR(SUMIF(bs_30M3!$A:$A,BS_CONSOLIDADO!$A26,bs_30M3!AL:AL),"") -> 0 | K26: =IFERROR(SUMIF(bs_60M6!$A:$A,BS_CONSOLIDADO!$A26,bs_60M6!AR:AR),"") -> 0 | L26: =IFERROR(SUMIF(bs_60M6!$A:$A,BS_CONSOLIDADO!$A26,bs_60M6!AM:AM),"") -> 0 | M26: =IFERROR(E26/F26,"") | N26: =IFERROR(G26/H26,"") | O26: =IFERROR(I26/J26,"") | P26: =IFERROR(K26/L26,"") | Q26: =IFERROR(C26/B26,"") | R26: =IFERROR(D26/C26,"")
B27: =IFERROR(SUMIF(bs_propostas!A:A,BS_CONSOLIDADO!A27,bs_propostas!D:D),"") -> 0 | C27: =IFERROR(SUMIF(bs_propostas!$A:$A,BS_CONSOLIDADO!$A27,bs_propostas!E:E),"") -> 0 | D27: =IFERROR(SUMIF(bs_propostas!$A:$A,BS_CONSOLIDADO!$A27,bs_propostas!F:F),"") -> 0 | E27: =IFERROR(SUMIF(bs_30M2!$A:$A,BS_CONSOLIDADO!$A27,bs_30M2!AN:AN),"") -> 0 | F27: =IFERROR(SUMIF(bs_30M2!$A:$A,BS_CONSOLIDADO!$A27,bs_30M2!AI:AI),"") -> 0 | G27: =IFERROR(SUMIF(bs_30M2!$A:$A,BS_CONSOLIDADO!$A27,bs_30M2!AP:AP),"") -> 0 | H27: =IFERROR(SUMIF(bs_30M2!$A:$A,BS_CONSOLIDADO!$A27,bs_30M2!AK:AK),"") -> 0 | I27: =IFERROR(SUMIF(bs_30M3!$A:$A,BS_CONSOLIDADO!$A27,bs_30M3!AQ:AQ),"") -> 0 | J27: =IFERROR(SUMIF(bs_30M3!$A:$A,BS_CONSOLIDADO!$A27,bs_30M3!AL:AL),"") -> 0 | K27: =IFERROR(SUMIF(bs_60M6!$A:$A,BS_CONSOLIDADO!$A27,bs_60M6!AR:AR),"") -> 0 | L27: =IFERROR(SUMIF(bs_60M6!$A:$A,BS_CONSOLIDADO!$A27,bs_60M6!AM:AM),"") -> 0 | M27: =IFERROR(E27/F27,"") | N27: =IFERROR(G27/H27,"") | O27: =IFERROR(I27/J27,"") | P27: =IFERROR(K27/L27,"") | Q27: =IFERROR(C27/B27,"") | R27: =IFERROR(D27/C27,"")
B28: =IFERROR(SUMIF(bs_propostas!A:A,BS_CONSOLIDADO!A28,bs_propostas!D:D),"") -> 0 | C28: =IFERROR(SUMIF(bs_propostas!$A:$A,BS_CONSOLIDADO!$A28,bs_propostas!E:E),"") -> 0 | D28: =IFERROR(SUMIF(bs_propostas!$A:$A,BS_CONSOLIDADO!$A28,bs_propostas!F:F),"") -> 0 | E28: =IFERROR(SUMIF(bs_30M2!$A:$A,BS_CONSOLIDADO!$A28,bs_30M2!AN:AN),"") -> 0 | F28: =IFERROR(SUMIF(bs_30M2!$A:$A,BS_CONSOLIDADO!$A28,bs_30M2!AI:AI),"") -> 0 | G28: =IFERROR(SUMIF(bs_30M2!$A:$A,BS_CONSOLIDADO!$A28,bs_30M2!AP:AP),"") -> 0 | H28: =IFERROR(SUMIF(bs_30M2!$A:$A,BS_CONSOLIDADO!$A28,bs_30M2!AK:AK),"") -> 0 | I28: =IFERROR(SUMIF(bs_30M3!$A:$A,BS_CONSOLIDADO!$A28,bs_30M3!AQ:AQ),"") -> 0 | J28: =IFERROR(SUMIF(bs_30M3!$A:$A,BS_CONSOLIDADO!$A28,bs_30M3!AL:AL),"") -> 0 | K28: =IFERROR(SUMIF(bs_60M6!$A:$A,BS_CONSOLIDADO!$A28,bs_60M6!AR:AR),"") -> 0 | L28: =IFERROR(SUMIF(bs_60M6!$A:$A,BS_CONSOLIDADO!$A28,bs_60M6!AM:AM),"") -> 0 | M28: =IFERROR(E28/F28,"") | N28: =IFERROR(G28/H28,"") | O28: =IFERROR(I28/J28,"") | P28: =IFERROR(K28/L28,"") | Q28: =IFERROR(C28/B28,"") | R28: =IFERROR(D28/C28,"")
B29: =IFERROR(SUMIF(bs_propostas!A:A,BS_CONSOLIDADO!A29,bs_propostas!D:D),"") -> 0 | C29: =IFERROR(SUMIF(bs_propostas!$A:$A,BS_CONSOLIDADO!$A29,bs_propostas!E:E),"") -> 0 | D29: =IFERROR(SUMIF(bs_propostas!$A:$A,BS_CONSOLIDADO!$A29,bs_propostas!F:F),"") -> 0 | E29: =IFERROR(SUMIF(bs_30M2!$A:$A,BS_CONSOLIDADO!$A29,bs_30M2!AN:AN),"") -> 0 | F29: =IFERROR(SUMIF(bs_30M2!$A:$A,BS_CONSOLIDADO!$A29,bs_30M2!AI:AI),"") -> 0 | G29: =IFERROR(SUMIF(bs_30M2!$A:$A,BS_CONSOLIDADO!$A29,bs_30M2!AP:AP),"") -> 0 | H29: =IFERROR(SUMIF(bs_30M2!$A:$A,BS_CONSOLIDADO!$A29,bs_30M2!AK:AK),"") -> 0 | I29: =IFERROR(SUMIF(bs_30M3!$A:$A,BS_CONSOLIDADO!$A29,bs_30M3!AQ:AQ),"") -> 0 | J29: =IFERROR(SUMIF(bs_30M3!$A:$A,BS_CONSOLIDADO!$A29,bs_30M3!AL:AL),"") -> 0 | K29: =IFERROR(SUMIF(bs_60M6!$A:$A,BS_CONSOLIDADO!$A29,bs_60M6!AR:AR),"") -> 0 | L29: =IFERROR(SUMIF(bs_60M6!$A:$A,BS_CONSOLIDADO!$A29,bs_60M6!AM:AM),"") -> 0 | M29: =IFERROR(E29/F29,"") | N29: =IFERROR(G29/H29,"") | O29: =IFERROR(I29/J29,"") | P29: =IFERROR(K29/L29,"") | Q29: =IFERROR(C29/B29,"") | R29: =IFERROR(D29/C29,"")
B30: =IFERROR(SUMIF(bs_propostas!A:A,BS_CONSOLIDADO!A30,bs_propostas!D:D),"") -> 0 | C30: =IFERROR(SUMIF(bs_propostas!$A:$A,BS_CONSOLIDADO!$A30,bs_propostas!E:E),"") -> 0 | D30: =IFERROR(SUMIF(bs_propostas!$A:$A,BS_CONSOLIDADO!$A30,bs_propostas!F:F),"") -> 0 | E30: =IFERROR(SUMIF(bs_30M2!$A:$A,BS_CONSOLIDADO!$A30,bs_30M2!AN:AN),"") -> 0 | F30: =IFERROR(SUMIF(bs_30M2!$A:$A,BS_CONSOLIDADO!$A30,bs_30M2!AI:AI),"") -> 0 | G30: =IFERROR(SUMIF(bs_30M2!$A:$A,BS_CONSOLIDADO!$A30,bs_30M2!AP:AP),"") -> 0 | H30: =IFERROR(SUMIF(bs_30M2!$A:$A,BS_CONSOLIDADO!$A30,bs_30M2!AK:AK),"") -> 0 | I30: =IFERROR(SUMIF(bs_30M3!$A:$A,BS_CONSOLIDADO!$A30,bs_30M3!AQ:AQ),"") -> 0 | J30: =IFERROR(SUMIF(bs_30M3!$A:$A,BS_CONSOLIDADO!$A30,bs_30M3!AL:AL),"") -> 0 | K30: =IFERROR(SUMIF(bs_60M6!$A:$A,BS_CONSOLIDADO!$A30,bs_60M6!AR:AR),"") -> 0 | L30: =IFERROR(SUMIF(bs_60M6!$A:$A,BS_CONSOLIDADO!$A30,bs_60M6!AM:AM),"") -> 0 | M30: =IFERROR(E30/F30,"") | N30: =IFERROR(G30/H30,"") | O30: =IFERROR(I30/J30,"") | P30: =IFERROR(K30/L30,"") | Q30: =IFERROR(C30/B30,"") | R30: =IFERROR(D30/C30,"")
B31: =IFERROR(SUMIF(bs_propostas!A:A,BS_CONSOLIDADO!A31,bs_propostas!D:D),"") -> 0 | C31: =IFERROR(SUMIF(bs_propostas!$A:$A,BS_CONSOLIDADO!$A31,bs_propostas!E:E),"") -> 0 | D31: =IFERROR(SUMIF(bs_propostas!$A:$A,BS_CONSOLIDADO!$A31,bs_propostas!F:F),"") -> 0 | E31: =IFERROR(SUMIF(bs_30M2!$A:$A,BS_CONSOLIDADO!$A31,bs_30M2!AN:AN),"") -> 0 | F31: =IFERROR(SUMIF(bs_30M2!$A:$A,BS_CONSOLIDADO!$A31,bs_30M2!AI:AI),"") -> 0 | G31: =IFERROR(SUMIF(bs_30M2!$A:$A,BS_CONSOLIDADO!$A31,bs_30M2!AP:AP),"") -> 0 | H31: =IFERROR(SUMIF(bs_30M2!$A:$A,BS_CONSOLIDADO!$A31,bs_30M2!AK:AK),"") -> 0 | I31: =IFERROR(SUMIF(bs_30M3!$A:$A,BS_CONSOLIDADO!$A31,bs_30M3!AQ:AQ),"") -> 0 | J31: =IFERROR(SUMIF(bs_30M3!$A:$A,BS_CONSOLIDADO!$A31,bs_30M3!AL:AL),"") -> 0 | K31: =IFERROR(SUMIF(bs_60M6!$A:$A,BS_CONSOLIDADO!$A31,bs_60M6!AR:AR),"") -> 0 | L31: =IFERROR(SUMIF(bs_60M6!$A:$A,BS_CONSOLIDADO!$A31,bs_60M6!AM:AM),"") -> 0 | M31: =IFERROR(E31/F31,"") | N31: =IFERROR(G31/H31,"") | O31: =IFERROR(I31/J31,"") | P31: =IFERROR(K31/L31,"") | Q31: =IFERROR(C31/B31,"") | R31: =IFERROR(D31/C31,"")
B32: =IFERROR(SUMIF(bs_propostas!A:A,BS_CONSOLIDADO!A32,bs_propostas!D:D),"") -> 0 | C32: =IFERROR(SUMIF(bs_propostas!$A:$A,BS_CONSOLIDADO!$A32,bs_propostas!E:E),"") -> 0 | D32: =IFERROR(SUMIF(bs_propostas!$A:$A,BS_CONSOLIDADO!$A32,bs_propostas!F:F),"") -> 0 | E32: =IFERROR(SUMIF(bs_30M2!$A:$A,BS_CONSOLIDADO!$A32,bs_30M2!AN:AN),"") -> 0 | F32: =IFERROR(SUMIF(bs_30M2!$A:$A,BS_CONSOLIDADO!$A32,bs_30M2!AI:AI),"") -> 0 | G32: =IFERROR(SUMIF(bs_30M2!$A:$A,BS_CONSOLIDADO!$A32,bs_30M2!AP:AP),"") -> 0 | H32: =IFERROR(SUMIF(bs_30M2!$A:$A,BS_CONSOLIDADO!$A32,bs_30M2!AK:AK),"") -> 0 | I32: =IFERROR(SUMIF(bs_30M3!$A:$A,BS_CONSOLIDADO!$A32,bs_30M3!AQ:AQ),"") -> 0 | J32: =IFERROR(SUMIF(bs_30M3!$A:$A,BS_CONSOLIDADO!$A32,bs_30M3!AL:AL),"") -> 0 | K32: =IFERROR(SUMIF(bs_60M6!$A:$A,BS_CONSOLIDADO!$A32,bs_60M6!AR:AR),"") -> 0 | L32: =IFERROR(SUMIF(bs_60M6!$A:$A,BS_CONSOLIDADO!$A32,bs_60M6!AM:AM),"") -> 0 | M32: =IFERROR(E32/F32,"") | N32: =IFERROR(G32/H32,"") | O32: =IFERROR(I32/J32,"") | P32: =IFERROR(K32/L32,"") | Q32: =IFERROR(C32/B32,"") | R32: =IFERROR(D32/C32,"")
B33: =IFERROR(SUMIF(bs_propostas!A:A,BS_CONSOLIDADO!A33,bs_propostas!D:D),"") -> 0 | C33: =IFERROR(SUMIF(bs_propostas!$A:$A,BS_CONSOLIDADO!$A33,bs_propostas!E:E),"") -> 0 | D33: =IFERROR(SUMIF(bs_propostas!$A:$A,BS_CONSOLIDADO!$A33,bs_propostas!F:F),"") -> 0 | E33: =IFERROR(SUMIF(bs_30M2!$A:$A,BS_CONSOLIDADO!$A33,bs_30M2!AN:AN),"") -> 0 | F33: =IFERROR(SUMIF(bs_30M2!$A:$A,BS_CONSOLIDADO!$A33,bs_30M2!AI:AI),"") -> 0 | G33: =IFERROR(SUMIF(bs_30M2!$A:$A,BS_CONSOLIDADO!$A33,bs_30M2!AP:AP),"") -> 0 | H33: =IFERROR(SUMIF(bs_30M2!$A:$A,BS_CONSOLIDADO!$A33,bs_30M2!AK:AK),"") -> 0 | I33: =IFERROR(SUMIF(bs_30M3!$A:$A,BS_CONSOLIDADO!$A33,bs_30M3!AQ:AQ),"") -> 0 | J33: =IFERROR(SUMIF(bs_30M3!$A:$A,BS_CONSOLIDADO!$A33,bs_30M3!AL:AL),"") -> 0 | K33: =IFERROR(SUMIF(bs_60M6!$A:$A,BS_CONSOLIDADO!$A33,bs_60M6!AR:AR),"") -> 0 | L33: =IFERROR(SUMIF(bs_60M6!$A:$A,BS_CONSOLIDADO!$A33,bs_60M6!AM:AM),"") -> 0 | M33: =IFERROR(E33/F33,"") | N33: =IFERROR(G33/H33,"") | O33: =IFERROR(I33/J33,"") | P33: =IFERROR(K33/L33,"") | Q33: =IFERROR(C33/B33,"") | R33: =IFERROR(D33/C33,"")
B34: =IFERROR(SUMIF(bs_propostas!A:A,BS_CONSOLIDADO!A34,bs_propostas!D:D),"") -> 0 | C34: =IFERROR(SUMIF(bs_propostas!$A:$A,BS_CONSOLIDADO!$A34,bs_propostas!E:E),"") -> 0 | D34: =IFERROR(SUMIF(bs_propostas!$A:$A,BS_CONSOLIDADO!$A34,bs_propostas!F:F),"") -> 0 | E34: =IFERROR(SUMIF(bs_30M2!$A:$A,BS_CONSOLIDADO!$A34,bs_30M2!AN:AN),"") -> 0 | F34: =IFERROR(SUMIF(bs_30M2!$A:$A,BS_CONSOLIDADO!$A34,bs_30M2!AI:AI),"") -> 0 | G34: =IFERROR(SUMIF(bs_30M2!$A:$A,BS_CONSOLIDADO!$A34,bs_30M2!AP:AP),"") -> 0 | H34: =IFERROR(SUMIF(bs_30M2!$A:$A,BS_CONSOLIDADO!$A34,bs_30M2!AK:AK),"") -> 0 | I34: =IFERROR(SUMIF(bs_30M3!$A:$A,BS_CONSOLIDADO!$A34,bs_30M3!AQ:AQ),"") -> 0 | J34: =IFERROR(SUMIF(bs_30M3!$A:$A,BS_CONSOLIDADO!$A34,bs_30M3!AL:AL),"") -> 0 | K34: =IFERROR(SUMIF(bs_60M6!$A:$A,BS_CONSOLIDADO!$A34,bs_60M6!AR:AR),"") -> 0 | L34: =IFERROR(SUMIF(bs_60M6!$A:$A,BS_CONSOLIDADO!$A34,bs_60M6!AM:AM),"") -> 0 | M34: =IFERROR(E34/F34,"") | N34: =IFERROR(G34/H34,"") | O34: =IFERROR(I34/J34,"") | P34: =IFERROR(K34/L34,"") | Q34: =IFERROR(C34/B34,"") | R34: =IFERROR(D34/C34,"")
B35: =IFERROR(SUMIF(bs_propostas!A:A,BS_CONSOLIDADO!A35,bs_propostas!D:D),"") -> 0 | C35: =IFERROR(SUMIF(bs_propostas!$A:$A,BS_CONSOLIDADO!$A35,bs_propostas!E:E),"") -> 0 | D35: =IFERROR(SUMIF(bs_propostas!$A:$A,BS_CONSOLIDADO!$A35,bs_propostas!F:F),"") -> 0 | E35: =IFERROR(SUMIF(bs_30M2!$A:$A,BS_CONSOLIDADO!$A35,bs_30M2!AN:AN),"") -> 0 | F35: =IFERROR(SUMIF(bs_30M2!$A:$A,BS_CONSOLIDADO!$A35,bs_30M2!AI:AI),"") -> 0 | G35: =IFERROR(SUMIF(bs_30M2!$A:$A,BS_CONSOLIDADO!$A35,bs_30M2!AP:AP),"") -> 0 | H35: =IFERROR(SUMIF(bs_30M2!$A:$A,BS_CONSOLIDADO!$A35,bs_30M2!AK:AK),"") -> 0 | I35: =IFERROR(SUMIF(bs_30M3!$A:$A,BS_CONSOLIDADO!$A35,bs_30M3!AQ:AQ),"") -> 0 | J35: =IFERROR(SUMIF(bs_30M3!$A:$A,BS_CONSOLIDADO!$A35,bs_30M3!AL:AL),"") -> 0 | K35: =IFERROR(SUMIF(bs_60M6!$A:$A,BS_CONSOLIDADO!$A35,bs_60M6!AR:AR),"") -> 0 | L35: =IFERROR(SUMIF(bs_60M6!$A:$A,BS_CONSOLIDADO!$A35,bs_60M6!AM:AM),"") -> 0 | M35: =IFERROR(E35/F35,"") | N35: =IFERROR(G35/H35,"") | O35: =IFERROR(I35/J35,"") | P35: =IFERROR(K35/L35,"") | Q35: =IFERROR(C35/B35,"") | R35: =IFERROR(D35/C35,"")
B36: =IFERROR(SUMIF(bs_propostas!A:A,BS_CONSOLIDADO!A36,bs_propostas!D:D),"") -> 0 | C36: =IFERROR(SUMIF(bs_propostas!$A:$A,BS_CONSOLIDADO!$A36,bs_propostas!E:E),"") -> 0 | D36: =IFERROR(SUMIF(bs_propostas!$A:$A,BS_CONSOLIDADO!$A36,bs_propostas!F:F),"") -> 0 | E36: =IFERROR(SUMIF(bs_30M2!$A:$A,BS_CONSOLIDADO!$A36,bs_30M2!AN:AN),"") -> 0 | F36: =IFERROR(SUMIF(bs_30M2!$A:$A,BS_CONSOLIDADO!$A36,bs_30M2!AI:AI),"") -> 0 | G36: =IFERROR(SUMIF(bs_30M2!$A:$A,BS_CONSOLIDADO!$A36,bs_30M2!AP:AP),"") -> 0 | H36: =IFERROR(SUMIF(bs_30M2!$A:$A,BS_CONSOLIDADO!$A36,bs_30M2!AK:AK),"") -> 0 | I36: =IFERROR(SUMIF(bs_30M3!$A:$A,BS_CONSOLIDADO!$A36,bs_30M3!AQ:AQ),"") -> 0 | J36: =IFERROR(SUMIF(bs_30M3!$A:$A,BS_CONSOLIDADO!$A36,bs_30M3!AL:AL),"") -> 0 | K36: =IFERROR(SUMIF(bs_60M6!$A:$A,BS_CONSOLIDADO!$A36,bs_60M6!AR:AR),"") -> 0 | L36: =IFERROR(SUMIF(bs_60M6!$A:$A,BS_CONSOLIDADO!$A36,bs_60M6!AM:AM),"") -> 0 | M36: =IFERROR(E36/F36,"") | N36: =IFERROR(G36/H36,"") | O36: =IFERROR(I36/J36,"") | P36: =IFERROR(K36/L36,"") | Q36: =IFERROR(C36/B36,"") | R36: =IFERROR(D36/C36,"")
B37: =IFERROR(SUMIF(bs_propostas!A:A,BS_CONSOLIDADO!A37,bs_propostas!D:D),"") -> 0 | C37: =IFERROR(SUMIF(bs_propostas!$A:$A,BS_CONSOLIDADO!$A37,bs_propostas!E:E),"") -> 0 | D37: =IFERROR(SUMIF(bs_propostas!$A:$A,BS_CONSOLIDADO!$A37,bs_propostas!F:F),"") -> 0 | E37: =IFERROR(SUMIF(bs_30M2!$A:$A,BS_CONSOLIDADO!$A37,bs_30M2!AN:AN),"") -> 0 | F37: =IFERROR(SUMIF(bs_30M2!$A:$A,BS_CONSOLIDADO!$A37,bs_30M2!AI:AI),"") -> 0 | G37: =IFERROR(SUMIF(bs_30M2!$A:$A,BS_CONSOLIDADO!$A37,bs_30M2!AP:AP),"") -> 0 | H37: =IFERROR(SUMIF(bs_30M2!$A:$A,BS_CONSOLIDADO!$A37,bs_30M2!AK:AK),"") -> 0 | I37: =IFERROR(SUMIF(bs_30M3!$A:$A,BS_CONSOLIDADO!$A37,bs_30M3!AQ:AQ),"") -> 0 | J37: =IFERROR(SUMIF(bs_30M3!$A:$A,BS_CONSOLIDADO!$A37,bs_30M3!AL:AL),"") -> 0 | K37: =IFERROR(SUMIF(bs_60M6!$A:$A,BS_CONSOLIDADO!$A37,bs_60M6!AR:AR),"") -> 0 | L37: =IFERROR(SUMIF(bs_60M6!$A:$A,BS_CONSOLIDADO!$A37,bs_60M6!AM:AM),"") -> 0 | M37: =IFERROR(E37/F37,"") | N37: =IFERROR(G37/H37,"") | O37: =IFERROR(I37/J37,"") | P37: =IFERROR(K37/L37,"") | Q37: =IFERROR(C37/B37,"") | R37: =IFERROR(D37/C37,"")
... B399: =IFERROR(SUMIF(bs_propostas!A:A,BS_CONSOLIDADO!A399,bs_propostas!D:D),"") -> 0 | C399: =IFERROR(SUMIF(bs_propostas!$A:$A,BS_CONSOLIDADO!$A399,bs_propostas!E:E),"") -> 0 | D399: =IFERROR(SUMIF(bs_propostas!$A:$A,BS_CONSOLIDADO!$A399,bs_propostas!F:F),"") -> 0 | E399: =IFERROR(SUMIF(bs_30M2!$A:$A,BS_CONSOLIDADO!$A399,bs_30M2!AN:AN),"") -> 0 | F399: =IFERROR(SUMIF(bs_30M2!$A:$A,BS_CONSOLIDADO!$A399,bs_30M2!AI:AI),"") -> 0 | G399: =IFERROR(SUMIF(bs_30M2!$A:$A,BS_CONSOLIDADO!$A399,bs_30M2!AP:AP),"") -> 0 | H399: =IFERROR(SUMIF(bs_30M2!$A:$A,BS_CONSOLIDADO!$A399,bs_30M2!AK:AK),"") -> 0 | I399: =IFERROR(SUMIF(bs_30M3!$A:$A,BS_CONSOLIDADO!$A399,bs_30M3!AQ:AQ),"") -> 0 | J399: =IFERROR(SUMIF(bs_30M3!$A:$A,BS_CONSOLIDADO!$A399,bs_30M3!AL:AL),"") -> 0 | K399: =IFERROR(SUMIF(bs_60M6!$A:$A,BS_CONSOLIDADO!$A399,bs_60M6!AR:AR),"") -> 0 | L399: =IFERROR(SUMIF(bs_60M6!$A:$A,BS_CONSOLIDADO!$A399,bs_60M6!AM:AM),"") -> 0 | M399: =IFERROR(E399/F399,"") | N399: =IFERROR(G399/H399,"") | O399: =IFERROR(I399/J399,"") | P399: =IFERROR(K399/L399,"") | Q399: =IFERROR(C399/B399,"") | R399: =IFERROR(D399/C399,"")

Sheet BS_SIMULADOR
B4: # Propostas Total | C4: # Propostas Aprovadas | D4: # Propostas Efetivadas | E4: $ Vl. FPD | F4: $ Vl. Primeira Fatura | G4: $ Saldo O30M2 | H4: $ Saldo Mob 2 | I4: $ Saldo O30M3 | J4: $ Saldo Mob 3 | K4: $ Saldo O60M6 | L4: $ Saldo Mob 6 | M4: %FPD $ | N4: %OVER30M2 | O4: %OVER30M3 | P4: %OVER60M6 | Q4: %TXA AP | R4: %TXA EFE | S4: Δ PROPOSTA | T4: Δ APROVADA | U4: Δ Efeti | V4: Δ $ Vl. FPD | W4: Δ $ Vl. Primeira Fatura | X4: Δ $ Saldo O30M2 | Y4: Δ $ Saldo Mob 2 | Z4: Δ $ Saldo O30M3 | AA4: Δ $ Saldo Mob 3 | AB4: Δ $ Saldo O60M6 | AC4: Δ $ Saldo Mob 6
A5: GERAL | B5: =SUM(B7:B400) -> 7629 | C5: =SUM(C7:C400) -> 1602 | D5: =SUM(D7:D400) -> 943 | E5: =SUM(E7:E400) -> 31872.65 | F5: =SUM(F7:F400) -> 294563.74 | G5: =SUM(G7:G400) -> 119494.92 | H5: =SUM(H7:H400) -> 1292788.1 | I5: =SUM(I7:I400) -> 178943.13 | ... L5: =SUM(L7:L400) -> 1225648.6 | M5: =IFERROR(E5/F5,"") -> 0.1082029 | N5: =IFERROR(G5/H5,"") -> 0.092431944 | O5: =IFERROR(I5/J5,"") -> 0.16626681 | P5: =IFERROR(K5/L5,"") -> 0.23754568 | Q5: =IFERROR(C5/B5,"") -> 0.2099882 | R5: =IFERROR(D5/C5,"") -> 0.5886392 | S5: =SUM(S7:S400) -> 0 | T5: =SUM(T7:T400) -> 0 | U5: =SUM(U7:U400) -> 0 | V5: =SUM(V7:V400) -> 0 | W5: =SUM(W7:W400) -> 0 | X5: =SUM(X7:X400) -> 0 | Y5: =SUM(Y7:Y400) -> 0 | Z5: =SUM(Z7:Z400) -> 0 | ... AC5: =SUM(AC7:AC400) -> 0
A6: {=_xlfn.UNIQUE(_xlfn._xlws.FILTER(bs_propostas!A:A, bs_propostas!A:A <> ""))} -> Parceiro | N6: =IFERROR(G6/H6,"") | O6: =IFERROR(I6/J6,"") | P6: =IFERROR(K6/L6,"") | Q6: =IFERROR(C6/B6,"") | R6: =IFERROR(D6/C6,"")
A7: Parceiro 1 | B7: =IF(Simulador!$B6="", "", SUMIFS(bs_propostas!$D:$D, bs_propostas!$A:$A, $A7)) | C7: =IF(Simulador!$B6="", "", SUMIFS(bs_propostas!$E:$E, bs_propostas!$A:$A, $A7) - SUMIFS(bs_propostas!$E:$E, bs_propostas!$A:$A, $A7, bs_propostas!$CJ:$CJ, ">=" & MATCH(Simulador!$B6, {"A1";"A2";"B1";"B2";"B3";"C1";"C2";"D1";"D2";"E1"}, 0))) | D7: =IF(Simulador!$B6="", "", SUMIFS(bs_propostas!$F:$F, bs_propostas!$A:$A, $A7) - SUMIFS(bs_propostas!$F:$F, bs_propostas!$A:$A, $A7, bs_propostas!$CJ:$CJ, ">=" & MATCH(Simulador!$B6, {"A1";"A2";"B1";"B2";"B3";"C1";"C2";"D1";"D2";"E1"}, 0))) | E7: =IF(Simulador!$B6="", "", SUMIFS(bs_30M2!$AN:$AN, bs_30M2!$A:$A, $A7) - SUMIFS(bs_30M2!$AN:$AN, bs_30M2!$A:$A, $A7, bs_30M2!$CJ:$CJ, ">=" & MATCH(Simulador!$B6, {"A1";"A2";"B1";"B2";"B3";"C1";"C2";"D1";"D2";"E1"}, 0))) | F7: =IF(Simulador!$B6="", "", SUMIFS(bs_30M2!$AI:$AI, bs_30M2!$A:$A, $A7) - SUMIFS(bs_30M2!$AI:$AI, bs_30M2!$A:$A, $A7, bs_30M2!$CJ:$CJ, ">=" & MATCH(Simulador!$B6, {"A1";"A2";"B1";"B2";"B3";"C1";"C2";"D1";"D2";"E1"}, 0))) | G7: =IF(Simulador!$B6="", "", SUMIFS(bs_30M2!$AP:$AP, bs_30M2!$A:$A, $A7) - SUMIFS(bs_30M2!$AP:$AP, bs_30M2!$A:$A, $A7, bs_30M2!$CJ:$CJ, ">=" & MATCH(Simulador!$B6, {"A1";"A2";"B1";"B2";"B3";"C1";"C2";"D1";"D2";"E1"}, 0))) | H7: =IF(Simulador!$B6="", "", SUMIFS(bs_30M2!$AK:$AK, bs_30M2!$A:$A, $A7) - SUMIFS(bs_30M2!$AK:$AK, bs_30M2!$A:$A, $A7, bs_30M2!$CJ:$CJ, ">=" & MATCH(Simulador!$B6, {"A1";"A2";"B1";"B2";"B3";"C1";"C2";"D1";"D2";"E1"}, 0))) | I7: =IF(Simulador!$B6="", "", SUMIFS(bs_30M3!$AQ:$AQ, bs_30M3!$A:$A, $A7) - SUMIFS(bs_30M3!$AQ:$AQ, bs_30M3!$A:$A, $A7, bs_30M3!$CJ:$CJ, ">=" & MATCH(Simulador!$B6, {"A1";"A2";"B1";"B2";"B3";"C1";"C2";"D1";"D2";"E1"}, 0))) | J7: =IF(Simulador!$B6="", "", SUMIFS(bs_30M3!$AL:$AL, bs_30M3!$A:$A, $A7) - SUMIFS(bs_30M3!$AL:$AL, bs_30M3!$A:$A, $A7, bs_30M3!$CJ:$CJ, ">=" & MATCH(Simulador!$B6, {"A1";"A2";"B1";"B2";"B3";"C1";"C2";"D1";"D2";"E1"}, 0))) | K7: =IF(Simulador!$B6="", "", SUMIFS(bs_60M6!$AR:$AR, bs_60M6!$A:$A, $A7) - SUMIFS(bs_60M6!$AR:$AR, bs_60M6!$A:$A, $A7, bs_60M6!$CJ:$CJ, ">=" & MATCH(Simulador!$B6, {"A1";"A2";"B1";"B2";"B3";"C1";"C2";"D1";"D2";"E1"}, 0))) | L7: =IF(Simulador!$B6="", "", SUMIFS(bs_60M6!$AM:$AM, bs_60M6!$A:$A, $A7) - SUMIFS(bs_60M6!$AM:$AM, bs_60M6!$A:$A, $A7, bs_60M6!$CJ:$CJ, ">=" & MATCH(Simulador!$B6, {"A1";"A2";"B1";"B2";"B3";"C1";"C2";"D1";"D2";"E1"}, 0))) | M7: =IFERROR(E7/F7,"") | N7: =IFERROR(G7/H7,"") | O7: =IFERROR(I7/J7,"") | P7: =IFERROR(K7/L7,"") | Q7: =IFERROR(C7/B7,"") | R7: =IFERROR(D7/C7,"") | S7: =IFERROR(_xlfn.XLOOKUP(A7,BS_CONSOLIDADO!A:A,BS_CONSOLIDADO!B:B,"")-B7,"") | T7: =IFERROR(_xlfn.XLOOKUP(A7,BS_CONSOLIDADO!A:A,BS_CONSOLIDADO!C:C,"")-C7,"") | U7: =IFERROR(_xlfn.XLOOKUP(A7,BS_CONSOLIDADO!A:A,BS_CONSOLIDADO!D:D)-D7,"") | V7: =IFERROR(_xlfn.XLOOKUP($A7,BS_CONSOLIDADO!$A:$A,BS_CONSOLIDADO!E:E,"")-E7,"") | W7: =IFERROR(_xlfn.XLOOKUP($A7,BS_CONSOLIDADO!$A:$A,BS_CONSOLIDADO!F:F,"")-F7,"") | X7: =IFERROR(_xlfn.XLOOKUP($A7,BS_CONSOLIDADO!$A:$A,BS_CONSOLIDADO!G:G,"")-G7,"") | Y7: =IFERROR(_xlfn.XLOOKUP($A7,BS_CONSOLIDADO!$A:$A,BS_CONSOLIDADO!H:H,"")-H7,"") | Z7: =IFERROR(_xlfn.XLOOKUP($A7,BS_CONSOLIDADO!$A:$A,BS_CONSOLIDADO!I:I,"")-I7,"") | AA7: =IFERROR(_xlfn.XLOOKUP($A7,BS_CONSOLIDADO!$A:$A,BS_CONSOLIDADO!J:J,"")-J7,"") | AB7: =IFERROR(_xlfn.XLOOKUP($A7,BS_CONSOLIDADO!$A:$A,BS_CONSOLIDADO!K:K,"")-K7,"") | AC7: =IFERROR(_xlfn.XLOOKUP($A7,BS_CONSOLIDADO!$A:$A,BS_CONSOLIDADO!L:L,"")-L7,"")
A8: Parceiro 2 | B8: =IF(Simulador!$B7="", "", SUMIFS(bs_propostas!$D:$D, bs_propostas!$A:$A, $A8)) | C8: =IF(Simulador!$B7="", "", SUMIFS(bs_propostas!$E:$E, bs_propostas!$A:$A, $A8) - SUMIFS(bs_propostas!$E:$E, bs_propostas!$A:$A, $A8, bs_propostas!$CJ:$CJ, ">=" & MATCH(Simulador!$B7, {"A1";"A2";"B1";"B2";"B3";"C1";"C2";"D1";"D2";"E1"}, 0))) | D8: =IF(Simulador!$B7="", "", SUMIFS(bs_propostas!$F:$F, bs_propostas!$A:$A, $A8) - SUMIFS(bs_propostas!$F:$F, bs_propostas!$A:$A, $A8, bs_propostas!$CJ:$CJ, ">=" & MATCH(Simulador!$B7, {"A1";"A2";"B1";"B2";"B3";"C1";"C2";"D1";"D2";"E1"}, 0))) | E8: =IF(Simulador!$B7="", "", SUMIFS(bs_30M2!$AN:$AN, bs_30M2!$A:$A, $A8) - SUMIFS(bs_30M2!$AN:$AN, bs_30M2!$A:$A, $A8, bs_30M2!$CJ:$CJ, ">=" & MATCH(Simulador!$B7, {"A1";"A2";"B1";"B2";"B3";"C1";"C2";"D1";"D2";"E1"}, 0))) | F8: =IF(Simulador!$B7="", "", SUMIFS(bs_30M2!$AI:$AI, bs_30M2!$A:$A, $A8) - SUMIFS(bs_30M2!$AI:$AI, bs_30M2!$A:$A, $A8, bs_30M2!$CJ:$CJ, ">=" & MATCH(Simulador!$B7, {"A1";"A2";"B1";"B2";"B3";"C1";"C2";"D1";"D2";"E1"}, 0))) | G8: =IF(Simulador!$B7="", "", SUMIFS(bs_30M2!$AP:$AP, bs_30M2!$A:$A, $A8) - SUMIFS(bs_30M2!$AP:$AP, bs_30M2!$A:$A, $A8, bs_30M2!$CJ:$CJ, ">=" & MATCH(Simulador!$B7, {"A1";"A2";"B1";"B2";"B3";"C1";"C2";"D1";"D2";"E1"}, 0))) | H8: =IF(Simulador!$B7="", "", SUMIFS(bs_30M2!$AK:$AK, bs_30M2!$A:$A, $A8) - SUMIFS(bs_30M2!$AK:$AK, bs_30M2!$A:$A, $A8, bs_30M2!$CJ:$CJ, ">=" & MATCH(Simulador!$B7, {"A1";"A2";"B1";"B2";"B3";"C1";"C2";"D1";"D2";"E1"}, 0))) | I8: =IF(Simulador!$B7="", "", SUMIFS(bs_30M3!$AQ:$AQ, bs_30M3!$A:$A, $A8) - SUMIFS(bs_30M3!$AQ:$AQ, bs_30M3!$A:$A, $A8, bs_30M3!$CJ:$CJ, ">=" & MATCH(Simulador!$B7, {"A1";"A2";"B1";"B2";"B3";"C1";"C2";"D1";"D2";"E1"}, 0))) | J8: =IF(Simulador!$B7="", "", SUMIFS(bs_30M3!$AL:$AL, bs_30M3!$A:$A, $A8) - SUMIFS(bs_30M3!$AL:$AL, bs_30M3!$A:$A, $A8, bs_30M3!$CJ:$CJ, ">=" & MATCH(Simulador!$B7, {"A1";"A2";"B1";"B2";"B3";"C1";"C2";"D1";"D2";"E1"}, 0))) | K8: =IF(Simulador!$B7="", "", SUMIFS(bs_60M6!$AR:$AR, bs_60M6!$A:$A, $A8) - SUMIFS(bs_60M6!$AR:$AR, bs_60M6!$A:$A, $A8, bs_60M6!$CJ:$CJ, ">=" & MATCH(Simulador!$B7, {"A1";"A2";"B1";"B2";"B3";"C1";"C2";"D1";"D2";"E1"}, 0))) | L8: =IF(Simulador!$B7="", "", SUMIFS(bs_60M6!$AM:$AM, bs_60M6!$A:$A, $A8) - SUMIFS(bs_60M6!$AM:$AM, bs_60M6!$A:$A, $A8, bs_60M6!$CJ:$CJ, ">=" & MATCH(Simulador!$B7, {"A1";"A2";"B1";"B2";"B3";"C1";"C2";"D1";"D2";"E1"}, 0))) | M8: =IFERROR(E8/F8,"") | N8: =IFERROR(G8/H8,"") | O8: =IFERROR(I8/J8,"") | P8: =IFERROR(K8/L8,"") | Q8: =IFERROR(C8/B8,"") | R8: =IFERROR(D8/C8,"") | S8: =IFERROR(_xlfn.XLOOKUP(A8,BS_CONSOLIDADO!A:A,BS_CONSOLIDADO!B:B,"")-B8,"") | T8: =IFERROR(_xlfn.XLOOKUP(A8,BS_CONSOLIDADO!A:A,BS_CONSOLIDADO!C:C,"")-C8,"") | U8: =IFERROR(_xlfn.XLOOKUP(A8,BS_CONSOLIDADO!A:A,BS_CONSOLIDADO!D:D)-D8,"") | V8: =IFERROR(_xlfn.XLOOKUP($A8,BS_CONSOLIDADO!$A:$A,BS_CONSOLIDADO!E:E,"")-E8,"") | W8: =IFERROR(_xlfn.XLOOKUP($A8,BS_CONSOLIDADO!$A:$A,BS_CONSOLIDADO!F:F,"")-F8,"") | X8: =IFERROR(_xlfn.XLOOKUP($A8,BS_CONSOLIDADO!A:A,BS_CONSOLIDADO!G:G,"")-G8,"") | Y8: =IFERROR(_xlfn.XLOOKUP($A8,BS_CONSOLIDADO!$A:$A,BS_CONSOLIDADO!H:H,"")-H8,"") | Z8: =IFERROR(_xlfn.XLOOKUP($A8,BS_CONSOLIDADO!$A:$A,BS_CONSOLIDADO!I:I,"")-I8,"") | AA8: =IFERROR(_xlfn.XLOOKUP($A8,BS_CONSOLIDADO!$A:$A,BS_CONSOLIDADO!J:J,"")-J8,"") | AB8: =IFERROR(_xlfn.XLOOKUP($A8,BS_CONSOLIDADO!$A:$A,BS_CONSOLIDADO!K:K,"")-K8,"") | AC8: =IFERROR(_xlfn.XLOOKUP($A8,BS_CONSOLIDADO!$A:$A,BS_CONSOLIDADO!L:L,"")-L8,"")
A9: Parceiro 3 | B9: =IF(Simulador!$B8="", "", SUMIFS(bs_propostas!$D:$D, bs_propostas!$A:$A, $A9)) | C9: =IF(Simulador!$B8="", "", SUMIFS(bs_propostas!$E:$E, bs_propostas!$A:$A, $A9) - SUMIFS(bs_propostas!$E:$E, bs_propostas!$A:$A, $A9, bs_propostas!$CJ:$CJ, ">=" & MATCH(Simulador!$B8, {"A1";"A2";"B1";"B2";"B3";"C1";"C2";"D1";"D2";"E1"}, 0))) | D9: =IF(Simulador!$B8="", "", SUMIFS(bs_propostas!$F:$F, bs_propostas!$A:$A, $A9) - SUMIFS(bs_propostas!$F:$F, bs_propostas!$A:$A, $A9, bs_propostas!$CJ:$CJ, ">=" & MATCH(Simulador!$B8, {"A1";"A2";"B1";"B2";"B3";"C1";"C2";"D1";"D2";"E1"}, 0))) | E9: =IF(Simulador!$B8="", "", SUMIFS(bs_30M2!$AN:$AN, bs_30M2!$A:$A, $A9) - SUMIFS(bs_30M2!$AN:$AN, bs_30M2!$A:$A, $A9, bs_30M2!$CJ:$CJ, ">=" & MATCH(Simulador!$B8, {"A1";"A2";"B1";"B2";"B3";"C1";"C2";"D1";"D2";"E1"}, 0))) | F9: =IF(Simulador!$B8="", "", SUMIFS(bs_30M2!$AI:$AI, bs_30M2!$A:$A, $A9) - SUMIFS(bs_30M2!$AI:$AI, bs_30M2!$A:$A, $A9, bs_30M2!$CJ:$CJ, ">=" & MATCH(Simulador!$B8, {"A1";"A2";"B1";"B2";"B3";"C1";"C2";"D1";"D2";"E1"}, 0))) | G9: =IF(Simulador!$B8="", "", SUMIFS(bs_30M2!$AP:$AP, bs_30M2!$A:$A, $A9) - SUMIFS(bs_30M2!$AP:$AP, bs_30M2!$A:$A, $A9, bs_30M2!$CJ:$CJ, ">=" & MATCH(Simulador!$B8, {"A1";"A2";"B1";"B2";"B3";"C1";"C2";"D1";"D2";"E1"}, 0))) | H9: =IF(Simulador!$B8="", "", SUMIFS(bs_30M2!$AK:$AK, bs_30M2!$A:$A, $A9) - SUMIFS(bs_30M2!$AK:$AK, bs_30M2!$A:$A, $A9, bs_30M2!$CJ:$CJ, ">=" & MATCH(Simulador!$B8, {"A1";"A2";"B1";"B2";"B3";"C1";"C2";"D1";"D2";"E1"}, 0))) | I9: =IF(Simulador!$B8="", "", SUMIFS(bs_30M3!$AQ:$AQ, bs_30M3!$A:$A, $A9) - SUMIFS(bs_30M3!$AQ:$AQ, bs_30M3!$A:$A, $A9, bs_30M3!$CJ:$CJ, ">=" & MATCH(Simulador!$B8, {"A1";"A2";"B1";"B2";"B3";"C1";"C2";"D1";"D2";"E1"}, 0))) | J9: =IF(Simulador!$B8="", "", SUMIFS(bs_30M3!$AL:$AL, bs_30M3!$A:$A, $A9) - SUMIFS(bs_30M3!$AL:$AL, bs_30M3!$A:$A, $A9, bs_30M3!$CJ:$CJ, ">=" & MATCH(Simulador!$B8, {"A1";"A2";"B1";"B2";"B3";"C1";"C2";"D1";"D2";"E1"}, 0))) | K9: =IF(Simulador!$B8="", "", SUMIFS(bs_60M6!$AR:$AR, bs_60M6!$A:$A, $A9) - SUMIFS(bs_60M6!$AR:$AR, bs_60M6!$A:$A, $A9, bs_60M6!$CJ:$CJ, ">=" & MATCH(Simulador!$B8, {"A1";"A2";"B1";"B2";"B3";"C1";"C2";"D1";"D2";"E1"}, 0))) | L9: =IF(Simulador!$B8="", "", SUMIFS(bs_60M6!$AM:$AM, bs_60M6!$A:$A, $A9) - SUMIFS(bs_60M6!$AM:$AM, bs_60M6!$A:$A, $A9, bs_60M6!$CJ:$CJ, ">=" & MATCH(Simulador!$B8, {"A1";"A2";"B1";"B2";"B3";"C1";"C2";"D1";"D2";"E1"}, 0))) | M9: =IFERROR(E9/F9,"") | N9: =IFERROR(G9/H9,"") | O9: =IFERROR(I9/J9,"") | P9: =IFERROR(K9/L9,"") | Q9: =IFERROR(C9/B9,"") | R9: =IFERROR(D9/C9,"") | S9: =IFERROR(_xlfn.XLOOKUP(A9,BS_CONSOLIDADO!A:A,BS_CONSOLIDADO!B:B,"")-B9,"") | T9: =IFERROR(_xlfn.XLOOKUP(A9,BS_CONSOLIDADO!A:A,BS_CONSOLIDADO!C:C,"")-C9,"") | U9: =IFERROR(_xlfn.XLOOKUP(A9,BS_CONSOLIDADO!A:A,BS_CONSOLIDADO!D:D)-D9,"") | V9: =IFERROR(_xlfn.XLOOKUP($A9,BS_CONSOLIDADO!$A:$A,BS_CONSOLIDADO!E:E,"")-E9,"") | W9: =IFERROR(_xlfn.XLOOKUP($A9,BS_CONSOLIDADO!$A:$A,BS_CONSOLIDADO!F:F,"")-F9,"") | X9: =IFERROR(_xlfn.XLOOKUP($A9,BS_CONSOLIDADO!A:A,BS_CONSOLIDADO!G:G,"")-G9,"") | Y9: =IFERROR(_xlfn.XLOOKUP($A9,BS_CONSOLIDADO!$A:$A,BS_CONSOLIDADO!H:H,"")-H9,"") | Z9: =IFERROR(_xlfn.XLOOKUP($A9,BS_CONSOLIDADO!$A:$A,BS_CONSOLIDADO!I:I,"")-I9,"") | AA9: =IFERROR(_xlfn.XLOOKUP($A9,BS_CONSOLIDADO!$A:$A,BS_CONSOLIDADO!J:J,"")-J9,"") | AB9: =IFERROR(_xlfn.XLOOKUP($A9,BS_CONSOLIDADO!$A:$A,BS_CONSOLIDADO!K:K,"")-K9,"") | AC9: =IFERROR(_xlfn.XLOOKUP($A9,BS_CONSOLIDADO!$A:$A,BS_CONSOLIDADO!L:L,"")-L9,"")
A10: Parceiro 4 | B10: =IF(Simulador!$B9="", "", SUMIFS(bs_propostas!$D:$D, bs_propostas!$A:$A, $A10)) | C10: =IF(Simulador!$B9="", "", SUMIFS(bs_propostas!$E:$E, bs_propostas!$A:$A, $A10) - SUMIFS(bs_propostas!$E:$E, bs_propostas!$A:$A, $A10, bs_propostas!$CJ:$CJ, ">=" & MATCH(Simulador!$B9, {"A1";"A2";"B1";"B2";"B3";"C1";"C2";"D1";"D2";"E1"}, 0))) | D10: =IF(Simulador!$B9="", "", SUMIFS(bs_propostas!$F:$F, bs_propostas!$A:$A, $A10) - SUMIFS(bs_propostas!$F:$F, bs_propostas!$A:$A, $A10, bs_propostas!$CJ:$CJ, ">=" & MATCH(Simulador!$B9, {"A1";"A2";"B1";"B2";"B3";"C1";"C2";"D1";"D2";"E1"}, 0))) | E10: =IF(Simulador!$B9="", "", SUMIFS(bs_30M2!$AN:$AN, bs_30M2!$A:$A, $A10) - SUMIFS(bs_30M2!$AN:$AN, bs_30M2!$A:$A, $A10, bs_30M2!$CJ:$CJ, ">=" & MATCH(Simulador!$B9, {"A1";"A2";"B1";"B2";"B3";"C1";"C2";"D1";"D2";"E1"}, 0))) | F10: =IF(Simulador!$B9="", "", SUMIFS(bs_30M2!$AI:$AI, bs_30M2!$A:$A, $A10) - SUMIFS(bs_30M2!$AI:$AI, bs_30M2!$A:$A, $A10, bs_30M2!$CJ:$CJ, ">=" & MATCH(Simulador!$B9, {"A1";"A2";"B1";"B2";"B3";"C1";"C2";"D1";"D2";"E1"}, 0))) | G10: =IF(Simulador!$B9="", "", SUMIFS(bs_30M2!$AP:$AP, bs_30M2!$A:$A, $A10) - SUMIFS(bs_30M2!$AP:$AP, bs_30M2!$A:$A, $A10, bs_30M2!$CJ:$CJ, ">=" & MATCH(Simulador!$B9, {"A1";"A2";"B1";"B2";"B3";"C1";"C2";"D1";"D2";"E1"}, 0))) | H10: =IF(Simulador!$B9="", "", SUMIFS(bs_30M2!$AK:$AK, bs_30M2!$A:$A, $A10) - SUMIFS(bs_30M2!$AK:$AK, bs_30M2!$A:$A, $A10, bs_30M2!$CJ:$CJ, ">=" & MATCH(Simulador!$B9, {"A1";"A2";"B1";"B2";"B3";"C1";"C2";"D1";"D2";"E1"}, 0))) | I10: =IF(Simulador!$B9="", "", SUMIFS(bs_30M3!$AQ:$AQ, bs_30M3!$A:$A, $A10) - SUMIFS(bs_30M3!$AQ:$AQ, bs_30M3!$A:$A, $A10, bs_30M3!$CJ:$CJ, ">=" & MATCH(Simulador!$B9, {"A1";"A2";"B1";"B2";"B3";"C1";"C2";"D1";"D2";"E1"}, 0))) | J10: =IF(Simulador!$B9="", "", SUMIFS(bs_30M3!$AL:$AL, bs_30M3!$A:$A, $A10) - SUMIFS(bs_30M3!$AL:$AL, bs_30M3!$A:$A, $A10, bs_30M3!$CJ:$CJ, ">=" & MATCH(Simulador!$B9, {"A1";"A2";"B1";"B2";"B3";"C1";"C2";"D1";"D2";"E1"}, 0))) | K10: =IF(Simulador!$B9="", "", SUMIFS(bs_60M6!$AR:$AR, bs_60M6!$A:$A, $A10) - SUMIFS(bs_60M6!$AR:$AR, bs_60M6!$A:$A, $A10, bs_60M6!$CJ:$CJ, ">=" & MATCH(Simulador!$B9, {"A1";"A2";"B1";"B2";"B3";"C1";"C2";"D1";"D2";"E1"}, 0))) | L10: =IF(Simulador!$B9="", "", SUMIFS(bs_60M6!$AM:$AM, bs_60M6!$A:$A, $A10) - SUMIFS(bs_60M6!$AM:$AM, bs_60M6!$A:$A, $A10, bs_60M6!$CJ:$CJ, ">=" & MATCH(Simulador!$B9, {"A1";"A2";"B1";"B2";"B3";"C1";"C2";"D1";"D2";"E1"}, 0))) | M10: =IFERROR(E10/F10,"") | N10: =IFERROR(G10/H10,"") | O10: =IFERROR(I10/J10,"") | P10: =IFERROR(K10/L10,"") | Q10: =IFERROR(C10/B10,"") | R10: =IFERROR(D10/C10,"") | S10: =IFERROR(_xlfn.XLOOKUP(A10,BS_CONSOLIDADO!A:A,BS_CONSOLIDADO!B:B,"")-B10,"") | T10: =IFERROR(_xlfn.XLOOKUP(A10,BS_CONSOLIDADO!A:A,BS_CONSOLIDADO!C:C,"")-C10,"") | U10: =IFERROR(_xlfn.XLOOKUP(A10,BS_CONSOLIDADO!A:A,BS_CONSOLIDADO!D:D)-D10,"") | V10: =IFERROR(_xlfn.XLOOKUP($A10,BS_CONSOLIDADO!$A:$A,BS_CONSOLIDADO!E:E,"")-E10,"") | W10: =IFERROR(_xlfn.XLOOKUP($A10,BS_CONSOLIDADO!$A:$A,BS_CONSOLIDADO!F:F,"")-F10,"") | X10: =IFERROR(_xlfn.XLOOKUP($A10,BS_CONSOLIDADO!A:A,BS_CONSOLIDADO!G:G,"")-G10,"") | Y10: =IFERROR(_xlfn.XLOOKUP($A10,BS_CONSOLIDADO!$A:$A,BS_CONSOLIDADO!H:H,"")-H10,"") | Z10: =IFERROR(_xlfn.XLOOKUP($A10,BS_CONSOLIDADO!$A:$A,BS_CONSOLIDADO!I:I,"")-I10,"") | AA10: =IFERROR(_xlfn.XLOOKUP($A10,BS_CONSOLIDADO!$A:$A,BS_CONSOLIDADO!J:J,"")-J10,"") | AB10: =IFERROR(_xlfn.XLOOKUP($A10,BS_CONSOLIDADO!$A:$A,BS_CONSOLIDADO!K:K,"")-K10,"") | AC10: =IFERROR(_xlfn.XLOOKUP($A10,BS_CONSOLIDADO!$A:$A,BS_CONSOLIDADO!L:L,"")-L10,"")
A11: Parceiro 5 | B11: =IF(Simulador!$B10="", "", SUMIFS(bs_propostas!$D:$D, bs_propostas!$A:$A, $A11)) | C11: =IF(Simulador!$B10="", "", SUMIFS(bs_propostas!$E:$E, bs_propostas!$A:$A, $A11) - SUMIFS(bs_propostas!$E:$E, bs_propostas!$A:$A, $A11, bs_propostas!$CJ:$CJ, ">=" & MATCH(Simulador!$B10, {"A1";"A2";"B1";"B2";"B3";"C1";"C2";"D1";"D2";"E1"}, 0))) | D11: =IF(Simulador!$B10="", "", SUMIFS(bs_propostas!$F:$F, bs_propostas!$A:$A, $A11) - SUMIFS(bs_propostas!$F:$F, bs_propostas!$A:$A, $A11, bs_propostas!$CJ:$CJ, ">=" & MATCH(Simulador!$B10, {"A1";"A2";"B1";"B2";"B3";"C1";"C2";"D1";"D2";"E1"}, 0))) | E11: =IF(Simulador!$B10="", "", SUMIFS(bs_30M2!$AN:$AN, bs_30M2!$A:$A, $A11) - SUMIFS(bs_30M2!$AN:$AN, bs_30M2!$A:$A, $A11, bs_30M2!$CJ:$CJ, ">=" & MATCH(Simulador!$B10, {"A1";"A2";"B1";"B2";"B3";"C1";"C2";"D1";"D2";"E1"}, 0))) | F11: =IF(Simulador!$B10="", "", SUMIFS(bs_30M2!$AI:$AI, bs_30M2!$A:$A, $A11) - SUMIFS(bs_30M2!$AI:$AI, bs_30M2!$A:$A, $A11, bs_30M2!$CJ:$CJ, ">=" & MATCH(Simulador!$B10, {"A1";"A2";"B1";"B2";"B3";"C1";"C2";"D1";"D2";"E1"}, 0))) | G11: =IF(Simulador!$B10="", "", SUMIFS(bs_30M2!$AP:$AP, bs_30M2!$A:$A, $A11) - SUMIFS(bs_30M2!$AP:$AP, bs_30M2!$A:$A, $A11, bs_30M2!$CJ:$CJ, ">=" & MATCH(Simulador!$B10, {"A1";"A2";"B1";"B2";"B3";"C1";"C2";"D1";"D2";"E1"}, 0))) | H11: =IF(Simulador!$B10="", "", SUMIFS(bs_30M2!$AK:$AK, bs_30M2!$A:$A, $A11) - SUMIFS(bs_30M2!$AK:$AK, bs_30M2!$A:$A, $A11, bs_30M2!$CJ:$CJ, ">=" & MATCH(Simulador!$B10, {"A1";"A2";"B1";"B2";"B3";"C1";"C2";"D1";"D2";"E1"}, 0))) | I11: =IF(Simulador!$B10="", "", SUMIFS(bs_30M3!$AQ:$AQ, bs_30M3!$A:$A, $A11) - SUMIFS(bs_30M3!$AQ:$AQ, bs_30M3!$A:$A, $A11, bs_30M3!$CJ:$CJ, ">=" & MATCH(Simulador!$B10, {"A1";"A2";"B1";"B2";"B3";"C1";"C2";"D1";"D2";"E1"}, 0))) | J11: =IF(Simulador!$B10="", "", SUMIFS(bs_30M3!$AL:$AL, bs_30M3!$A:$A, $A11) - SUMIFS(bs_30M3!$AL:$AL, bs_30M3!$A:$A, $A11, bs_30M3!$CJ:$CJ, ">=" & MATCH(Simulador!$B10, {"A1";"A2";"B1";"B2";"B3";"C1";"C2";"D1";"D2";"E1"}, 0))) | K11: =IF(Simulador!$B10="", "", SUMIFS(bs_60M6!$AR:$AR, bs_60M6!$A:$A, $A11) - SUMIFS(bs_60M6!$AR:$AR, bs_60M6!$A:$A, $A11, bs_60M6!$CJ:$CJ, ">=" & MATCH(Simulador!$B10, {"A1";"A2";"B1";"B2";"B3";"C1";"C2";"D1";"D2";"E1"}, 0))) | L11: =IF(Simulador!$B10="", "", SUMIFS(bs_60M6!$AM:$AM, bs_60M6!$A:$A, $A11) - SUMIFS(bs_60M6!$AM:$AM, bs_60M6!$A:$A, $A11, bs_60M6!$CJ:$CJ, ">=" & MATCH(Simulador!$B10, {"A1";"A2";"B1";"B2";"B3";"C1";"C2";"D1";"D2";"E1"}, 0))) | M11: =IFERROR(E11/F11,"") | N11: =IFERROR(G11/H11,"") | O11: =IFERROR(I11/J11,"") | P11: =IFERROR(K11/L11,"") | Q11: =IFERROR(C11/B11,"") | R11: =IFERROR(D11/C11,"") | S11: =IFERROR(_xlfn.XLOOKUP(A11,BS_CONSOLIDADO!A:A,BS_CONSOLIDADO!B:B,"")-B11,"") | T11: =IFERROR(_xlfn.XLOOKUP(A11,BS_CONSOLIDADO!A:A,BS_CONSOLIDADO!C:C,"")-C11,"") | U11: =IFERROR(_xlfn.XLOOKUP(A11,BS_CONSOLIDADO!A:A,BS_CONSOLIDADO!D:D)-D11,"") | V11: =IFERROR(_xlfn.XLOOKUP($A11,BS_CONSOLIDADO!$A:$A,BS_CONSOLIDADO!E:E,"")-E11,"") | W11: =IFERROR(_xlfn.XLOOKUP($A11,BS_CONSOLIDADO!$A:$A,BS_CONSOLIDADO!F:F,"")-F11,"") | X11: =IFERROR(_xlfn.XLOOKUP($A11,BS_CONSOLIDADO!A:A,BS_CONSOLIDADO!G:G,"")-G11,"") | Y11: =IFERROR(_xlfn.XLOOKUP($A11,BS_CONSOLIDADO!$A:$A,BS_CONSOLIDADO!H:H,"")-H11,"") | Z11: =IFERROR(_xlfn.XLOOKUP($A11,BS_CONSOLIDADO!$A:$A,BS_CONSOLIDADO!I:I,"")-I11,"") | AA11: =IFERROR(_xlfn.XLOOKUP($A11,BS_CONSOLIDADO!$A:$A,BS_CONSOLIDADO!J:J,"")-J11,"") | AB11: =IFERROR(_xlfn.XLOOKUP($A11,BS_CONSOLIDADO!$A:$A,BS_CONSOLIDADO!K:K,"")-K11,"") | AC11: =IFERROR(_xlfn.XLOOKUP($A11,BS_CONSOLIDADO!$A:$A,BS_CONSOLIDADO!L:L,"")-L11,"")
A12: Parceiro 6 | B12: =IF(Simulador!$B11="", "", SUMIFS(bs_propostas!$D:$D, bs_propostas!$A:$A, $A12)) | C12: =IF(Simulador!$B11="", "", SUMIFS(bs_propostas!$E:$E, bs_propostas!$A:$A, $A12) - SUMIFS(bs_propostas!$E:$E, bs_propostas!$A:$A, $A12, bs_propostas!$CJ:$CJ, ">=" & MATCH(Simulador!$B11, {"A1";"A2";"B1";"B2";"B3";"C1";"C2";"D1";"D2";"E1"}, 0))) | D12: =IF(Simulador!$B11="", "", SUMIFS(bs_propostas!$F:$F, bs_propostas!$A:$A, $A12) - SUMIFS(bs_propostas!$F:$F, bs_propostas!$A:$A, $A12, bs_propostas!$CJ:$CJ, ">=" & MATCH(Simulador!$B11, {"A1";"A2";"B1";"B2";"B3";"C1";"C2";"D1";"D2";"E1"}, 0))) | E12: =IF(Simulador!$B11="", "", SUMIFS(bs_30M2!$AN:$AN, bs_30M2!$A:$A, $A12) - SUMIFS(bs_30M2!$AN:$AN, bs_30M2!$A:$A, $A12, bs_30M2!$CJ:$CJ, ">=" & MATCH(Simulador!$B11, {"A1";"A2";"B1";"B2";"B3";"C1";"C2";"D1";"D2";"E1"}, 0))) | F12: =IF(Simulador!$B11="", "", SUMIFS(bs_30M2!$AI:$AI, bs_30M2!$A:$A, $A12) - SUMIFS(bs_30M2!$AI:$AI, bs_30M2!$A:$A, $A12, bs_30M2!$CJ:$CJ, ">=" & MATCH(Simulador!$B11, {"A1";"A2";"B1";"B2";"B3";"C1";"C2";"D1";"D2";"E1"}, 0))) | G12: =IF(Simulador!$B11="", "", SUMIFS(bs_30M2!$AP:$AP, bs_30M2!$A:$A, $A12) - SUMIFS(bs_30M2!$AP:$AP, bs_30M2!$A:$A, $A12, bs_30M2!$CJ:$CJ, ">=" & MATCH(Simulador!$B11, {"A1";"A2";"B1";"B2";"B3";"C1";"C2";"D1";"D2";"E1"}, 0))) | H12: =IF(Simulador!$B11="", "", SUMIFS(bs_30M2!$AK:$AK, bs_30M2!$A:$A, $A12) - SUMIFS(bs_30M2!$AK:$AK, bs_30M2!$A:$A, $A12, bs_30M2!$CJ:$CJ, ">=" & MATCH(Simulador!$B11, {"A1";"A2";"B1";"B2";"B3";"C1";"C2";"D1";"D2";"E1"}, 0))) | I12: =IF(Simulador!$B11="", "", SUMIFS(bs_30M3!$AQ:$AQ, bs_30M3!$A:$A, $A12) - SUMIFS(bs_30M3!$AQ:$AQ, bs_30M3!$A:$A, $A12, bs_30M3!$CJ:$CJ, ">=" & MATCH(Simulador!$B11, {"A1";"A2";"B1";"B2";"B3";"C1";"C2";"D1";"D2";"E1"}, 0))) | J12: =IF(Simulador!$B11="", "", SUMIFS(bs_30M3!$AL:$AL, bs_30M3!$A:$A, $A12) - SUMIFS(bs_30M3!$AL:$AL, bs_30M3!$A:$A, $A12, bs_30M3!$CJ:$CJ, ">=" & MATCH(Simulador!$B11, {"A1";"A2";"B1";"B2";"B3";"C1";"C2";"D1";"D2";"E1"}, 0))) | K12: =IF(Simulador!$B11="", "", SUMIFS(bs_60M6!$AR:$AR, bs_60M6!$A:$A, $A12) - SUMIFS(bs_60M6!$AR:$AR, bs_60M6!$A:$A, $A12, bs_60M6!$CJ:$CJ, ">=" & MATCH(Simulador!$B11, {"A1";"A2";"B1";"B2";"B3";"C1";"C2";"D1";"D2";"E1"}, 0))) | L12: =IF(Simulador!$B11="", "", SUMIFS(bs_60M6!$AM:$AM, bs_60M6!$A:$A, $A12) - SUMIFS(bs_60M6!$AM:$AM, bs_60M6!$A:$A, $A12, bs_60M6!$CJ:$CJ, ">=" & MATCH(Simulador!$B11, {"A1";"A2";"B1";"B2";"B3";"C1";"C2";"D1";"D2";"E1"}, 0))) | M12: =IFERROR(E12/F12,"") | N12: =IFERROR(G12/H12,"") | O12: =IFERROR(I12/J12,"") | P12: =IFERROR(K12/L12,"") | Q12: =IFERROR(C12/B12,"") | R12: =IFERROR(D12/C12,"") | S12: =IFERROR(_xlfn.XLOOKUP(A12,BS_CONSOLIDADO!A:A,BS_CONSOLIDADO!B:B,"")-B12,"") | T12: =IFERROR(_xlfn.XLOOKUP(A12,BS_CONSOLIDADO!A:A,BS_CONSOLIDADO!C:C,"")-C12,"") | U12: =IFERROR(_xlfn.XLOOKUP(A12,BS_CONSOLIDADO!A:A,BS_CONSOLIDADO!D:D)-D12,"") | V12: =IFERROR(_xlfn.XLOOKUP($A12,BS_CONSOLIDADO!$A:$A,BS_CONSOLIDADO!E:E,"")-E12,"") | W12: =IFERROR(_xlfn.XLOOKUP($A12,BS_CONSOLIDADO!$A:$A,BS_CONSOLIDADO!F:F,"")-F12,"") | X12: =IFERROR(_xlfn.XLOOKUP($A12,BS_CONSOLIDADO!A:A,BS_CONSOLIDADO!G:G,"")-G12,"") | Y12: =IFERROR(_xlfn.XLOOKUP($A12,BS_CONSOLIDADO!$A:$A,BS_CONSOLIDADO!H:H,"")-H12,"") | Z12: =IFERROR(_xlfn.XLOOKUP($A12,BS_CONSOLIDADO!$A:$A,BS_CONSOLIDADO!I:I,"")-I12,"") | AA12: =IFERROR(_xlfn.XLOOKUP($A12,BS_CONSOLIDADO!$A:$A,BS_CONSOLIDADO!J:J,"")-J12,"") | AB12: =IFERROR(_xlfn.XLOOKUP($A12,BS_CONSOLIDADO!$A:$A,BS_CONSOLIDADO!K:K,"")-K12,"") | AC12: =IFERROR(_xlfn.XLOOKUP($A12,BS_CONSOLIDADO!$A:$A,BS_CONSOLIDADO!L:L,"")-L12,"")
A13: Parceiro 7 | B13: =IF(Simulador!$B12="", "", SUMIFS(bs_propostas!$D:$D, bs_propostas!$A:$A, $A13)) | C13: =IF(Simulador!$B12="", "", SUMIFS(bs_propostas!$E:$E, bs_propostas!$A:$A, $A13) - SUMIFS(bs_propostas!$E:$E, bs_propostas!$A:$A, $A13, bs_propostas!$CJ:$CJ, ">=" & MATCH(Simulador!$B12, {"A1";"A2";"B1";"B2";"B3";"C1";"C2";"D1";"D2";"E1"}, 0))) | D13: =IF(Simulador!$B12="", "", SUMIFS(bs_propostas!$F:$F, bs_propostas!$A:$A, $A13) - SUMIFS(bs_propostas!$F:$F, bs_propostas!$A:$A, $A13, bs_propostas!$CJ:$CJ, ">=" & MATCH(Simulador!$B12, {"A1";"A2";"B1";"B2";"B3";"C1";"C2";"D1";"D2";"E1"}, 0))) | E13: =IF(Simulador!$B12="", "", SUMIFS(bs_30M2!$AN:$AN, bs_30M2!$A:$A, $A13) - SUMIFS(bs_30M2!$AN:$AN, bs_30M2!$A:$A, $A13, bs_30M2!$CJ:$CJ, ">=" & MATCH(Simulador!$B12, {"A1";"A2";"B1";"B2";"B3";"C1";"C2";"D1";"D2";"E1"}, 0))) | F13: =IF(Simulador!$B12="", "", SUMIFS(bs_30M2!$AI:$AI, bs_30M2!$A:$A, $A13) - SUMIFS(bs_30M2!$AI:$AI, bs_30M2!$A:$A, $A13, bs_30M2!$CJ:$CJ, ">=" & MATCH(Simulador!$B12, {"A1";"A2";"B1";"B2";"B3";"C1";"C2";"D1";"D2";"E1"}, 0))) | G13: =IF(Simulador!$B12="", "", SUMIFS(bs_30M2!$AP:$AP, bs_30M2!$A:$A, $A13) - SUMIFS(bs_30M2!$AP:$AP, bs_30M2!$A:$A, $A13, bs_30M2!$CJ:$CJ, ">=" & MATCH(Simulador!$B12, {"A1";"A2";"B1";"B2";"B3";"C1";"C2";"D1";"D2";"E1"}, 0))) | H13: =IF(Simulador!$B12="", "", SUMIFS(bs_30M2!$AK:$AK, bs_30M2!$A:$A, $A13) - SUMIFS(bs_30M2!$AK:$AK, bs_30M2!$A:$A, $A13, bs_30M2!$CJ:$CJ, ">=" & MATCH(Simulador!$B12, {"A1";"A2";"B1";"B2";"B3";"C1";"C2";"D1";"D2";"E1"}, 0))) | I13: =IF(Simulador!$B12="", "", SUMIFS(bs_30M3!$AQ:$AQ, bs_30M3!$A:$A, $A13) - SUMIFS(bs_30M3!$AQ:$AQ, bs_30M3!$A:$A, $A13, bs_30M3!$CJ:$CJ, ">=" & MATCH(Simulador!$B12, {"A1";"A2";"B1";"B2";"B3";"C1";"C2";"D1";"D2";"E1"}, 0))) | J13: =IF(Simulador!$B12="", "", SUMIFS(bs_30M3!$AL:$AL, bs_30M3!$A:$A, $A13) - SUMIFS(bs_30M3!$AL:$AL, bs_30M3!$A:$A, $A13, bs_30M3!$CJ:$CJ, ">=" & MATCH(Simulador!$B12, {"A1";"A2";"B1";"B2";"B3";"C1";"C2";"D1";"D2";"E1"}, 0))) | K13: =IF(Simulador!$B12="", "", SUMIFS(bs_60M6!$AR:$AR, bs_60M6!$A:$A, $A13) - SUMIFS(bs_60M6!$AR:$AR, bs_60M6!$A:$A, $A13, bs_60M6!$CJ:$CJ, ">=" & MATCH(Simulador!$B12, {"A1";"A2";"B1";"B2";"B3";"C1";"C2";"D1";"D2";"E1"}, 0))) | L13: =IF(Simulador!$B12="", "", SUMIFS(bs_60M6!$AM:$AM, bs_60M6!$A:$A, $A13) - SUMIFS(bs_60M6!$AM:$AM, bs_60M6!$A:$A, $A13, bs_60M6!$CJ:$CJ, ">=" & MATCH(Simulador!$B12, {"A1";"A2";"B1";"B2";"B3";"C1";"C2";"D1";"D2";"E1"}, 0))) | M13: =IFERROR(E13/F13,"") | N13: =IFERROR(G13/H13,"") | O13: =IFERROR(I13/J13,"") | P13: =IFERROR(K13/L13,"") | Q13: =IFERROR(C13/B13,"") | R13: =IFERROR(D13/C13,"") | S13: =IFERROR(_xlfn.XLOOKUP(A13,BS_CONSOLIDADO!A:A,BS_CONSOLIDADO!B:B,"")-B13,"") | T13: =IFERROR(_xlfn.XLOOKUP(A13,BS_CONSOLIDADO!A:A,BS_CONSOLIDADO!C:C,"")-C13,"") | U13: =IFERROR(_xlfn.XLOOKUP(A13,BS_CONSOLIDADO!A:A,BS_CONSOLIDADO!D:D)-D13,"") | V13: =IFERROR(_xlfn.XLOOKUP($A13,BS_CONSOLIDADO!$A:$A,BS_CONSOLIDADO!E:E,"")-E13,"") | W13: =IFERROR(_xlfn.XLOOKUP($A13,BS_CONSOLIDADO!$A:$A,BS_CONSOLIDADO!F:F,"")-F13,"") | X13: =IFERROR(_xlfn.XLOOKUP($A13,BS_CONSOLIDADO!A:A,BS_CONSOLIDADO!G:G,"")-G13,"") | Y13: =IFERROR(_xlfn.XLOOKUP($A13,BS_CONSOLIDADO!$A:$A,BS_CONSOLIDADO!H:H,"")-H13,"") | Z13: =IFERROR(_xlfn.XLOOKUP($A13,BS_CONSOLIDADO!$A:$A,BS_CONSOLIDADO!I:I,"")-I13,"") | AA13: =IFERROR(_xlfn.XLOOKUP($A13,BS_CONSOLIDADO!$A:$A,BS_CONSOLIDADO!J:J,"")-J13,"") | AB13: =IFERROR(_xlfn.XLOOKUP($A13,BS_CONSOLIDADO!$A:$A,BS_CONSOLIDADO!K:K,"")-K13,"") | AC13: =IFERROR(_xlfn.XLOOKUP($A13,BS_CONSOLIDADO!$A:$A,BS_CONSOLIDADO!L:L,"")-L13,"")
A14: Parceiro 8 | B14: =IF(Simulador!$B13="", "", SUMIFS(bs_propostas!$D:$D, bs_propostas!$A:$A, $A14)) | C14: =IF(Simulador!$B13="", "", SUMIFS(bs_propostas!$E:$E, bs_propostas!$A:$A, $A14) - SUMIFS(bs_propostas!$E:$E, bs_propostas!$A:$A, $A14, bs_propostas!$CJ:$CJ, ">=" & MATCH(Simulador!$B13, {"A1";"A2";"B1";"B2";"B3";"C1";"C2";"D1";"D2";"E1"}, 0))) | D14: =IF(Simulador!$B13="", "", SUMIFS(bs_propostas!$F:$F, bs_propostas!$A:$A, $A14) - SUMIFS(bs_propostas!$F:$F, bs_propostas!$A:$A, $A14, bs_propostas!$CJ:$CJ, ">=" & MATCH(Simulador!$B13, {"A1";"A2";"B1";"B2";"B3";"C1";"C2";"D1";"D2";"E1"}, 0))) | E14: =IF(Simulador!$B13="", "", SUMIFS(bs_30M2!$AN:$AN, bs_30M2!$A:$A, $A14) - SUMIFS(bs_30M2!$AN:$AN, bs_30M2!$A:$A, $A14, bs_30M2!$CJ:$CJ, ">=" & MATCH(Simulador!$B13, {"A1";"A2";"B1";"B2";"B3";"C1";"C2";"D1";"D2";"E1"}, 0))) | F14: =IF(Simulador!$B13="", "", SUMIFS(bs_30M2!$AI:$AI, bs_30M2!$A:$A, $A14) - SUMIFS(bs_30M2!$AI:$AI, bs_30M2!$A:$A, $A14, bs_30M2!$CJ:$CJ, ">=" & MATCH(Simulador!$B13, {"A1";"A2";"B1";"B2";"B3";"C1";"C2";"D1";"D2";"E1"}, 0))) | G14: =IF(Simulador!$B13="", "", SUMIFS(bs_30M2!$AP:$AP, bs_30M2!$A:$A, $A14) - SUMIFS(bs_30M2!$AP:$AP, bs_30M2!$A:$A, $A14, bs_30M2!$CJ:$CJ, ">=" & MATCH(Simulador!$B13, {"A1";"A2";"B1";"B2";"B3";"C1";"C2";"D1";"D2";"E1"}, 0))) | H14: =IF(Simulador!$B13="", "", SUMIFS(bs_30M2!$AK:$AK, bs_30M2!$A:$A, $A14) - SUMIFS(bs_30M2!$AK:$AK, bs_30M2!$A:$A, $A14, bs_30M2!$CJ:$CJ, ">=" & MATCH(Simulador!$B13, {"A1";"A2";"B1";"B2";"B3";"C1";"C2";"D1";"D2";"E1"}, 0))) | I14: =IF(Simulador!$B13="", "", SUMIFS(bs_30M3!$AQ:$AQ, bs_30M3!$A:$A, $A14) - SUMIFS(bs_30M3!$AQ:$AQ, bs_30M3!$A:$A, $A14, bs_30M3!$CJ:$CJ, ">=" & MATCH(Simulador!$B13, {"A1";"A2";"B1";"B2";"B3";"C1";"C2";"D1";"D2";"E1"}, 0))) | J14: =IF(Simulador!$B13="", "", SUMIFS(bs_30M3!$AL:$AL, bs_30M3!$A:$A, $A14) - SUMIFS(bs_30M3!$AL:$AL, bs_30M3!$A:$A, $A14, bs_30M3!$CJ:$CJ, ">=" & MATCH(Simulador!$B13, {"A1";"A2";"B1";"B2";"B3";"C1";"C2";"D1";"D2";"E1"}, 0))) | K14: =IF(Simulador!$B13="", "", SUMIFS(bs_60M6!$AR:$AR, bs_60M6!$A:$A, $A14) - SUMIFS(bs_60M6!$AR:$AR, bs_60M6!$A:$A, $A14, bs_60M6!$CJ:$CJ, ">=" & MATCH(Simulador!$B13, {"A1";"A2";"B1";"B2";"B3";"C1";"C2";"D1";"D2";"E1"}, 0))) | L14: =IF(Simulador!$B13="", "", SUMIFS(bs_60M6!$AM:$AM, bs_60M6!$A:$A, $A14) - SUMIFS(bs_60M6!$AM:$AM, bs_60M6!$A:$A, $A14, bs_60M6!$CJ:$CJ, ">=" & MATCH(Simulador!$B13, {"A1";"A2";"B1";"B2";"B3";"C1";"C2";"D1";"D2";"E1"}, 0))) | M14: =IFERROR(E14/F14,"") | N14: =IFERROR(G14/H14,"") | O14: =IFERROR(I14/J14,"") | P14: =IFERROR(K14/L14,"") | Q14: =IFERROR(C14/B14,"") | R14: =IFERROR(D14/C14,"") | S14: =IFERROR(_xlfn.XLOOKUP(A14,BS_CONSOLIDADO!A:A,BS_CONSOLIDADO!B:B,"")-B14,"") | T14: =IFERROR(_xlfn.XLOOKUP(A14,BS_CONSOLIDADO!A:A,BS_CONSOLIDADO!C:C,"")-C14,"") | U14: =IFERROR(_xlfn.XLOOKUP(A14,BS_CONSOLIDADO!A:A,BS_CONSOLIDADO!D:D)-D14,"") | V14: =IFERROR(_xlfn.XLOOKUP($A14,BS_CONSOLIDADO!$A:$A,BS_CONSOLIDADO!E:E,"")-E14,"") | W14: =IFERROR(_xlfn.XLOOKUP($A14,BS_CONSOLIDADO!$A:$A,BS_CONSOLIDADO!F:F,"")-F14,"") | X14: =IFERROR(_xlfn.XLOOKUP($A14,BS_CONSOLIDADO!A:A,BS_CONSOLIDADO!G:G,"")-G14,"") | Y14: =IFERROR(_xlfn.XLOOKUP($A14,BS_CONSOLIDADO!$A:$A,BS_CONSOLIDADO!H:H,"")-H14,"") | Z14: =IFERROR(_xlfn.XLOOKUP($A14,BS_CONSOLIDADO!$A:$A,BS_CONSOLIDADO!I:I,"")-I14,"") | AA14: =IFERROR(_xlfn.XLOOKUP($A14,BS_CONSOLIDADO!$A:$A,BS_CONSOLIDADO!J:J,"")-J14,"") | AB14: =IFERROR(_xlfn.XLOOKUP($A14,BS_CONSOLIDADO!$A:$A,BS_CONSOLIDADO!K:K,"")-K14,"") | AC14: =IFERROR(_xlfn.XLOOKUP($A14,BS_CONSOLIDADO!$A:$A,BS_CONSOLIDADO!L:L,"")-L14,"")
A15: Parceiro 9 | B15: =IF(Simulador!$B14="", "", SUMIFS(bs_propostas!$D:$D, bs_propostas!$A:$A, $A15)) | C15: =IF(Simulador!$B14="", "", SUMIFS(bs_propostas!$E:$E, bs_propostas!$A:$A, $A15) - SUMIFS(bs_propostas!$E:$E, bs_propostas!$A:$A, $A15, bs_propostas!$CJ:$CJ, ">=" & MATCH(Simulador!$B14, {"A1";"A2";"B1";"B2";"B3";"C1";"C2";"D1";"D2";"E1"}, 0))) | D15: =IF(Simulador!$B14="", "", SUMIFS(bs_propostas!$F:$F, bs_propostas!$A:$A, $A15) - SUMIFS(bs_propostas!$F:$F, bs_propostas!$A:$A, $A15, bs_propostas!$CJ:$CJ, ">=" & MATCH(Simulador!$B14, {"A1";"A2";"B1";"B2";"B3";"C1";"C2";"D1";"D2";"E1"}, 0))) | E15: =IF(Simulador!$B14="", "", SUMIFS(bs_30M2!$AN:$AN, bs_30M2!$A:$A, $A15) - SUMIFS(bs_30M2!$AN:$AN, bs_30M2!$A:$A, $A15, bs_30M2!$CJ:$CJ, ">=" & MATCH(Simulador!$B14, {"A1";"A2";"B1";"B2";"B3";"C1";"C2";"D1";"D2";"E1"}, 0))) | F15: =IF(Simulador!$B14="", "", SUMIFS(bs_30M2!$AI:$AI, bs_30M2!$A:$A, $A15) - SUMIFS(bs_30M2!$AI:$AI, bs_30M2!$A:$A, $A15, bs_30M2!$CJ:$CJ, ">=" & MATCH(Simulador!$B14, {"A1";"A2";"B1";"B2";"B3";"C1";"C2";"D1";"D2";"E1"}, 0))) | G15: =IF(Simulador!$B14="", "", SUMIFS(bs_30M2!$AP:$AP, bs_30M2!$A:$A, $A15) - SUMIFS(bs_30M2!$AP:$AP, bs_30M2!$A:$A, $A15, bs_30M2!$CJ:$CJ, ">=" & MATCH(Simulador!$B14, {"A1";"A2";"B1";"B2";"B3";"C1";"C2";"D1";"D2";"E1"}, 0))) | H15: =IF(Simulador!$B14="", "", SUMIFS(bs_30M2!$AK:$AK, bs_30M2!$A:$A, $A15) - SUMIFS(bs_30M2!$AK:$AK, bs_30M2!$A:$A, $A15, bs_30M2!$CJ:$CJ, ">=" & MATCH(Simulador!$B14, {"A1";"A2";"B1";"B2";"B3";"C1";"C2";"D1";"D2";"E1"}, 0))) | I15: =IF(Simulador!$B14="", "", SUMIFS(bs_30M3!$AQ:$AQ, bs_30M3!$A:$A, $A15) - SUMIFS(bs_30M3!$AQ:$AQ, bs_30M3!$A:$A, $A15, bs_30M3!$CJ:$CJ, ">=" & MATCH(Simulador!$B14, {"A1";"A2";"B1";"B2";"B3";"C1";"C2";"D1";"D2";"E1"}, 0))) | J15: =IF(Simulador!$B14="", "", SUMIFS(bs_30M3!$AL:$AL, bs_30M3!$A:$A, $A15) - SUMIFS(bs_30M3!$AL:$AL, bs_30M3!$A:$A, $A15, bs_30M3!$CJ:$CJ, ">=" & MATCH(Simulador!$B14, {"A1";"A2";"B1";"B2";"B3";"C1";"C2";"D1";"D2";"E1"}, 0))) | K15: =IF(Simulador!$B14="", "", SUMIFS(bs_60M6!$AR:$AR, bs_60M6!$A:$A, $A15) - SUMIFS(bs_60M6!$AR:$AR, bs_60M6!$A:$A, $A15, bs_60M6!$CJ:$CJ, ">=" & MATCH(Simulador!$B14, {"A1";"A2";"B1";"B2";"B3";"C1";"C2";"D1";"D2";"E1"}, 0))) | L15: =IF(Simulador!$B14="", "", SUMIFS(bs_60M6!$AM:$AM, bs_60M6!$A:$A, $A15) - SUMIFS(bs_60M6!$AM:$AM, bs_60M6!$A:$A, $A15, bs_60M6!$CJ:$CJ, ">=" & MATCH(Simulador!$B14, {"A1";"A2";"B1";"B2";"B3";"C1";"C2";"D1";"D2";"E1"}, 0))) | M15: =IFERROR(E15/F15,"") | N15: =IFERROR(G15/H15,"") | O15: =IFERROR(I15/J15,"") | P15: =IFERROR(K15/L15,"") | Q15: =IFERROR(C15/B15,"") | R15: =IFERROR(D15/C15,"") | S15: =IFERROR(_xlfn.XLOOKUP(A15,BS_CONSOLIDADO!A:A,BS_CONSOLIDADO!B:B,"")-B15,"") | T15: =IFERROR(_xlfn.XLOOKUP(A15,BS_CONSOLIDADO!A:A,BS_CONSOLIDADO!C:C,"")-C15,"") | U15: =IFERROR(_xlfn.XLOOKUP(A15,BS_CONSOLIDADO!A:A,BS_CONSOLIDADO!D:D)-D15,"") | V15: =IFERROR(_xlfn.XLOOKUP($A15,BS_CONSOLIDADO!$A:$A,BS_CONSOLIDADO!E:E,"")-E15,"") | W15: =IFERROR(_xlfn.XLOOKUP($A15,BS_CONSOLIDADO!$A:$A,BS_CONSOLIDADO!F:F,"")-F15,"") | X15: =IFERROR(_xlfn.XLOOKUP($A15,BS_CONSOLIDADO!A:A,BS_CONSOLIDADO!G:G,"")-G15,"") | Y15: =IFERROR(_xlfn.XLOOKUP($A15,BS_CONSOLIDADO!$A:$A,BS_CONSOLIDADO!H:H,"")-H15,"") | Z15: =IFERROR(_xlfn.XLOOKUP($A15,BS_CONSOLIDADO!$A:$A,BS_CONSOLIDADO!I:I,"")-I15,"") | AA15: =IFERROR(_xlfn.XLOOKUP($A15,BS_CONSOLIDADO!$A:$A,BS_CONSOLIDADO!J:J,"")-J15,"") | AB15: =IFERROR(_xlfn.XLOOKUP($A15,BS_CONSOLIDADO!$A:$A,BS_CONSOLIDADO!K:K,"")-K15,"") | AC15: =IFERROR(_xlfn.XLOOKUP($A15,BS_CONSOLIDADO!$A:$A,BS_CONSOLIDADO!L:L,"")-L15,"")
A16: Parceiro 10 | B16: =IF(Simulador!$B15="", "", SUMIFS(bs_propostas!$D:$D, bs_propostas!$A:$A, $A16)) | C16: =IF(Simulador!$B15="", "", SUMIFS(bs_propostas!$E:$E, bs_propostas!$A:$A, $A16) - SUMIFS(bs_propostas!$E:$E, bs_propostas!$A:$A, $A16, bs_propostas!$CJ:$CJ, ">=" & MATCH(Simulador!$B15, {"A1";"A2";"B1";"B2";"B3";"C1";"C2";"D1";"D2";"E1"}, 0))) | D16: =IF(Simulador!$B15="", "", SUMIFS(bs_propostas!$F:$F, bs_propostas!$A:$A, $A16) - SUMIFS(bs_propostas!$F:$F, bs_propostas!$A:$A, $A16, bs_propostas!$CJ:$CJ, ">=" & MATCH(Simulador!$B15, {"A1";"A2";"B1";"B2";"B3";"C1";"C2";"D1";"D2";"E1"}, 0))) | E16: =IF(Simulador!$B15="", "", SUMIFS(bs_30M2!$AN:$AN, bs_30M2!$A:$A, $A16) - SUMIFS(bs_30M2!$AN:$AN, bs_30M2!$A:$A, $A16, bs_30M2!$CJ:$CJ, ">=" & MATCH(Simulador!$B15, {"A1";"A2";"B1";"B2";"B3";"C1";"C2";"D1";"D2";"E1"}, 0))) | F16: =IF(Simulador!$B15="", "", SUMIFS(bs_30M2!$AI:$AI, bs_30M2!$A:$A, $A16) - SUMIFS(bs_30M2!$AI:$AI, bs_30M2!$A:$A, $A16, bs_30M2!$CJ:$CJ, ">=" & MATCH(Simulador!$B15, {"A1";"A2";"B1";"B2";"B3";"C1";"C2";"D1";"D2";"E1"}, 0))) | G16: =IF(Simulador!$B15="", "", SUMIFS(bs_30M2!$AP:$AP, bs_30M2!$A:$A, $A16) - SUMIFS(bs_30M2!$AP:$AP, bs_30M2!$A:$A, $A16, bs_30M2!$CJ:$CJ, ">=" & MATCH(Simulador!$B15, {"A1";"A2";"B1";"B2";"B3";"C1";"C2";"D1";"D2";"E1"}, 0))) | H16: =IF(Simulador!$B15="", "", SUMIFS(bs_30M2!$AK:$AK, bs_30M2!$A:$A, $A16) - SUMIFS(bs_30M2!$AK:$AK, bs_30M2!$A:$A, $A16, bs_30M2!$CJ:$CJ, ">=" & MATCH(Simulador!$B15, {"A1";"A2";"B1";"B2";"B3";"C1";"C2";"D1";"D2";"E1"}, 0))) | I16: =IF(Simulador!$B15="", "", SUMIFS(bs_30M3!$AQ:$AQ, bs_30M3!$A:$A, $A16) - SUMIFS(bs_30M3!$AQ:$AQ, bs_30M3!$A:$A, $A16, bs_30M3!$CJ:$CJ, ">=" & MATCH(Simulador!$B15, {"A1";"A2";"B1";"B2";"B3";"C1";"C2";"D1";"D2";"E1"}, 0))) | J16: =IF(Simulador!$B15="", "", SUMIFS(bs_30M3!$AL:$AL, bs_30M3!$A:$A, $A16) - SUMIFS(bs_30M3!$AL:$AL, bs_30M3!$A:$A, $A16, bs_30M3!$CJ:$CJ, ">=" & MATCH(Simulador!$B15, {"A1";"A2";"B1";"B2";"B3";"C1";"C2";"D1";"D2";"E1"}, 0))) | K16: =IF(Simulador!$B15="", "", SUMIFS(bs_60M6!$AR:$AR, bs_60M6!$A:$A, $A16) - SUMIFS(bs_60M6!$AR:$AR, bs_60M6!$A:$A, $A16, bs_60M6!$CJ:$CJ, ">=" & MATCH(Simulador!$B15, {"A1";"A2";"B1";"B2";"B3";"C1";"C2";"D1";"D2";"E1"}, 0))) | L16: =IF(Simulador!$B15="", "", SUMIFS(bs_60M6!$AM:$AM, bs_60M6!$A:$A, $A16) - SUMIFS(bs_60M6!$AM:$AM, bs_60M6!$A:$A, $A16, bs_60M6!$CJ:$CJ, ">=" & MATCH(Simulador!$B15, {"A1";"A2";"B1";"B2";"B3";"C1";"C2";"D1";"D2";"E1"}, 0))) | M16: =IFERROR(E16/F16,"") | N16: =IFERROR(G16/H16,"") | O16: =IFERROR(I16/J16,"") | P16: =IFERROR(K16/L16,"") | Q16: =IFERROR(C16/B16,"") | R16: =IFERROR(D16/C16,"") | S16: =IFERROR(_xlfn.XLOOKUP(A16,BS_CONSOLIDADO!A:A,BS_CONSOLIDADO!B:B,"")-B16,"") | T16: =IFERROR(_xlfn.XLOOKUP(A16,BS_CONSOLIDADO!A:A,BS_CONSOLIDADO!C:C,"")-C16,"") | U16: =IFERROR(_xlfn.XLOOKUP(A16,BS_CONSOLIDADO!A:A,BS_CONSOLIDADO!D:D)-D16,"") | V16: =IFERROR(_xlfn.XLOOKUP($A16,BS_CONSOLIDADO!$A:$A,BS_CONSOLIDADO!E:E,"")-E16,"") | W16: =IFERROR(_xlfn.XLOOKUP($A16,BS_CONSOLIDADO!$A:$A,BS_CONSOLIDADO!F:F,"")-F16,"") | X16: =IFERROR(_xlfn.XLOOKUP($A16,BS_CONSOLIDADO!A:A,BS_CONSOLIDADO!G:G,"")-G16,"") | Y16: =IFERROR(_xlfn.XLOOKUP($A16,BS_CONSOLIDADO!$A:$A,BS_CONSOLIDADO!H:H,"")-H16,"") | Z16: =IFERROR(_xlfn.XLOOKUP($A16,BS_CONSOLIDADO!$A:$A,BS_CONSOLIDADO!I:I,"")-I16,"") | AA16: =IFERROR(_xlfn.XLOOKUP($A16,BS_CONSOLIDADO!$A:$A,BS_CONSOLIDADO!J:J,"")-J16,"") | AB16: =IFERROR(_xlfn.XLOOKUP($A16,BS_CONSOLIDADO!$A:$A,BS_CONSOLIDADO!K:K,"")-K16,"") | AC16: =IFERROR(_xlfn.XLOOKUP($A16,BS_CONSOLIDADO!$A:$A,BS_CONSOLIDADO!L:L,"")-L16,"")
A17: Parceiro 11 | B17: =IF(Simulador!$B16="", "", SUMIFS(bs_propostas!$D:$D, bs_propostas!$A:$A, $A17)) | C17: =IF(Simulador!$B16="", "", SUMIFS(bs_propostas!$E:$E, bs_propostas!$A:$A, $A17) - SUMIFS(bs_propostas!$E:$E, bs_propostas!$A:$A, $A17, bs_propostas!$CJ:$CJ, ">=" & MATCH(Simulador!$B16, {"A1";"A2";"B1";"B2";"B3";"C1";"C2";"D1";"D2";"E1"}, 0))) | D17: =IF(Simulador!$B16="", "", SUMIFS(bs_propostas!$F:$F, bs_propostas!$A:$A, $A17) - SUMIFS(bs_propostas!$F:$F, bs_propostas!$A:$A, $A17, bs_propostas!$CJ:$CJ, ">=" & MATCH(Simulador!$B16, {"A1";"A2";"B1";"B2";"B3";"C1";"C2";"D1";"D2";"E1"}, 0))) | E17: =IF(Simulador!$B16="", "", SUMIFS(bs_30M2!$AN:$AN, bs_30M2!$A:$A, $A17) - SUMIFS(bs_30M2!$AN:$AN, bs_30M2!$A:$A, $A17, bs_30M2!$CJ:$CJ, ">=" & MATCH(Simulador!$B16, {"A1";"A2";"B1";"B2";"B3";"C1";"C2";"D1";"D2";"E1"}, 0))) | F17: =IF(Simulador!$B16="", "", SUMIFS(bs_30M2!$AI:$AI, bs_30M2!$A:$A, $A17) - SUMIFS(bs_30M2!$AI:$AI, bs_30M2!$A:$A, $A17, bs_30M2!$CJ:$CJ, ">=" & MATCH(Simulador!$B16, {"A1";"A2";"B1";"B2";"B3";"C1";"C2";"D1";"D2";"E1"}, 0))) | G17: =IF(Simulador!$B16="", "", SUMIFS(bs_30M2!$AP:$AP, bs_30M2!$A:$A, $A17) - SUMIFS(bs_30M2!$AP:$AP, bs_30M2!$A:$A, $A17, bs_30M2!$CJ:$CJ, ">=" & MATCH(Simulador!$B16, {"A1";"A2";"B1";"B2";"B3";"C1";"C2";"D1";"D2";"E1"}, 0))) | H17: =IF(Simulador!$B16="", "", SUMIFS(bs_30M2!$AK:$AK, bs_30M2!$A:$A, $A17) - SUMIFS(bs_30M2!$AK:$AK, bs_30M2!$A:$A, $A17, bs_30M2!$CJ:$CJ, ">=" & MATCH(Simulador!$B16, {"A1";"A2";"B1";"B2";"B3";"C1";"C2";"D1";"D2";"E1"}, 0))) | I17: =IF(Simulador!$B16="", "", SUMIFS(bs_30M3!$AQ:$AQ, bs_30M3!$A:$A, $A17) - SUMIFS(bs_30M3!$AQ:$AQ, bs_30M3!$A:$A, $A17, bs_30M3!$CJ:$CJ, ">=" & MATCH(Simulador!$B16, {"A1";"A2";"B1";"B2";"B3";"C1";"C2";"D1";"D2";"E1"}, 0))) | J17: =IF(Simulador!$B16="", "", SUMIFS(bs_30M3!$AL:$AL, bs_30M3!$A:$A, $A17) - SUMIFS(bs_30M3!$AL:$AL, bs_30M3!$A:$A, $A17, bs_30M3!$CJ:$CJ, ">=" & MATCH(Simulador!$B16, {"A1";"A2";"B1";"B2";"B3";"C1";"C2";"D1";"D2";"E1"}, 0))) | K17: =IF(Simulador!$B16="", "", SUMIFS(bs_60M6!$AR:$AR, bs_60M6!$A:$A, $A17) - SUMIFS(bs_60M6!$AR:$AR, bs_60M6!$A:$A, $A17, bs_60M6!$CJ:$CJ, ">=" & MATCH(Simulador!$B16, {"A1";"A2";"B1";"B2";"B3";"C1";"C2";"D1";"D2";"E1"}, 0))) | L17: =IF(Simulador!$B16="", "", SUMIFS(bs_60M6!$AM:$AM, bs_60M6!$A:$A, $A17) - SUMIFS(bs_60M6!$AM:$AM, bs_60M6!$A:$A, $A17, bs_60M6!$CJ:$CJ, ">=" & MATCH(Simulador!$B16, {"A1";"A2";"B1";"B2";"B3";"C1";"C2";"D1";"D2";"E1"}, 0))) | M17: =IFERROR(E17/F17,"") | N17: =IFERROR(G17/H17,"") | O17: =IFERROR(I17/J17,"") | P17: =IFERROR(K17/L17,"") | Q17: =IFERROR(C17/B17,"") | R17: =IFERROR(D17/C17,"") | S17: =IFERROR(_xlfn.XLOOKUP(A17,BS_CONSOLIDADO!A:A,BS_CONSOLIDADO!B:B,"")-B17,"") | T17: =IFERROR(_xlfn.XLOOKUP(A17,BS_CONSOLIDADO!A:A,BS_CONSOLIDADO!C:C,"")-C17,"") | U17: =IFERROR(_xlfn.XLOOKUP(A17,BS_CONSOLIDADO!A:A,BS_CONSOLIDADO!D:D)-D17,"") | V17: =IFERROR(_xlfn.XLOOKUP($A17,BS_CONSOLIDADO!$A:$A,BS_CONSOLIDADO!E:E,"")-E17,"") | W17: =IFERROR(_xlfn.XLOOKUP($A17,BS_CONSOLIDADO!$A:$A,BS_CONSOLIDADO!F:F,"")-F17,"") | X17: =IFERROR(_xlfn.XLOOKUP($A17,BS_CONSOLIDADO!A:A,BS_CONSOLIDADO!G:G,"")-G17,"") | Y17: =IFERROR(_xlfn.XLOOKUP($A17,BS_CONSOLIDADO!$A:$A,BS_CONSOLIDADO!H:H,"")-H17,"") | Z17: =IFERROR(_xlfn.XLOOKUP($A17,BS_CONSOLIDADO!$A:$A,BS_CONSOLIDADO!I:I,"")-I17,"") | AA17: =IFERROR(_xlfn.XLOOKUP($A17,BS_CONSOLIDADO!$A:$A,BS_CONSOLIDADO!J:J,"")-J17,"") | AB17: =IFERROR(_xlfn.XLOOKUP($A17,BS_CONSOLIDADO!$A:$A,BS_CONSOLIDADO!K:K,"")-K17,"") | AC17: =IFERROR(_xlfn.XLOOKUP($A17,BS_CONSOLIDADO!$A:$A,BS_CONSOLIDADO!L:L,"")-L17,"")
A18: Parceiro 12 | B18: =IF(Simulador!$B17="", "", SUMIFS(bs_propostas!$D:$D, bs_propostas!$A:$A, $A18)) | C18: =IF(Simulador!$B17="", "", SUMIFS(bs_propostas!$E:$E, bs_propostas!$A:$A, $A18) - SUMIFS(bs_propostas!$E:$E, bs_propostas!$A:$A, $A18, bs_propostas!$CJ:$CJ, ">=" & MATCH(Simulador!$B17, {"A1";"A2";"B1";"B2";"B3";"C1";"C2";"D1";"D2";"E1"}, 0))) | D18: =IF(Simulador!$B17="", "", SUMIFS(bs_propostas!$F:$F, bs_propostas!$A:$A, $A18) - SUMIFS(bs_propostas!$F:$F, bs_propostas!$A:$A, $A18, bs_propostas!$CJ:$CJ, ">=" & MATCH(Simulador!$B17, {"A1";"A2";"B1";"B2";"B3";"C1";"C2";"D1";"D2";"E1"}, 0))) | E18: =IF(Simulador!$B17="", "", SUMIFS(bs_30M2!$AN:$AN, bs_30M2!$A:$A, $A18) - SUMIFS(bs_30M2!$AN:$AN, bs_30M2!$A:$A, $A18, bs_30M2!$CJ:$CJ, ">=" & MATCH(Simulador!$B17, {"A1";"A2";"B1";"B2";"B3";"C1";"C2";"D1";"D2";"E1"}, 0))) | F18: =IF(Simulador!$B17="", "", SUMIFS(bs_30M2!$AI:$AI, bs_30M2!$A:$A, $A18) - SUMIFS(bs_30M2!$AI:$AI, bs_30M2!$A:$A, $A18, bs_30M2!$CJ:$CJ, ">=" & MATCH(Simulador!$B17, {"A1";"A2";"B1";"B2";"B3";"C1";"C2";"D1";"D2";"E1"}, 0))) | G18: =IF(Simulador!$B17="", "", SUMIFS(bs_30M2!$AP:$AP, bs_30M2!$A:$A, $A18) - SUMIFS(bs_30M2!$AP:$AP, bs_30M2!$A:$A, $A18, bs_30M2!$CJ:$CJ, ">=" & MATCH(Simulador!$B17, {"A1";"A2";"B1";"B2";"B3";"C1";"C2";"D1";"D2";"E1"}, 0))) | H18: =IF(Simulador!$B17="", "", SUMIFS(bs_30M2!$AK:$AK, bs_30M2!$A:$A, $A18) - SUMIFS(bs_30M2!$AK:$AK, bs_30M2!$A:$A, $A18, bs_30M2!$CJ:$CJ, ">=" & MATCH(Simulador!$B17, {"A1";"A2";"B1";"B2";"B3";"C1";"C2";"D1";"D2";"E1"}, 0))) | I18: =IF(Simulador!$B17="", "", SUMIFS(bs_30M3!$AQ:$AQ, bs_30M3!$A:$A, $A18) - SUMIFS(bs_30M3!$AQ:$AQ, bs_30M3!$A:$A, $A18, bs_30M3!$CJ:$CJ, ">=" & MATCH(Simulador!$B17, {"A1";"A2";"B1";"B2";"B3";"C1";"C2";"D1";"D2";"E1"}, 0))) | J18: =IF(Simulador!$B17="", "", SUMIFS(bs_30M3!$AL:$AL, bs_30M3!$A:$A, $A18) - SUMIFS(bs_30M3!$AL:$AL, bs_30M3!$A:$A, $A18, bs_30M3!$CJ:$CJ, ">=" & MATCH(Simulador!$B17, {"A1";"A2";"B1";"B2";"B3";"C1";"C2";"D1";"D2";"E1"}, 0))) | K18: =IF(Simulador!$B17="", "", SUMIFS(bs_60M6!$AR:$AR, bs_60M6!$A:$A, $A18) - SUMIFS(bs_60M6!$AR:$AR, bs_60M6!$A:$A, $A18, bs_60M6!$CJ:$CJ, ">=" & MATCH(Simulador!$B17, {"A1";"A2";"B1";"B2";"B3";"C1";"C2";"D1";"D2";"E1"}, 0))) | L18: =IF(Simulador!$B17="", "", SUMIFS(bs_60M6!$AM:$AM, bs_60M6!$A:$A, $A18) - SUMIFS(bs_60M6!$AM:$AM, bs_60M6!$A:$A, $A18, bs_60M6!$CJ:$CJ, ">=" & MATCH(Simulador!$B17, {"A1";"A2";"B1";"B2";"B3";"C1";"C2";"D1";"D2";"E1"}, 0))) | M18: =IFERROR(E18/F18,"") | N18: =IFERROR(G18/H18,"") | O18: =IFERROR(I18/J18,"") | P18: =IFERROR(K18/L18,"") | Q18: =IFERROR(C18/B18,"") | R18: =IFERROR(D18/C18,"") | S18: =IFERROR(_xlfn.XLOOKUP(A18,BS_CONSOLIDADO!A:A,BS_CONSOLIDADO!B:B,"")-B18,"") | T18: =IFERROR(_xlfn.XLOOKUP(A18,BS_CONSOLIDADO!A:A,BS_CONSOLIDADO!C:C,"")-C18,"") | U18: =IFERROR(_xlfn.XLOOKUP(A18,BS_CONSOLIDADO!A:A,BS_CONSOLIDADO!D:D)-D18,"") | V18: =IFERROR(_xlfn.XLOOKUP($A18,BS_CONSOLIDADO!$A:$A,BS_CONSOLIDADO!E:E,"")-E18,"") | W18: =IFERROR(_xlfn.XLOOKUP($A18,BS_CONSOLIDADO!$A:$A,BS_CONSOLIDADO!F:F,"")-F18,"") | X18: =IFERROR(_xlfn.XLOOKUP($A18,BS_CONSOLIDADO!A:A,BS_CONSOLIDADO!G:G,"")-G18,"") | Y18: =IFERROR(_xlfn.XLOOKUP($A18,BS_CONSOLIDADO!$A:$A,BS_CONSOLIDADO!H:H,"")-H18,"") | Z18: =IFERROR(_xlfn.XLOOKUP($A18,BS_CONSOLIDADO!$A:$A,BS_CONSOLIDADO!I:I,"")-I18,"") | AA18: =IFERROR(_xlfn.XLOOKUP($A18,BS_CONSOLIDADO!$A:$A,BS_CONSOLIDADO!J:J,"")-J18,"") | AB18: =IFERROR(_xlfn.XLOOKUP($A18,BS_CONSOLIDADO!$A:$A,BS_CONSOLIDADO!K:K,"")-K18,"") | AC18: =IFERROR(_xlfn.XLOOKUP($A18,BS_CONSOLIDADO!$A:$A,BS_CONSOLIDADO!L:L,"")-L18,"")
A19: Parceiro 13 | B19: =IF(Simulador!$B18="", "", SUMIFS(bs_propostas!$D:$D, bs_propostas!$A:$A, $A19)) | C19: =IF(Simulador!$B18="", "", SUMIFS(bs_propostas!$E:$E, bs_propostas!$A:$A, $A19) - SUMIFS(bs_propostas!$E:$E, bs_propostas!$A:$A, $A19, bs_propostas!$CJ:$CJ, ">=" & MATCH(Simulador!$B18, {"A1";"A2";"B1";"B2";"B3";"C1";"C2";"D1";"D2";"E1"}, 0))) | D19: =IF(Simulador!$B18="", "", SUMIFS(bs_propostas!$F:$F, bs_propostas!$A:$A, $A19) - SUMIFS(bs_propostas!$F:$F, bs_propostas!$A:$A, $A19, bs_propostas!$CJ:$CJ, ">=" & MATCH(Simulador!$B18, {"A1";"A2";"B1";"B2";"B3";"C1";"C2";"D1";"D2";"E1"}, 0))) | E19: =IF(Simulador!$B18="", "", SUMIFS(bs_30M2!$AN:$AN, bs_30M2!$A:$A, $A19) - SUMIFS(bs_30M2!$AN:$AN, bs_30M2!$A:$A, $A19, bs_30M2!$CJ:$CJ, ">=" & MATCH(Simulador!$B18, {"A1";"A2";"B1";"B2";"B3";"C1";"C2";"D1";"D2";"E1"}, 0))) | F19: =IF(Simulador!$B18="", "", SUMIFS(bs_30M2!$AI:$AI, bs_30M2!$A:$A, $A19) - SUMIFS(bs_30M2!$AI:$AI, bs_30M2!$A:$A, $A19, bs_30M2!$CJ:$CJ, ">=" & MATCH(Simulador!$B18, {"A1";"A2";"B1";"B2";"B3";"C1";"C2";"D1";"D2";"E1"}, 0))) | G19: =IF(Simulador!$B18="", "", SUMIFS(bs_30M2!$AP:$AP, bs_30M2!$A:$A, $A19) - SUMIFS(bs_30M2!$AP:$AP, bs_30M2!$A:$A, $A19, bs_30M2!$CJ:$CJ, ">=" & MATCH(Simulador!$B18, {"A1";"A2";"B1";"B2";"B3";"C1";"C2";"D1";"D2";"E1"}, 0))) | H19: =IF(Simulador!$B18="", "", SUMIFS(bs_30M2!$AK:$AK, bs_30M2!$A:$A, $A19) - SUMIFS(bs_30M2!$AK:$AK, bs_30M2!$A:$A, $A19, bs_30M2!$CJ:$CJ, ">=" & MATCH(Simulador!$B18, {"A1";"A2";"B1";"B2";"B3";"C1";"C2";"D1";"D2";"E1"}, 0))) | I19: =IF(Simulador!$B18="", "", SUMIFS(bs_30M3!$AQ:$AQ, bs_30M3!$A:$A, $A19) - SUMIFS(bs_30M3!$AQ:$AQ, bs_30M3!$A:$A, $A19, bs_30M3!$CJ:$CJ, ">=" & MATCH(Simulador!$B18, {"A1";"A2";"B1";"B2";"B3";"C1";"C2";"D1";"D2";"E1"}, 0))) | J19: =IF(Simulador!$B18="", "", SUMIFS(bs_30M3!$AL:$AL, bs_30M3!$A:$A, $A19) - SUMIFS(bs_30M3!$AL:$AL, bs_30M3!$A:$A, $A19, bs_30M3!$CJ:$CJ, ">=" & MATCH(Simulador!$B18, {"A1";"A2";"B1";"B2";"B3";"C1";"C2";"D1";"D2";"E1"}, 0))) | K19: =IF(Simulador!$B18="", "", SUMIFS(bs_60M6!$AR:$AR, bs_60M6!$A:$A, $A19) - SUMIFS(bs_60M6!$AR:$AR, bs_60M6!$A:$A, $A19, bs_60M6!$CJ:$CJ, ">=" & MATCH(Simulador!$B18, {"A1";"A2";"B1";"B2";"B3";"C1";"C2";"D1";"D2";"E1"}, 0))) | L19: =IF(Simulador!$B18="", "", SUMIFS(bs_60M6!$AM:$AM, bs_60M6!$A:$A, $A19) - SUMIFS(bs_60M6!$AM:$AM, bs_60M6!$A:$A, $A19, bs_60M6!$CJ:$CJ, ">=" & MATCH(Simulador!$B18, {"A1";"A2";"B1";"B2";"B3";"C1";"C2";"D1";"D2";"E1"}, 0))) | M19: =IFERROR(E19/F19,"") | N19: =IFERROR(G19/H19,"") | O19: =IFERROR(I19/J19,"") | P19: =IFERROR(K19/L19,"") | Q19: =IFERROR(C19/B19,"") | R19: =IFERROR(D19/C19,"") | S19: =IFERROR(_xlfn.XLOOKUP(A19,BS_CONSOLIDADO!A:A,BS_CONSOLIDADO!B:B,"")-B19,"") | T19: =IFERROR(_xlfn.XLOOKUP(A19,BS_CONSOLIDADO!A:A,BS_CONSOLIDADO!C:C,"")-C19,"") | U19: =IFERROR(_xlfn.XLOOKUP(A19,BS_CONSOLIDADO!A:A,BS_CONSOLIDADO!D:D)-D19,"") | V19: =IFERROR(_xlfn.XLOOKUP($A19,BS_CONSOLIDADO!$A:$A,BS_CONSOLIDADO!E:E,"")-E19,"") | W19: =IFERROR(_xlfn.XLOOKUP($A19,BS_CONSOLIDADO!$A:$A,BS_CONSOLIDADO!F:F,"")-F19,"") | X19: =IFERROR(_xlfn.XLOOKUP($A19,BS_CONSOLIDADO!A:A,BS_CONSOLIDADO!G:G,"")-G19,"") | Y19: =IFERROR(_xlfn.XLOOKUP($A19,BS_CONSOLIDADO!$A:$A,BS_CONSOLIDADO!H:H,"")-H19,"") | Z19: =IFERROR(_xlfn.XLOOKUP($A19,BS_CONSOLIDADO!$A:$A,BS_CONSOLIDADO!I:I,"")-I19,"") | AA19: =IFERROR(_xlfn.XLOOKUP($A19,BS_CONSOLIDADO!$A:$A,BS_CONSOLIDADO!J:J,"")-J19,"") | AB19: =IFERROR(_xlfn.XLOOKUP($A19,BS_CONSOLIDADO!$A:$A,BS_CONSOLIDADO!K:K,"")-K19,"") | AC19: =IFERROR(_xlfn.XLOOKUP($A19,BS_CONSOLIDADO!$A:$A,BS_CONSOLIDADO!L:L,"")-L19,"")
... A26: Parceiro 20 | B26: =IF(Simulador!$B25="", "", SUMIFS(bs_propostas!$D:$D, bs_propostas!$A:$A, $A26)) | C26: =IF(Simulador!$B25="", "", SUMIFS(bs_propostas!$E:$E, bs_propostas!$A:$A, $A26) - SUMIFS(bs_propostas!$E:$E, bs_propostas!$A:$A, $A26, bs_propostas!$CJ:$CJ, ">=" & MATCH(Simulador!$B25, {"A1";"A2";"B1";"B2";"B3";"C1";"C2";"D1";"D2";"E1"}, 0))) | D26: =IF(Simulador!$B25="", "", SUMIFS(bs_propostas!$F:$F, bs_propostas!$A:$A, $A26) - SUMIFS(bs_propostas!$F:$F, bs_propostas!$A:$A, $A26, bs_propostas!$CJ:$CJ, ">=" & MATCH(Simulador!$B25, {"A1";"A2";"B1";"B2";"B3";"C1";"C2";"D1";"D2";"E1"}, 0))) | E26: =IF(Simulador!$B25="", "", SUMIFS(bs_30M2!$AN:$AN, bs_30M2!$A:$A, $A26) - SUMIFS(bs_30M2!$AN:$AN, bs_30M2!$A:$A, $A26, bs_30M2!$CJ:$CJ, ">=" & MATCH(Simulador!$B25, {"A1";"A2";"B1";"B2";"B3";"C1";"C2";"D1";"D2";"E1"}, 0))) | F26: =IF(Simulador!$B25="", "", SUMIFS(bs_30M2!$AI:$AI, bs_30M2!$A:$A, $A26) - SUMIFS(bs_30M2!$AI:$AI, bs_30M2!$A:$A, $A26, bs_30M2!$CJ:$CJ, ">=" & MATCH(Simulador!$B25, {"A1";"A2";"B1";"B2";"B3";"C1";"C2";"D1";"D2";"E1"}, 0))) | G26: =IF(Simulador!$B25="", "", SUMIFS(bs_30M2!$AP:$AP, bs_30M2!$A:$A, $A26) - SUMIFS(bs_30M2!$AP:$AP, bs_30M2!$A:$A, $A26, bs_30M2!$CJ:$CJ, ">=" & MATCH(Simulador!$B25, {"A1";"A2";"B1";"B2";"B3";"C1";"C2";"D1";"D2";"E1"}, 0))) | H26: =IF(Simulador!$B25="", "", SUMIFS(bs_30M2!$AK:$AK, bs_30M2!$A:$A, $A26) - SUMIFS(bs_30M2!$AK:$AK, bs_30M2!$A:$A, $A26, bs_30M2!$CJ:$CJ, ">=" & MATCH(Simulador!$B25, {"A1";"A2";"B1";"B2";"B3";"C1";"C2";"D1";"D2";"E1"}, 0))) | I26: =IF(Simulador!$B25="", "", SUMIFS(bs_30M3!$AQ:$AQ, bs_30M3!$A:$A, $A26) - SUMIFS(bs_30M3!$AQ:$AQ, bs_30M3!$A:$A, $A26, bs_30M3!$CJ:$CJ, ">=" & MATCH(Simulador!$B25, {"A1";"A2";"B1";"B2";"B3";"C1";"C2";"D1";"D2";"E1"}, 0))) | J26: =IF(Simulador!$B25="", "", SUMIFS(bs_30M3!$AL:$AL, bs_30M3!$A:$A, $A26) - SUMIFS(bs_30M3!$AL:$AL, bs_30M3!$A:$A, $A26, bs_30M3!$CJ:$CJ, ">=" & MATCH(Simulador!$B25, {"A1";"A2";"B1";"B2";"B3";"C1";"C2";"D1";"D2";"E1"}, 0))) | K26: =IF(Simulador!$B25="", "", SUMIFS(bs_60M6!$AR:$AR, bs_60M6!$A:$A, $A26) - SUMIFS(bs_60M6!$AR:$AR, bs_60M6!$A:$A, $A26, bs_60M6!$CJ:$CJ, ">=" & MATCH(Simulador!$B25, {"A1";"A2";"B1";"B2";"B3";"C1";"C2";"D1";"D2";"E1"}, 0))) | L26: =IF(Simulador!$B25="", "", SUMIFS(bs_60M6!$AM:$AM, bs_60M6!$A:$A, $A26) - SUMIFS(bs_60M6!$AM:$AM, bs_60M6!$A:$A, $A26, bs_60M6!$CJ:$CJ, ">=" & MATCH(Simulador!$B25, {"A1";"A2";"B1";"B2";"B3";"C1";"C2";"D1";"D2";"E1"}, 0))) | M26: =IFERROR(E26/F26,"") | N26: =IFERROR(G26/H26,"") | O26: =IFERROR(I26/J26,"") | P26: =IFERROR(K26/L26,"") | Q26: =IFERROR(C26/B26,"") | R26: =IFERROR(D26/C26,"") | S26: =IFERROR(_xlfn.XLOOKUP(A26,BS_CONSOLIDADO!A:A,BS_CONSOLIDADO!B:B,"")-B26,"") | T26: =IFERROR(_xlfn.XLOOKUP(A26,BS_CONSOLIDADO!A:A,BS_CONSOLIDADO!C:C,"")-C26,"") | U26: =IFERROR(_xlfn.XLOOKUP(A26,BS_CONSOLIDADO!A:A,BS_CONSOLIDADO!D:D)-D26,"") | V26: =IFERROR(_xlfn.XLOOKUP($A26,BS_CONSOLIDADO!$A:$A,BS_CONSOLIDADO!E:E,"")-E26,"") | W26: =IFERROR(_xlfn.XLOOKUP($A26,BS_CONSOLIDADO!$A:$A,BS_CONSOLIDADO!F:F,"")-F26,"") | X26: =IFERROR(_xlfn.XLOOKUP($A26,BS_CONSOLIDADO!A:A,BS_CONSOLIDADO!G:G,"")-G26,"") | Y26: =IFERROR(_xlfn.XLOOKUP($A26,BS_CONSOLIDADO!$A:$A,BS_CONSOLIDADO!H:H,"")-H26,"") | Z26: =IFERROR(_xlfn.XLOOKUP($A26,BS_CONSOLIDADO!$A:$A,BS_CONSOLIDADO!I:I,"")-I26,"") | AA26: =IFERROR(_xlfn.XLOOKUP($A26,BS_CONSOLIDADO!$A:$A,BS_CONSOLIDADO!J:J,"")-J26,"") | AB26: =IFERROR(_xlfn.XLOOKUP($A26,BS_CONSOLIDADO!$A:$A,BS_CONSOLIDADO!K:K,"")-K26,"") | AC26: =IFERROR(_xlfn.XLOOKUP($A26,BS_CONSOLIDADO!$A:$A,BS_CONSOLIDADO!L:L,"")-L26,"")
B27: =IF(Simulador!$B26="", "", SUMIFS(bs_propostas!$D:$D, bs_propostas!$A:$A, $A27)) | C27: =IF(Simulador!$B26="", "", SUMIFS(bs_propostas!$E:$E, bs_propostas!$A:$A, $A27) - SUMIFS(bs_propostas!$E:$E, bs_propostas!$A:$A, $A27, bs_propostas!$CJ:$CJ, ">=" & MATCH(Simulador!$B26, {"A1";"A2";"B1";"B2";"B3";"C1";"C2";"D1";"D2";"E1"}, 0))) | D27: =IF(Simulador!$B26="", "", SUMIFS(bs_propostas!$F:$F, bs_propostas!$A:$A, $A27) - SUMIFS(bs_propostas!$F:$F, bs_propostas!$A:$A, $A27, bs_propostas!$CJ:$CJ, ">=" & MATCH(Simulador!$B26, {"A1";"A2";"B1";"B2";"B3";"C1";"C2";"D1";"D2";"E1"}, 0))) | E27: =IF(Simulador!$B26="", "", SUMIFS(bs_30M2!$AN:$AN, bs_30M2!$A:$A, $A27) - SUMIFS(bs_30M2!$AN:$AN, bs_30M2!$A:$A, $A27, bs_30M2!$CJ:$CJ, ">=" & MATCH(Simulador!$B26, {"A1";"A2";"B1";"B2";"B3";"C1";"C2";"D1";"D2";"E1"}, 0))) | F27: =IF(Simulador!$B26="", "", SUMIFS(bs_30M2!$AI:$AI, bs_30M2!$A:$A, $A27) - SUMIFS(bs_30M2!$AI:$AI, bs_30M2!$A:$A, $A27, bs_30M2!$CJ:$CJ, ">=" & MATCH(Simulador!$B26, {"A1";"A2";"B1";"B2";"B3";"C1";"C2";"D1";"D2";"E1"}, 0))) | G27: =IF(Simulador!$B26="", "", SUMIFS(bs_30M2!$AP:$AP, bs_30M2!$A:$A, $A27) - SUMIFS(bs_30M2!$AP:$AP, bs_30M2!$A:$A, $A27, bs_30M2!$CJ:$CJ, ">=" & MATCH(Simulador!$B26, {"A1";"A2";"B1";"B2";"B3";"C1";"C2";"D1";"D2";"E1"}, 0))) | H27: =IF(Simulador!$B26="", "", SUMIFS(bs_30M2!$AK:$AK, bs_30M2!$A:$A, $A27) - SUMIFS(bs_30M2!$AK:$AK, bs_30M2!$A:$A, $A27, bs_30M2!$CJ:$CJ, ">=" & MATCH(Simulador!$B26, {"A1";"A2";"B1";"B2";"B3";"C1";"C2";"D1";"D2";"E1"}, 0))) | I27: =IF(Simulador!$B26="", "", SUMIFS(bs_30M3!$AQ:$AQ, bs_30M3!$A:$A, $A27) - SUMIFS(bs_30M3!$AQ:$AQ, bs_30M3!$A:$A, $A27, bs_30M3!$CJ:$CJ, ">=" & MATCH(Simulador!$B26, {"A1";"A2";"B1";"B2";"B3";"C1";"C2";"D1";"D2";"E1"}, 0))) | J27: =IF(Simulador!$B26="", "", SUMIFS(bs_30M3!$AL:$AL, bs_30M3!$A:$A, $A27) - SUMIFS(bs_30M3!$AL:$AL, bs_30M3!$A:$A, $A27, bs_30M3!$CJ:$CJ, ">=" & MATCH(Simulador!$B26, {"A1";"A2";"B1";"B2";"B3";"C1";"C2";"D1";"D2";"E1"}, 0))) | K27: =IF(Simulador!$B26="", "", SUMIFS(bs_60M6!$AR:$AR, bs_60M6!$A:$A, $A27) - SUMIFS(bs_60M6!$AR:$AR, bs_60M6!$A:$A, $A27, bs_60M6!$CJ:$CJ, ">=" & MATCH(Simulador!$B26, {"A1";"A2";"B1";"B2";"B3";"C1";"C2";"D1";"D2";"E1"}, 0))) | L27: =IF(Simulador!$B26="", "", SUMIFS(bs_60M6!$AM:$AM, bs_60M6!$A:$A, $A27) - SUMIFS(bs_60M6!$AM:$AM, bs_60M6!$A:$A, $A27, bs_60M6!$CJ:$CJ, ">=" & MATCH(Simulador!$B26, {"A1";"A2";"B1";"B2";"B3";"C1";"C2";"D1";"D2";"E1"}, 0))) | M27: =IFERROR(E27/F27,"") | N27: =IFERROR(G27/H27,"") | O27: =IFERROR(I27/J27,"") | P27: =IFERROR(K27/L27,"") | Q27: =IFERROR(C27/B27,"") | R27: =IFERROR(D27/C27,"") | S27: =IFERROR(_xlfn.XLOOKUP(A27,BS_CONSOLIDADO!A:A,BS_CONSOLIDADO!B:B,"")-B27,"") | T27: =IFERROR(_xlfn.XLOOKUP(A27,BS_CONSOLIDADO!A:A,BS_CONSOLIDADO!C:C,"")-C27,"") | U27: =IFERROR(_xlfn.XLOOKUP(A27,BS_CONSOLIDADO!A:A,BS_CONSOLIDADO!D:D)-D27,"") | V27: =IFERROR(_xlfn.XLOOKUP($A27,BS_CONSOLIDADO!$A:$A,BS_CONSOLIDADO!E:E,"")-E27,"") | W27: =IFERROR(_xlfn.XLOOKUP($A27,BS_CONSOLIDADO!$A:$A,BS_CONSOLIDADO!F:F,"")-F27,"") | X27: =IFERROR(_xlfn.XLOOKUP($A27,BS_CONSOLIDADO!A:A,BS_CONSOLIDADO!G:G,"")-G27,"") | Y27: =IFERROR(_xlfn.XLOOKUP($A27,BS_CONSOLIDADO!$A:$A,BS_CONSOLIDADO!H:H,"")-H27,"") | Z27: =IFERROR(_xlfn.XLOOKUP($A27,BS_CONSOLIDADO!$A:$A,BS_CONSOLIDADO!I:I,"")-I27,"") | AA27: =IFERROR(_xlfn.XLOOKUP($A27,BS_CONSOLIDADO!$A:$A,BS_CONSOLIDADO!J:J,"")-J27,"") | AB27: =IFERROR(_xlfn.XLOOKUP($A27,BS_CONSOLIDADO!$A:$A,BS_CONSOLIDADO!K:K,"")-K27,"") | AC27: =IFERROR(_xlfn.XLOOKUP($A27,BS_CONSOLIDADO!$A:$A,BS_CONSOLIDADO!L:L,"")-L27,"")
B28: =IF(Simulador!$B27="", "", SUMIFS(bs_propostas!$D:$D, bs_propostas!$A:$A, $A28)) | C28: =IF(Simulador!$B27="", "", SUMIFS(bs_propostas!$E:$E, bs_propostas!$A:$A, $A28) - SUMIFS(bs_propostas!$E:$E, bs_propostas!$A:$A, $A28, bs_propostas!$CJ:$CJ, ">=" & MATCH(Simulador!$B27, {"A1";"A2";"B1";"B2";"B3";"C1";"C2";"D1";"D2";"E1"}, 0))) | D28: =IF(Simulador!$B27="", "", SUMIFS(bs_propostas!$F:$F, bs_propostas!$A:$A, $A28) - SUMIFS(bs_propostas!$F:$F, bs_propostas!$A:$A, $A28, bs_propostas!$CJ:$CJ, ">=" & MATCH(Simulador!$B27, {"A1";"A2";"B1";"B2";"B3";"C1";"C2";"D1";"D2";"E1"}, 0))) | E28: =IF(Simulador!$B27="", "", SUMIFS(bs_30M2!$AN:$AN, bs_30M2!$A:$A, $A28) - SUMIFS(bs_30M2!$AN:$AN, bs_30M2!$A:$A, $A28, bs_30M2!$CJ:$CJ, ">=" & MATCH(Simulador!$B27, {"A1";"A2";"B1";"B2";"B3";"C1";"C2";"D1";"D2";"E1"}, 0))) | F28: =IF(Simulador!$B27="", "", SUMIFS(bs_30M2!$AI:$AI, bs_30M2!$A:$A, $A28) - SUMIFS(bs_30M2!$AI:$AI, bs_30M2!$A:$A, $A28, bs_30M2!$CJ:$CJ, ">=" & MATCH(Simulador!$B27, {"A1";"A2";"B1";"B2";"B3";"C1";"C2";"D1";"D2";"E1"}, 0))) | G28: =IF(Simulador!$B27="", "", SUMIFS(bs_30M2!$AP:$AP, bs_30M2!$A:$A, $A28) - SUMIFS(bs_30M2!$AP:$AP, bs_30M2!$A:$A, $A28, bs_30M2!$CJ:$CJ, ">=" & MATCH(Simulador!$B27, {"A1";"A2";"B1";"B2";"B3";"C1";"C2";"D1";"D2";"E1"}, 0))) | H28: =IF(Simulador!$B27="", "", SUMIFS(bs_30M2!$AK:$AK, bs_30M2!$A:$A, $A28) - SUMIFS(bs_30M2!$AK:$AK, bs_30M2!$A:$A, $A28, bs_30M2!$CJ:$CJ, ">=" & MATCH(Simulador!$B27, {"A1";"A2";"B1";"B2";"B3";"C1";"C2";"D1";"D2";"E1"}, 0))) | I28: =IF(Simulador!$B27="", "", SUMIFS(bs_30M3!$AQ:$AQ, bs_30M3!$A:$A, $A28) - SUMIFS(bs_30M3!$AQ:$AQ, bs_30M3!$A:$A, $A28, bs_30M3!$CJ:$CJ, ">=" & MATCH(Simulador!$B27, {"A1";"A2";"B1";"B2";"B3";"C1";"C2";"D1";"D2";"E1"}, 0))) | J28: =IF(Simulador!$B27="", "", SUMIFS(bs_30M3!$AL:$AL, bs_30M3!$A:$A, $A28) - SUMIFS(bs_30M3!$AL:$AL, bs_30M3!$A:$A, $A28, bs_30M3!$CJ:$CJ, ">=" & MATCH(Simulador!$B27, {"A1";"A2";"B1";"B2";"B3";"C1";"C2";"D1";"D2";"E1"}, 0))) | K28: =IF(Simulador!$B27="", "", SUMIFS(bs_60M6!$AR:$AR, bs_60M6!$A:$A, $A28) - SUMIFS(bs_60M6!$AR:$AR, bs_60M6!$A:$A, $A28, bs_60M6!$CJ:$CJ, ">=" & MATCH(Simulador!$B27, {"A1";"A2";"B1";"B2";"B3";"C1";"C2";"D1";"D2";"E1"}, 0))) | L28: =IF(Simulador!$B27="", "", SUMIFS(bs_60M6!$AM:$AM, bs_60M6!$A:$A, $A28) - SUMIFS(bs_60M6!$AM:$AM, bs_60M6!$A:$A, $A28, bs_60M6!$CJ:$CJ, ">=" & MATCH(Simulador!$B27, {"A1";"A2";"B1";"B2";"B3";"C1";"C2";"D1";"D2";"E1"}, 0))) | M28: =IFERROR(E28/F28,"") | N28: =IFERROR(G28/H28,"") | O28: =IFERROR(I28/J28,"") | P28: =IFERROR(K28/L28,"") | Q28: =IFERROR(C28/B28,"") | R28: =IFERROR(D28/C28,"") | S28: =IFERROR(_xlfn.XLOOKUP(A28,BS_CONSOLIDADO!A:A,BS_CONSOLIDADO!B:B,"")-B28,"") | T28: =IFERROR(_xlfn.XLOOKUP(A28,BS_CONSOLIDADO!A:A,BS_CONSOLIDADO!C:C,"")-C28,"") | U28: =IFERROR(_xlfn.XLOOKUP(A28,BS_CONSOLIDADO!A:A,BS_CONSOLIDADO!D:D)-D28,"") | V28: =IFERROR(_xlfn.XLOOKUP($A28,BS_CONSOLIDADO!$A:$A,BS_CONSOLIDADO!E:E,"")-E28,"") | W28: =IFERROR(_xlfn.XLOOKUP($A28,BS_CONSOLIDADO!$A:$A,BS_CONSOLIDADO!F:F,"")-F28,"") | X28: =IFERROR(_xlfn.XLOOKUP($A28,BS_CONSOLIDADO!A:A,BS_CONSOLIDADO!G:G,"")-G28,"") | Y28: =IFERROR(_xlfn.XLOOKUP($A28,BS_CONSOLIDADO!$A:$A,BS_CONSOLIDADO!H:H,"")-H28,"") | Z28: =IFERROR(_xlfn.XLOOKUP($A28,BS_CONSOLIDADO!$A:$A,BS_CONSOLIDADO!I:I,"")-I28,"") | AA28: =IFERROR(_xlfn.XLOOKUP($A28,BS_CONSOLIDADO!$A:$A,BS_CONSOLIDADO!J:J,"")-J28,"") | AB28: =IFERROR(_xlfn.XLOOKUP($A28,BS_CONSOLIDADO!$A:$A,BS_CONSOLIDADO!K:K,"")-K28,"") | AC28: =IFERROR(_xlfn.XLOOKUP($A28,BS_CONSOLIDADO!$A:$A,BS_CONSOLIDADO!L:L,"")-L28,"")
B29: =IF(Simulador!$B28="", "", SUMIFS(bs_propostas!$D:$D, bs_propostas!$A:$A, $A29)) | C29: =IF(Simulador!$B28="", "", SUMIFS(bs_propostas!$E:$E, bs_propostas!$A:$A, $A29) - SUMIFS(bs_propostas!$E:$E, bs_propostas!$A:$A, $A29, bs_propostas!$CJ:$CJ, ">=" & MATCH(Simulador!$B28, {"A1";"A2";"B1";"B2";"B3";"C1";"C2";"D1";"D2";"E1"}, 0))) | D29: =IF(Simulador!$B28="", "", SUMIFS(bs_propostas!$F:$F, bs_propostas!$A:$A, $A29) - SUMIFS(bs_propostas!$F:$F, bs_propostas!$A:$A, $A29, bs_propostas!$CJ:$CJ, ">=" & MATCH(Simulador!$B28, {"A1";"A2";"B1";"B2";"B3";"C1";"C2";"D1";"D2";"E1"}, 0))) | E29: =IF(Simulador!$B28="", "", SUMIFS(bs_30M2!$AN:$AN, bs_30M2!$A:$A, $A29) - SUMIFS(bs_30M2!$AN:$AN, bs_30M2!$A:$A, $A29, bs_30M2!$CJ:$CJ, ">=" & MATCH(Simulador!$B28, {"A1";"A2";"B1";"B2";"B3";"C1";"C2";"D1";"D2";"E1"}, 0))) | F29: =IF(Simulador!$B28="", "", SUMIFS(bs_30M2!$AI:$AI, bs_30M2!$A:$A, $A29) - SUMIFS(bs_30M2!$AI:$AI, bs_30M2!$A:$A, $A29, bs_30M2!$CJ:$CJ, ">=" & MATCH(Simulador!$B28, {"A1";"A2";"B1";"B2";"B3";"C1";"C2";"D1";"D2";"E1"}, 0))) | G29: =IF(Simulador!$B28="", "", SUMIFS(bs_30M2!$AP:$AP, bs_30M2!$A:$A, $A29) - SUMIFS(bs_30M2!$AP:$AP, bs_30M2!$A:$A, $A29, bs_30M2!$CJ:$CJ, ">=" & MATCH(Simulador!$B28, {"A1";"A2";"B1";"B2";"B3";"C1";"C2";"D1";"D2";"E1"}, 0))) | H29: =IF(Simulador!$B28="", "", SUMIFS(bs_30M2!$AK:$AK, bs_30M2!$A:$A, $A29) - SUMIFS(bs_30M2!$AK:$AK, bs_30M2!$A:$A, $A29, bs_30M2!$CJ:$CJ, ">=" & MATCH(Simulador!$B28, {"A1";"A2";"B1";"B2";"B3";"C1";"C2";"D1";"D2";"E1"}, 0))) | I29: =IF(Simulador!$B28="", "", SUMIFS(bs_30M3!$AQ:$AQ, bs_30M3!$A:$A, $A29) - SUMIFS(bs_30M3!$AQ:$AQ, bs_30M3!$A:$A, $A29, bs_30M3!$CJ:$CJ, ">=" & MATCH(Simulador!$B28, {"A1";"A2";"B1";"B2";"B3";"C1";"C2";"D1";"D2";"E1"}, 0))) | J29: =IF(Simulador!$B28="", "", SUMIFS(bs_30M3!$AL:$AL, bs_30M3!$A:$A, $A29) - SUMIFS(bs_30M3!$AL:$AL, bs_30M3!$A:$A, $A29, bs_30M3!$CJ:$CJ, ">=" & MATCH(Simulador!$B28, {"A1";"A2";"B1";"B2";"B3";"C1";"C2";"D1";"D2";"E1"}, 0))) | K29: =IF(Simulador!$B28="", "", SUMIFS(bs_60M6!$AR:$AR, bs_60M6!$A:$A, $A29) - SUMIFS(bs_60M6!$AR:$AR, bs_60M6!$A:$A, $A29, bs_60M6!$CJ:$CJ, ">=" & MATCH(Simulador!$B28, {"A1";"A2";"B1";"B2";"B3";"C1";"C2";"D1";"D2";"E1"}, 0))) | L29: =IF(Simulador!$B28="", "", SUMIFS(bs_60M6!$AM:$AM, bs_60M6!$A:$A, $A29) - SUMIFS(bs_60M6!$AM:$AM, bs_60M6!$A:$A, $A29, bs_60M6!$CJ:$CJ, ">=" & MATCH(Simulador!$B28, {"A1";"A2";"B1";"B2";"B3";"C1";"C2";"D1";"D2";"E1"}, 0))) | M29: =IFERROR(E29/F29,"") | N29: =IFERROR(G29/H29,"") | O29: =IFERROR(I29/J29,"") | P29: =IFERROR(K29/L29,"") | Q29: =IFERROR(C29/B29,"") | R29: =IFERROR(D29/C29,"") | S29: =IFERROR(_xlfn.XLOOKUP(A29,BS_CONSOLIDADO!A:A,BS_CONSOLIDADO!B:B,"")-B29,"") | T29: =IFERROR(_xlfn.XLOOKUP(A29,BS_CONSOLIDADO!A:A,BS_CONSOLIDADO!C:C,"")-C29,"") | U29: =IFERROR(_xlfn.XLOOKUP(A29,BS_CONSOLIDADO!A:A,BS_CONSOLIDADO!D:D)-D29,"") | V29: =IFERROR(_xlfn.XLOOKUP($A29,BS_CONSOLIDADO!$A:$A,BS_CONSOLIDADO!E:E,"")-E29,"") | W29: =IFERROR(_xlfn.XLOOKUP($A29,BS_CONSOLIDADO!$A:$A,BS_CONSOLIDADO!F:F,"")-F29,"") | X29: =IFERROR(_xlfn.XLOOKUP($A29,BS_CONSOLIDADO!A:A,BS_CONSOLIDADO!G:G,"")-G29,"") | Y29: =IFERROR(_xlfn.XLOOKUP($A29,BS_CONSOLIDADO!$A:$A,BS_CONSOLIDADO!H:H,"")-H29,"") | Z29: =IFERROR(_xlfn.XLOOKUP($A29,BS_CONSOLIDADO!$A:$A,BS_CONSOLIDADO!I:I,"")-I29,"") | AA29: =IFERROR(_xlfn.XLOOKUP($A29,BS_CONSOLIDADO!$A:$A,BS_CONSOLIDADO!J:J,"")-J29,"") | AB29: =IFERROR(_xlfn.XLOOKUP($A29,BS_CONSOLIDADO!$A:$A,BS_CONSOLIDADO!K:K,"")-K29,"") | AC29: =IFERROR(_xlfn.XLOOKUP($A29,BS_CONSOLIDADO!$A:$A,BS_CONSOLIDADO!L:L,"")-L29,"")
B30: =IF(Simulador!$B29="", "", SUMIFS(bs_propostas!$D:$D, bs_propostas!$A:$A, $A30)) | C30: =IF(Simulador!$B29="", "", SUMIFS(bs_propostas!$E:$E, bs_propostas!$A:$A, $A30) - SUMIFS(bs_propostas!$E:$E, bs_propostas!$A:$A, $A30, bs_propostas!$CJ:$CJ, ">=" & MATCH(Simulador!$B29, {"A1";"A2";"B1";"B2";"B3";"C1";"C2";"D1";"D2";"E1"}, 0))) | D30: =IF(Simulador!$B29="", "", SUMIFS(bs_propostas!$F:$F, bs_propostas!$A:$A, $A30) - SUMIFS(bs_propostas!$F:$F, bs_propostas!$A:$A, $A30, bs_propostas!$CJ:$CJ, ">=" & MATCH(Simulador!$B29, {"A1";"A2";"B1";"B2";"B3";"C1";"C2";"D1";"D2";"E1"}, 0))) | E30: =IF(Simulador!$B29="", "", SUMIFS(bs_30M2!$AN:$AN, bs_30M2!$A:$A, $A30) - SUMIFS(bs_30M2!$AN:$AN, bs_30M2!$A:$A, $A30, bs_30M2!$CJ:$CJ, ">=" & MATCH(Simulador!$B29, {"A1";"A2";"B1";"B2";"B3";"C1";"C2";"D1";"D2";"E1"}, 0))) | F30: =IF(Simulador!$B29="", "", SUMIFS(bs_30M2!$AI:$AI, bs_30M2!$A:$A, $A30) - SUMIFS(bs_30M2!$AI:$AI, bs_30M2!$A:$A, $A30, bs_30M2!$CJ:$CJ, ">=" & MATCH(Simulador!$B29, {"A1";"A2";"B1";"B2";"B3";"C1";"C2";"D1";"D2";"E1"}, 0))) | G30: =IF(Simulador!$B29="", "", SUMIFS(bs_30M2!$AP:$AP, bs_30M2!$A:$A, $A30) - SUMIFS(bs_30M2!$AP:$AP, bs_30M2!$A:$A, $A30, bs_30M2!$CJ:$CJ, ">=" & MATCH(Simulador!$B29, {"A1";"A2";"B1";"B2";"B3";"C1";"C2";"D1";"D2";"E1"}, 0))) | H30: =IF(Simulador!$B29="", "", SUMIFS(bs_30M2!$AK:$AK, bs_30M2!$A:$A, $A30) - SUMIFS(bs_30M2!$AK:$AK, bs_30M2!$A:$A, $A30, bs_30M2!$CJ:$CJ, ">=" & MATCH(Simulador!$B29, {"A1";"A2";"B1";"B2";"B3";"C1";"C2";"D1";"D2";"E1"}, 0))) | I30: =IF(Simulador!$B29="", "", SUMIFS(bs_30M3!$AQ:$AQ, bs_30M3!$A:$A, $A30) - SUMIFS(bs_30M3!$AQ:$AQ, bs_30M3!$A:$A, $A30, bs_30M3!$CJ:$CJ, ">=" & MATCH(Simulador!$B29, {"A1";"A2";"B1";"B2";"B3";"C1";"C2";"D1";"D2";"E1"}, 0))) | J30: =IF(Simulador!$B29="", "", SUMIFS(bs_30M3!$AL:$AL, bs_30M3!$A:$A, $A30) - SUMIFS(bs_30M3!$AL:$AL, bs_30M3!$A:$A, $A30, bs_30M3!$CJ:$CJ, ">=" & MATCH(Simulador!$B29, {"A1";"A2";"B1";"B2";"B3";"C1";"C2";"D1";"D2";"E1"}, 0))) | K30: =IF(Simulador!$B29="", "", SUMIFS(bs_60M6!$AR:$AR, bs_60M6!$A:$A, $A30) - SUMIFS(bs_60M6!$AR:$AR, bs_60M6!$A:$A, $A30, bs_60M6!$CJ:$CJ, ">=" & MATCH(Simulador!$B29, {"A1";"A2";"B1";"B2";"B3";"C1";"C2";"D1";"D2";"E1"}, 0))) | L30: =IF(Simulador!$B29="", "", SUMIFS(bs_60M6!$AM:$AM, bs_60M6!$A:$A, $A30) - SUMIFS(bs_60M6!$AM:$AM, bs_60M6!$A:$A, $A30, bs_60M6!$CJ:$CJ, ">=" & MATCH(Simulador!$B29, {"A1";"A2";"B1";"B2";"B3";"C1";"C2";"D1";"D2";"E1"}, 0))) | M30: =IFERROR(E30/F30,"") | N30: =IFERROR(G30/H30,"") | O30: =IFERROR(I30/J30,"") | P30: =IFERROR(K30/L30,"") | Q30: =IFERROR(C30/B30,"") | R30: =IFERROR(D30/C30,"") | S30: =IFERROR(_xlfn.XLOOKUP(A30,BS_CONSOLIDADO!A:A,BS_CONSOLIDADO!B:B,"")-B30,"") | T30: =IFERROR(_xlfn.XLOOKUP(A30,BS_CONSOLIDADO!A:A,BS_CONSOLIDADO!C:C,"")-C30,"") | U30: =IFERROR(_xlfn.XLOOKUP(A30,BS_CONSOLIDADO!A:A,BS_CONSOLIDADO!D:D)-D30,"") | V30: =IFERROR(_xlfn.XLOOKUP($A30,BS_CONSOLIDADO!$A:$A,BS_CONSOLIDADO!E:E,"")-E30,"") | W30: =IFERROR(_xlfn.XLOOKUP($A30,BS_CONSOLIDADO!$A:$A,BS_CONSOLIDADO!F:F,"")-F30,"") | X30: =IFERROR(_xlfn.XLOOKUP($A30,BS_CONSOLIDADO!A:A,BS_CONSOLIDADO!G:G,"")-G30,"") | Y30: =IFERROR(_xlfn.XLOOKUP($A30,BS_CONSOLIDADO!$A:$A,BS_CONSOLIDADO!H:H,"")-H30,"") | Z30: =IFERROR(_xlfn.XLOOKUP($A30,BS_CONSOLIDADO!$A:$A,BS_CONSOLIDADO!I:I,"")-I30,"") | AA30: =IFERROR(_xlfn.XLOOKUP($A30,BS_CONSOLIDADO!$A:$A,BS_CONSOLIDADO!J:J,"")-J30,"") | AB30: =IFERROR(_xlfn.XLOOKUP($A30,BS_CONSOLIDADO!$A:$A,BS_CONSOLIDADO!K:K,"")-K30,"") | AC30: =IFERROR(_xlfn.XLOOKUP($A30,BS_CONSOLIDADO!$A:$A,BS_CONSOLIDADO!L:L,"")-L30,"")
B31: =IF(Simulador!$B30="", "", SUMIFS(bs_propostas!$D:$D, bs_propostas!$A:$A, $A31)) | C31: =IF(Simulador!$B30="", "", SUMIFS(bs_propostas!$E:$E, bs_propostas!$A:$A, $A31) - SUMIFS(bs_propostas!$E:$E, bs_propostas!$A:$A, $A31, bs_propostas!$CJ:$CJ, ">=" & MATCH(Simulador!$B30, {"A1";"A2";"B1";"B2";"B3";"C1";"C2";"D1";"D2";"E1"}, 0))) | D31: =IF(Simulador!$B30="", "", SUMIFS(bs_propostas!$F:$F, bs_propostas!$A:$A, $A31) - SUMIFS(bs_propostas!$F:$F, bs_propostas!$A:$A, $A31, bs_propostas!$CJ:$CJ, ">=" & MATCH(Simulador!$B30, {"A1";"A2";"B1";"B2";"B3";"C1";"C2";"D1";"D2";"E1"}, 0))) | E31: =IF(Simulador!$B30="", "", SUMIFS(bs_30M2!$AN:$AN, bs_30M2!$A:$A, $A31) - SUMIFS(bs_30M2!$AN:$AN, bs_30M2!$A:$A, $A31, bs_30M2!$CJ:$CJ, ">=" & MATCH(Simulador!$B30, {"A1";"A2";"B1";"B2";"B3";"C1";"C2";"D1";"D2";"E1"}, 0))) | F31: =IF(Simulador!$B30="", "", SUMIFS(bs_30M2!$AI:$AI, bs_30M2!$A:$A, $A31) - SUMIFS(bs_30M2!$AI:$AI, bs_30M2!$A:$A, $A31, bs_30M2!$CJ:$CJ, ">=" & MATCH(Simulador!$B30, {"A1";"A2";"B1";"B2";"B3";"C1";"C2";"D1";"D2";"E1"}, 0))) | G31: =IF(Simulador!$B30="", "", SUMIFS(bs_30M2!$AP:$AP, bs_30M2!$A:$A, $A31) - SUMIFS(bs_30M2!$AP:$AP, bs_30M2!$A:$A, $A31, bs_30M2!$CJ:$CJ, ">=" & MATCH(Simulador!$B30, {"A1";"A2";"B1";"B2";"B3";"C1";"C2";"D1";"D2";"E1"}, 0))) | H31: =IF(Simulador!$B30="", "", SUMIFS(bs_30M2!$AK:$AK, bs_30M2!$A:$A, $A31) - SUMIFS(bs_30M2!$AK:$AK, bs_30M2!$A:$A, $A31, bs_30M2!$CJ:$CJ, ">=" & MATCH(Simulador!$B30, {"A1";"A2";"B1";"B2";"B3";"C1";"C2";"D1";"D2";"E1"}, 0))) | I31: =IF(Simulador!$B30="", "", SUMIFS(bs_30M3!$AQ:$AQ, bs_30M3!$A:$A, $A31) - SUMIFS(bs_30M3!$AQ:$AQ, bs_30M3!$A:$A, $A31, bs_30M3!$CJ:$CJ, ">=" & MATCH(Simulador!$B30, {"A1";"A2";"B1";"B2";"B3";"C1";"C2";"D1";"D2";"E1"}, 0))) | J31: =IF(Simulador!$B30="", "", SUMIFS(bs_30M3!$AL:$AL, bs_30M3!$A:$A, $A31) - SUMIFS(bs_30M3!$AL:$AL, bs_30M3!$A:$A, $A31, bs_30M3!$CJ:$CJ, ">=" & MATCH(Simulador!$B30, {"A1";"A2";"B1";"B2";"B3";"C1";"C2";"D1";"D2";"E1"}, 0))) | K31: =IF(Simulador!$B30="", "", SUMIFS(bs_60M6!$AR:$AR, bs_60M6!$A:$A, $A31) - SUMIFS(bs_60M6!$AR:$AR, bs_60M6!$A:$A, $A31, bs_60M6!$CJ:$CJ, ">=" & MATCH(Simulador!$B30, {"A1";"A2";"B1";"B2";"B3";"C1";"C2";"D1";"D2";"E1"}, 0))) | L31: =IF(Simulador!$B30="", "", SUMIFS(bs_60M6!$AM:$AM, bs_60M6!$A:$A, $A31) - SUMIFS(bs_60M6!$AM:$AM, bs_60M6!$A:$A, $A31, bs_60M6!$CJ:$CJ, ">=" & MATCH(Simulador!$B30, {"A1";"A2";"B1";"B2";"B3";"C1";"C2";"D1";"D2";"E1"}, 0))) | M31: =IFERROR(E31/F31,"") | N31: =IFERROR(G31/H31,"") | O31: =IFERROR(I31/J31,"") | P31: =IFERROR(K31/L31,"") | Q31: =IFERROR(C31/B31,"") | R31: =IFERROR(D31/C31,"") | S31: =IFERROR(_xlfn.XLOOKUP(A31,BS_CONSOLIDADO!A:A,BS_CONSOLIDADO!B:B,"")-B31,"") | T31: =IFERROR(_xlfn.XLOOKUP(A31,BS_CONSOLIDADO!A:A,BS_CONSOLIDADO!C:C,"")-C31,"") | U31: =IFERROR(_xlfn.XLOOKUP(A31,BS_CONSOLIDADO!A:A,BS_CONSOLIDADO!D:D)-D31,"") | V31: =IFERROR(_xlfn.XLOOKUP($A31,BS_CONSOLIDADO!$A:$A,BS_CONSOLIDADO!E:E,"")-E31,"") | W31: =IFERROR(_xlfn.XLOOKUP($A31,BS_CONSOLIDADO!$A:$A,BS_CONSOLIDADO!F:F,"")-F31,"") | X31: =IFERROR(_xlfn.XLOOKUP($A31,BS_CONSOLIDADO!A:A,BS_CONSOLIDADO!G:G,"")-G31,"") | Y31: =IFERROR(_xlfn.XLOOKUP($A31,BS_CONSOLIDADO!$A:$A,BS_CONSOLIDADO!H:H,"")-H31,"") | Z31: =IFERROR(_xlfn.XLOOKUP($A31,BS_CONSOLIDADO!$A:$A,BS_CONSOLIDADO!I:I,"")-I31,"") | AA31: =IFERROR(_xlfn.XLOOKUP($A31,BS_CONSOLIDADO!$A:$A,BS_CONSOLIDADO!J:J,"")-J31,"") | AB31: =IFERROR(_xlfn.XLOOKUP($A31,BS_CONSOLIDADO!$A:$A,BS_CONSOLIDADO!K:K,"")-K31,"") | AC31: =IFERROR(_xlfn.XLOOKUP($A31,BS_CONSOLIDADO!$A:$A,BS_CONSOLIDADO!L:L,"")-L31,"")
B32: =IF(Simulador!$B31="", "", SUMIFS(bs_propostas!$D:$D, bs_propostas!$A:$A, $A32)) | C32: =IF(Simulador!$B31="", "", SUMIFS(bs_propostas!$E:$E, bs_propostas!$A:$A, $A32) - SUMIFS(bs_propostas!$E:$E, bs_propostas!$A:$A, $A32, bs_propostas!$CJ:$CJ, ">=" & MATCH(Simulador!$B31, {"A1";"A2";"B1";"B2";"B3";"C1";"C2";"D1";"D2";"E1"}, 0))) | D32: =IF(Simulador!$B31="", "", SUMIFS(bs_propostas!$F:$F, bs_propostas!$A:$A, $A32) - SUMIFS(bs_propostas!$F:$F, bs_propostas!$A:$A, $A32, bs_propostas!$CJ:$CJ, ">=" & MATCH(Simulador!$B31, {"A1";"A2";"B1";"B2";"B3";"C1";"C2";"D1";"D2";"E1"}, 0))) | E32: =IF(Simulador!$B31="", "", SUMIFS(bs_30M2!$AN:$AN, bs_30M2!$A:$A, $A32) - SUMIFS(bs_30M2!$AN:$AN, bs_30M2!$A:$A, $A32, bs_30M2!$CJ:$CJ, ">=" & MATCH(Simulador!$B31, {"A1";"A2";"B1";"B2";"B3";"C1";"C2";"D1";"D2";"E1"}, 0))) | F32: =IF(Simulador!$B31="", "", SUMIFS(bs_30M2!$AI:$AI, bs_30M2!$A:$A, $A32) - SUMIFS(bs_30M2!$AI:$AI, bs_30M2!$A:$A, $A32, bs_30M2!$CJ:$CJ, ">=" & MATCH(Simulador!$B31, {"A1";"A2";"B1";"B2";"B3";"C1";"C2";"D1";"D2";"E1"}, 0))) | G32: =IF(Simulador!$B31="", "", SUMIFS(bs_30M2!$AP:$AP, bs_30M2!$A:$A, $A32) - SUMIFS(bs_30M2!$AP:$AP, bs_30M2!$A:$A, $A32, bs_30M2!$CJ:$CJ, ">=" & MATCH(Simulador!$B31, {"A1";"A2";"B1";"B2";"B3";"C1";"C2";"D1";"D2";"E1"}, 0))) | H32: =IF(Simulador!$B31="", "", SUMIFS(bs_30M2!$AK:$AK, bs_30M2!$A:$A, $A32) - SUMIFS(bs_30M2!$AK:$AK, bs_30M2!$A:$A, $A32, bs_30M2!$CJ:$CJ, ">=" & MATCH(Simulador!$B31, {"A1";"A2";"B1";"B2";"B3";"C1";"C2";"D1";"D2";"E1"}, 0))) | I32: =IF(Simulador!$B31="", "", SUMIFS(bs_30M3!$AQ:$AQ, bs_30M3!$A:$A, $A32) - SUMIFS(bs_30M3!$AQ:$AQ, bs_30M3!$A:$A, $A32, bs_30M3!$CJ:$CJ, ">=" & MATCH(Simulador!$B31, {"A1";"A2";"B1";"B2";"B3";"C1";"C2";"D1";"D2";"E1"}, 0))) | J32: =IF(Simulador!$B31="", "", SUMIFS(bs_30M3!$AL:$AL, bs_30M3!$A:$A, $A32) - SUMIFS(bs_30M3!$AL:$AL, bs_30M3!$A:$A, $A32, bs_30M3!$CJ:$CJ, ">=" & MATCH(Simulador!$B31, {"A1";"A2";"B1";"B2";"B3";"C1";"C2";"D1";"D2";"E1"}, 0))) | K32: =IF(Simulador!$B31="", "", SUMIFS(bs_60M6!$AR:$AR, bs_60M6!$A:$A, $A32) - SUMIFS(bs_60M6!$AR:$AR, bs_60M6!$A:$A, $A32, bs_60M6!$CJ:$CJ, ">=" & MATCH(Simulador!$B31, {"A1";"A2";"B1";"B2";"B3";"C1";"C2";"D1";"D2";"E1"}, 0))) | L32: =IF(Simulador!$B31="", "", SUMIFS(bs_60M6!$AM:$AM, bs_60M6!$A:$A, $A32) - SUMIFS(bs_60M6!$AM:$AM, bs_60M6!$A:$A, $A32, bs_60M6!$CJ:$CJ, ">=" & MATCH(Simulador!$B31, {"A1";"A2";"B1";"B2";"B3";"C1";"C2";"D1";"D2";"E1"}, 0))) | M32: =IFERROR(E32/F32,"") | N32: =IFERROR(G32/H32,"") | O32: =IFERROR(I32/J32,"") | P32: =IFERROR(K32/L32,"") | Q32: =IFERROR(C32/B32,"") | R32: =IFERROR(D32/C32,"") | S32: =IFERROR(_xlfn.XLOOKUP(A32,BS_CONSOLIDADO!A:A,BS_CONSOLIDADO!B:B,"")-B32,"") | T32: =IFERROR(_xlfn.XLOOKUP(A32,BS_CONSOLIDADO!A:A,BS_CONSOLIDADO!C:C,"")-C32,"") | U32: =IFERROR(_xlfn.XLOOKUP(A32,BS_CONSOLIDADO!A:A,BS_CONSOLIDADO!D:D)-D32,"") | V32: =IFERROR(_xlfn.XLOOKUP($A32,BS_CONSOLIDADO!$A:$A,BS_CONSOLIDADO!E:E,"")-E32,"") | W32: =IFERROR(_xlfn.XLOOKUP($A32,BS_CONSOLIDADO!$A:$A,BS_CONSOLIDADO!F:F,"")-F32,"") | X32: =IFERROR(_xlfn.XLOOKUP($A32,BS_CONSOLIDADO!A:A,BS_CONSOLIDADO!G:G,"")-G32,"") | Y32: =IFERROR(_xlfn.XLOOKUP($A32,BS_CONSOLIDADO!$A:$A,BS_CONSOLIDADO!H:H,"")-H32,"") | Z32: =IFERROR(_xlfn.XLOOKUP($A32,BS_CONSOLIDADO!$A:$A,BS_CONSOLIDADO!I:I,"")-I32,"") | AA32: =IFERROR(_xlfn.XLOOKUP($A32,BS_CONSOLIDADO!$A:$A,BS_CONSOLIDADO!J:J,"")-J32,"") | AB32: =IFERROR(_xlfn.XLOOKUP($A32,BS_CONSOLIDADO!$A:$A,BS_CONSOLIDADO!K:K,"")-K32,"") | AC32: =IFERROR(_xlfn.XLOOKUP($A32,BS_CONSOLIDADO!$A:$A,BS_CONSOLIDADO!L:L,"")-L32,"")
B33: =IF(Simulador!$B32="", "", SUMIFS(bs_propostas!$D:$D, bs_propostas!$A:$A, $A33)) | C33: =IF(Simulador!$B32="", "", SUMIFS(bs_propostas!$E:$E, bs_propostas!$A:$A, $A33) - SUMIFS(bs_propostas!$E:$E, bs_propostas!$A:$A, $A33, bs_propostas!$CJ:$CJ, ">=" & MATCH(Simulador!$B32, {"A1";"A2";"B1";"B2";"B3";"C1";"C2";"D1";"D2";"E1"}, 0))) | D33: =IF(Simulador!$B32="", "", SUMIFS(bs_propostas!$F:$F, bs_propostas!$A:$A, $A33) - SUMIFS(bs_propostas!$F:$F, bs_propostas!$A:$A, $A33, bs_propostas!$CJ:$CJ, ">=" & MATCH(Simulador!$B32, {"A1";"A2";"B1";"B2";"B3";"C1";"C2";"D1";"D2";"E1"}, 0))) | E33: =IF(Simulador!$B32="", "", SUMIFS(bs_30M2!$AN:$AN, bs_30M2!$A:$A, $A33) - SUMIFS(bs_30M2!$AN:$AN, bs_30M2!$A:$A, $A33, bs_30M2!$CJ:$CJ, ">=" & MATCH(Simulador!$B32, {"A1";"A2";"B1";"B2";"B3";"C1";"C2";"D1";"D2";"E1"}, 0))) | F33: =IF(Simulador!$B32="", "", SUMIFS(bs_30M2!$AI:$AI, bs_30M2!$A:$A, $A33) - SUMIFS(bs_30M2!$AI:$AI, bs_30M2!$A:$A, $A33, bs_30M2!$CJ:$CJ, ">=" & MATCH(Simulador!$B32, {"A1";"A2";"B1";"B2";"B3";"C1";"C2";"D1";"D2";"E1"}, 0))) | G33: =IF(Simulador!$B32="", "", SUMIFS(bs_30M2!$AP:$AP, bs_30M2!$A:$A, $A33) - SUMIFS(bs_30M2!$AP:$AP, bs_30M2!$A:$A, $A33, bs_30M2!$CJ:$CJ, ">=" & MATCH(Simulador!$B32, {"A1";"A2";"B1";"B2";"B3";"C1";"C2";"D1";"D2";"E1"}, 0))) | H33: =IF(Simulador!$B32="", "", SUMIFS(bs_30M2!$AK:$AK, bs_30M2!$A:$A, $A33) - SUMIFS(bs_30M2!$AK:$AK, bs_30M2!$A:$A, $A33, bs_30M2!$CJ:$CJ, ">=" & MATCH(Simulador!$B32, {"A1";"A2";"B1";"B2";"B3";"C1";"C2";"D1";"D2";"E1"}, 0))) | I33: =IF(Simulador!$B32="", "", SUMIFS(bs_30M3!$AQ:$AQ, bs_30M3!$A:$A, $A33) - SUMIFS(bs_30M3!$AQ:$AQ, bs_30M3!$A:$A, $A33, bs_30M3!$CJ:$CJ, ">=" & MATCH(Simulador!$B32, {"A1";"A2";"B1";"B2";"B3";"C1";"C2";"D1";"D2";"E1"}, 0))) | J33: =IF(Simulador!$B32="", "", SUMIFS(bs_30M3!$AL:$AL, bs_30M3!$A:$A, $A33) - SUMIFS(bs_30M3!$AL:$AL, bs_30M3!$A:$A, $A33, bs_30M3!$CJ:$CJ, ">=" & MATCH(Simulador!$B32, {"A1";"A2";"B1";"B2";"B3";"C1";"C2";"D1";"D2";"E1"}, 0))) | K33: =IF(Simulador!$B32="", "", SUMIFS(bs_60M6!$AR:$AR, bs_60M6!$A:$A, $A33) - SUMIFS(bs_60M6!$AR:$AR, bs_60M6!$A:$A, $A33, bs_60M6!$CJ:$CJ, ">=" & MATCH(Simulador!$B32, {"A1";"A2";"B1";"B2";"B3";"C1";"C2";"D1";"D2";"E1"}, 0))) | L33: =IF(Simulador!$B32="", "", SUMIFS(bs_60M6!$AM:$AM, bs_60M6!$A:$A, $A33) - SUMIFS(bs_60M6!$AM:$AM, bs_60M6!$A:$A, $A33, bs_60M6!$CJ:$CJ, ">=" & MATCH(Simulador!$B32, {"A1";"A2";"B1";"B2";"B3";"C1";"C2";"D1";"D2";"E1"}, 0))) | M33: =IFERROR(E33/F33,"") | N33: =IFERROR(G33/H33,"") | O33: =IFERROR(I33/J33,"") | P33: =IFERROR(K33/L33,"") | Q33: =IFERROR(C33/B33,"") | R33: =IFERROR(D33/C33,"") | S33: =IFERROR(_xlfn.XLOOKUP(A33,BS_CONSOLIDADO!A:A,BS_CONSOLIDADO!B:B,"")-B33,"") | T33: =IFERROR(_xlfn.XLOOKUP(A33,BS_CONSOLIDADO!A:A,BS_CONSOLIDADO!C:C,"")-C33,"") | U33: =IFERROR(_xlfn.XLOOKUP(A33,BS_CONSOLIDADO!A:A,BS_CONSOLIDADO!D:D)-D33,"") | V33: =IFERROR(_xlfn.XLOOKUP($A33,BS_CONSOLIDADO!$A:$A,BS_CONSOLIDADO!E:E,"")-E33,"") | W33: =IFERROR(_xlfn.XLOOKUP($A33,BS_CONSOLIDADO!$A:$A,BS_CONSOLIDADO!F:F,"")-F33,"") | X33: =IFERROR(_xlfn.XLOOKUP($A33,BS_CONSOLIDADO!A:A,BS_CONSOLIDADO!G:G,"")-G33,"") | Y33: =IFERROR(_xlfn.XLOOKUP($A33,BS_CONSOLIDADO!$A:$A,BS_CONSOLIDADO!H:H,"")-H33,"") | Z33: =IFERROR(_xlfn.XLOOKUP($A33,BS_CONSOLIDADO!$A:$A,BS_CONSOLIDADO!I:I,"")-I33,"") | AA33: =IFERROR(_xlfn.XLOOKUP($A33,BS_CONSOLIDADO!$A:$A,BS_CONSOLIDADO!J:J,"")-J33,"") | AB33: =IFERROR(_xlfn.XLOOKUP($A33,BS_CONSOLIDADO!$A:$A,BS_CONSOLIDADO!K:K,"")-K33,"") | AC33: =IFERROR(_xlfn.XLOOKUP($A33,BS_CONSOLIDADO!$A:$A,BS_CONSOLIDADO!L:L,"")-L33,"")
B34: =IF(Simulador!$B33="", "", SUMIFS(bs_propostas!$D:$D, bs_propostas!$A:$A, $A34)) | C34: =IF(Simulador!$B33="", "", SUMIFS(bs_propostas!$E:$E, bs_propostas!$A:$A, $A34) - SUMIFS(bs_propostas!$E:$E, bs_propostas!$A:$A, $A34, bs_propostas!$CJ:$CJ, ">=" & MATCH(Simulador!$B33, {"A1";"A2";"B1";"B2";"B3";"C1";"C2";"D1";"D2";"E1"}, 0))) | D34: =IF(Simulador!$B33="", "", SUMIFS(bs_propostas!$F:$F, bs_propostas!$A:$A, $A34) - SUMIFS(bs_propostas!$F:$F, bs_propostas!$A:$A, $A34, bs_propostas!$CJ:$CJ, ">=" & MATCH(Simulador!$B33, {"A1";"A2";"B1";"B2";"B3";"C1";"C2";"D1";"D2";"E1"}, 0))) | E34: =IF(Simulador!$B33="", "", SUMIFS(bs_30M2!$AN:$AN, bs_30M2!$A:$A, $A34) - SUMIFS(bs_30M2!$AN:$AN, bs_30M2!$A:$A, $A34, bs_30M2!$CJ:$CJ, ">=" & MATCH(Simulador!$B33, {"A1";"A2";"B1";"B2";"B3";"C1";"C2";"D1";"D2";"E1"}, 0))) | F34: =IF(Simulador!$B33="", "", SUMIFS(bs_30M2!$AI:$AI, bs_30M2!$A:$A, $A34) - SUMIFS(bs_30M2!$AI:$AI, bs_30M2!$A:$A, $A34, bs_30M2!$CJ:$CJ, ">=" & MATCH(Simulador!$B33, {"A1";"A2";"B1";"B2";"B3";"C1";"C2";"D1";"D2";"E1"}, 0))) | G34: =IF(Simulador!$B33="", "", SUMIFS(bs_30M2!$AP:$AP, bs_30M2!$A:$A, $A34) - SUMIFS(bs_30M2!$AP:$AP, bs_30M2!$A:$A, $A34, bs_30M2!$CJ:$CJ, ">=" & MATCH(Simulador!$B33, {"A1";"A2";"B1";"B2";"B3";"C1";"C2";"D1";"D2";"E1"}, 0))) | H34: =IF(Simulador!$B33="", "", SUMIFS(bs_30M2!$AK:$AK, bs_30M2!$A:$A, $A34) - SUMIFS(bs_30M2!$AK:$AK, bs_30M2!$A:$A, $A34, bs_30M2!$CJ:$CJ, ">=" & MATCH(Simulador!$B33, {"A1";"A2";"B1";"B2";"B3";"C1";"C2";"D1";"D2";"E1"}, 0))) | I34: =IF(Simulador!$B33="", "", SUMIFS(bs_30M3!$AQ:$AQ, bs_30M3!$A:$A, $A34) - SUMIFS(bs_30M3!$AQ:$AQ, bs_30M3!$A:$A, $A34, bs_30M3!$CJ:$CJ, ">=" & MATCH(Simulador!$B33, {"A1";"A2";"B1";"B2";"B3";"C1";"C2";"D1";"D2";"E1"}, 0))) | J34: =IF(Simulador!$B33="", "", SUMIFS(bs_30M3!$AL:$AL, bs_30M3!$A:$A, $A34) - SUMIFS(bs_30M3!$AL:$AL, bs_30M3!$A:$A, $A34, bs_30M3!$CJ:$CJ, ">=" & MATCH(Simulador!$B33, {"A1";"A2";"B1";"B2";"B3";"C1";"C2";"D1";"D2";"E1"}, 0))) | K34: =IF(Simulador!$B33="", "", SUMIFS(bs_60M6!$AR:$AR, bs_60M6!$A:$A, $A34) - SUMIFS(bs_60M6!$AR:$AR, bs_60M6!$A:$A, $A34, bs_60M6!$CJ:$CJ, ">=" & MATCH(Simulador!$B33, {"A1";"A2";"B1";"B2";"B3";"C1";"C2";"D1";"D2";"E1"}, 0))) | L34: =IF(Simulador!$B33="", "", SUMIFS(bs_60M6!$AM:$AM, bs_60M6!$A:$A, $A34) - SUMIFS(bs_60M6!$AM:$AM, bs_60M6!$A:$A, $A34, bs_60M6!$CJ:$CJ, ">=" & MATCH(Simulador!$B33, {"A1";"A2";"B1";"B2";"B3";"C1";"C2";"D1";"D2";"E1"}, 0))) | M34: =IFERROR(E34/F34,"") | N34: =IFERROR(G34/H34,"") | O34: =IFERROR(I34/J34,"") | P34: =IFERROR(K34/L34,"") | Q34: =IFERROR(C34/B34,"") | R34: =IFERROR(D34/C34,"") | S34: =IFERROR(_xlfn.XLOOKUP(A34,BS_CONSOLIDADO!A:A,BS_CONSOLIDADO!B:B,"")-B34,"") | T34: =IFERROR(_xlfn.XLOOKUP(A34,BS_CONSOLIDADO!A:A,BS_CONSOLIDADO!C:C,"")-C34,"") | U34: =IFERROR(_xlfn.XLOOKUP(A34,BS_CONSOLIDADO!A:A,BS_CONSOLIDADO!D:D)-D34,"") | V34: =IFERROR(_xlfn.XLOOKUP($A34,BS_CONSOLIDADO!$A:$A,BS_CONSOLIDADO!E:E,"")-E34,"") | W34: =IFERROR(_xlfn.XLOOKUP($A34,BS_CONSOLIDADO!$A:$A,BS_CONSOLIDADO!F:F,"")-F34,"") | X34: =IFERROR(_xlfn.XLOOKUP($A34,BS_CONSOLIDADO!A:A,BS_CONSOLIDADO!G:G,"")-G34,"") | Y34: =IFERROR(_xlfn.XLOOKUP($A34,BS_CONSOLIDADO!$A:$A,BS_CONSOLIDADO!H:H,"")-H34,"") | Z34: =IFERROR(_xlfn.XLOOKUP($A34,BS_CONSOLIDADO!$A:$A,BS_CONSOLIDADO!I:I,"")-I34,"") | AA34: =IFERROR(_xlfn.XLOOKUP($A34,BS_CONSOLIDADO!$A:$A,BS_CONSOLIDADO!J:J,"")-J34,"") | AB34: =IFERROR(_xlfn.XLOOKUP($A34,BS_CONSOLIDADO!$A:$A,BS_CONSOLIDADO!K:K,"")-K34,"") | AC34: =IFERROR(_xlfn.XLOOKUP($A34,BS_CONSOLIDADO!$A:$A,BS_CONSOLIDADO!L:L,"")-L34,"")
B35: =IF(Simulador!$B34="", "", SUMIFS(bs_propostas!$D:$D, bs_propostas!$A:$A, $A35)) | C35: =IF(Simulador!$B34="", "", SUMIFS(bs_propostas!$E:$E, bs_propostas!$A:$A, $A35) - SUMIFS(bs_propostas!$E:$E, bs_propostas!$A:$A, $A35, bs_propostas!$CJ:$CJ, ">=" & MATCH(Simulador!$B34, {"A1";"A2";"B1";"B2";"B3";"C1";"C2";"D1";"D2";"E1"}, 0))) | D35: =IF(Simulador!$B34="", "", SUMIFS(bs_propostas!$F:$F, bs_propostas!$A:$A, $A35) - SUMIFS(bs_propostas!$F:$F, bs_propostas!$A:$A, $A35, bs_propostas!$CJ:$CJ, ">=" & MATCH(Simulador!$B34, {"A1";"A2";"B1";"B2";"B3";"C1";"C2";"D1";"D2";"E1"}, 0))) | E35: =IF(Simulador!$B34="", "", SUMIFS(bs_30M2!$AN:$AN, bs_30M2!$A:$A, $A35) - SUMIFS(bs_30M2!$AN:$AN, bs_30M2!$A:$A, $A35, bs_30M2!$CJ:$CJ, ">=" & MATCH(Simulador!$B34, {"A1";"A2";"B1";"B2";"B3";"C1";"C2";"D1";"D2";"E1"}, 0))) | F35: =IF(Simulador!$B34="", "", SUMIFS(bs_30M2!$AI:$AI, bs_30M2!$A:$A, $A35) - SUMIFS(bs_30M2!$AI:$AI, bs_30M2!$A:$A, $A35, bs_30M2!$CJ:$CJ, ">=" & MATCH(Simulador!$B34, {"A1";"A2";"B1";"B2";"B3";"C1";"C2";"D1";"D2";"E1"}, 0))) | G35: =IF(Simulador!$B34="", "", SUMIFS(bs_30M2!$AP:$AP, bs_30M2!$A:$A, $A35) - SUMIFS(bs_30M2!$AP:$AP, bs_30M2!$A:$A, $A35, bs_30M2!$CJ:$CJ, ">=" & MATCH(Simulador!$B34, {"A1";"A2";"B1";"B2";"B3";"C1";"C2";"D1";"D2";"E1"}, 0))) | H35: =IF(Simulador!$B34="", "", SUMIFS(bs_30M2!$AK:$AK, bs_30M2!$A:$A, $A35) - SUMIFS(bs_30M2!$AK:$AK, bs_30M2!$A:$A, $A35, bs_30M2!$CJ:$CJ, ">=" & MATCH(Simulador!$B34, {"A1";"A2";"B1";"B2";"B3";"C1";"C2";"D1";"D2";"E1"}, 0))) | I35: =IF(Simulador!$B34="", "", SUMIFS(bs_30M3!$AQ:$AQ, bs_30M3!$A:$A, $A35) - SUMIFS(bs_30M3!$AQ:$AQ, bs_30M3!$A:$A, $A35, bs_30M3!$CJ:$CJ, ">=" & MATCH(Simulador!$B34, {"A1";"A2";"B1";"B2";"B3";"C1";"C2";"D1";"D2";"E1"}, 0))) | J35: =IF(Simulador!$B34="", "", SUMIFS(bs_30M3!$AL:$AL, bs_30M3!$A:$A, $A35) - SUMIFS(bs_30M3!$AL:$AL, bs_30M3!$A:$A, $A35, bs_30M3!$CJ:$CJ, ">=" & MATCH(Simulador!$B34, {"A1";"A2";"B1";"B2";"B3";"C1";"C2";"D1";"D2";"E1"}, 0))) | K35: =IF(Simulador!$B34="", "", SUMIFS(bs_60M6!$AR:$AR, bs_60M6!$A:$A, $A35) - SUMIFS(bs_60M6!$AR:$AR, bs_60M6!$A:$A, $A35, bs_60M6!$CJ:$CJ, ">=" & MATCH(Simulador!$B34, {"A1";"A2";"B1";"B2";"B3";"C1";"C2";"D1";"D2";"E1"}, 0))) | L35: =IF(Simulador!$B34="", "", SUMIFS(bs_60M6!$AM:$AM, bs_60M6!$A:$A, $A35) - SUMIFS(bs_60M6!$AM:$AM, bs_60M6!$A:$A, $A35, bs_60M6!$CJ:$CJ, ">=" & MATCH(Simulador!$B34, {"A1";"A2";"B1";"B2";"B3";"C1";"C2";"D1";"D2";"E1"}, 0))) | M35: =IFERROR(E35/F35,"") | N35: =IFERROR(G35/H35,"") | O35: =IFERROR(I35/J35,"") | P35: =IFERROR(K35/L35,"") | Q35: =IFERROR(C35/B35,"") | R35: =IFERROR(D35/C35,"") | S35: =IFERROR(_xlfn.XLOOKUP(A35,BS_CONSOLIDADO!A:A,BS_CONSOLIDADO!B:B,"")-B35,"") | T35: =IFERROR(_xlfn.XLOOKUP(A35,BS_CONSOLIDADO!A:A,BS_CONSOLIDADO!C:C,"")-C35,"") | U35: =IFERROR(_xlfn.XLOOKUP(A35,BS_CONSOLIDADO!A:A,BS_CONSOLIDADO!D:D)-D35,"") | V35: =IFERROR(_xlfn.XLOOKUP($A35,BS_CONSOLIDADO!$A:$A,BS_CONSOLIDADO!E:E,"")-E35,"") | W35: =IFERROR(_xlfn.XLOOKUP($A35,BS_CONSOLIDADO!$A:$A,BS_CONSOLIDADO!F:F,"")-F35,"") | X35: =IFERROR(_xlfn.XLOOKUP($A35,BS_CONSOLIDADO!A:A,BS_CONSOLIDADO!G:G,"")-G35,"") | Y35: =IFERROR(_xlfn.XLOOKUP($A35,BS_CONSOLIDADO!$A:$A,BS_CONSOLIDADO!H:H,"")-H35,"") | Z35: =IFERROR(_xlfn.XLOOKUP($A35,BS_CONSOLIDADO!$A:$A,BS_CONSOLIDADO!I:I,"")-I35,"") | AA35: =IFERROR(_xlfn.XLOOKUP($A35,BS_CONSOLIDADO!$A:$A,BS_CONSOLIDADO!J:J,"")-J35,"") | AB35: =IFERROR(_xlfn.XLOOKUP($A35,BS_CONSOLIDADO!$A:$A,BS_CONSOLIDADO!K:K,"")-K35,"") | AC35: =IFERROR(_xlfn.XLOOKUP($A35,BS_CONSOLIDADO!$A:$A,BS_CONSOLIDADO!L:L,"")-L35,"")
